WORK/Verilog_modul_porownanie/porownanie_rtl.sv
/* Generated by Yosys 0.9 (git sha1 1979e0b) */

module porownanie_rtl(i_arg_A, i_arg_B, o_result);
  wire _000_;
  wire _001_;
  wire _002_;
  wire _003_;
  wire _004_;
  wire _005_;
  wire _006_;
  wire _007_;
  wire _008_;
  wire _009_;
  wire _010_;
  wire _011_;
  wire _012_;
  wire _013_;
  wire _014_;
  wire _015_;
  wire _016_;
  wire _017_;
  wire _018_;
  wire _019_;
  wire _020_;
  wire _021_;
  wire _022_;
  wire _023_;
  wire _024_;
  wire _025_;
  wire _026_;
  wire _027_;
  wire _028_;
  wire _029_;
  wire _030_;
  wire _031_;
  wire _032_;
  wire _033_;
  wire _034_;
  wire _035_;
  wire _036_;
  wire _037_;
  wire _038_;
  wire _039_;
  wire _040_;
  wire _041_;
  wire _042_;
  wire _043_;
  wire _044_;
  wire _045_;
  wire _046_;
  wire _047_;
  wire _048_;
  wire _049_;
  wire _050_;
  wire _051_;
  wire _052_;
  wire _053_;
  wire _054_;
  wire _055_;
  wire _056_;
  wire _057_;
  wire _058_;
  wire _059_;
  wire _060_;
  wire _061_;
  wire _062_;
  wire _063_;
  wire _064_;
  wire _065_;
  wire _066_;
  wire _067_;
  wire _068_;
  wire _069_;
  wire _070_;
  wire _071_;
  wire _072_;
  wire _073_;
  wire _074_;
  wire _075_;
  wire _076_;
  wire _077_;
  wire _078_;
  wire _079_;
  wire _080_;
  wire _081_;
  wire _082_;
  wire _083_;
  wire _084_;
  wire _085_;
  wire _086_;
  wire _087_;
  wire _088_;
  wire _089_;
  wire _090_;
  wire _091_;
  wire _092_;
  wire _093_;
  wire _094_;
  wire _095_;
  wire _096_;
  wire _097_;
  wire _098_;
  wire _099_;
  wire _100_;
  wire _101_;
  wire _102_;
  wire _103_;
  wire _104_;
  wire _105_;
  wire _106_;
  wire _107_;
  wire _108_;
  wire _109_;
  wire _110_;
  wire _111_;
  wire _112_;
  wire _113_;
  wire _114_;
  wire _115_;
  wire _116_;
  wire _117_;
  wire _118_;
  wire _119_;
  wire _120_;
  wire _121_;
  wire _122_;
  wire _123_;
  wire _124_;
  wire _125_;
  wire _126_;
  wire _127_;
  wire _128_;
  wire _129_;
  wire _130_;
  wire _131_;
  wire _132_;
  wire _133_;
  wire _134_;
  wire _135_;
  wire _136_;
  wire _137_;
  wire _138_;
  wire _139_;
  wire _140_;
  wire _141_;
  wire _142_;
  wire _143_;
  wire _144_;
  wire _145_;
  wire _146_;
  wire _147_;
  wire _148_;
  wire _149_;
  wire _150_;
  wire _151_;
  wire _152_;
  wire _153_;
  wire _154_;
  wire _155_;
  wire _156_;
  wire _157_;
  wire _158_;
  wire _159_;
  wire _160_;
  wire _161_;
  wire _162_;
  wire _163_;
  wire _164_;
  wire _165_;
  wire _166_;
  wire _167_;
  wire _168_;
  wire _169_;
  wire _170_;
  wire _171_;
  wire _172_;
  wire _173_;
  wire _174_;
  wire _175_;
  wire _176_;
  wire _177_;
  wire _178_;
  input [31:0] i_arg_A;
  input [31:0] i_arg_B;
  output o_result;
  assign _136_ = _108_ | _135_;
  assign _137_ = ~_136_;
  assign _138_ = _111_ & _137_;
  assign _139_ = _107_ & _138_;
  assign _140_ = _099_ & _139_;
  assign _141_ = _126_ & _140_;
  assign _142_ = _132_ & _141_;
  assign _143_ = _148_ | _142_;
  assign _144_ = ~_143_;
  assign o_result = _134_ & _144_;
  assign _145_ = ~i_arg_B[31];
  assign _146_ = i_arg_B[30] & i_arg_A[30];
  assign _147_ = ~_146_;
  assign _148_ = i_arg_B[31] & i_arg_A[31];
  assign _149_ = i_arg_B[31] ^ i_arg_A[31];
  assign _150_ = _145_ ^ i_arg_A[31];
  assign _151_ = _147_ & _149_;
  assign _152_ = _146_ | _150_;
  assign _153_ = i_arg_B[29] & i_arg_A[29];
  assign _154_ = i_arg_B[28] & i_arg_A[28];
  assign _155_ = _153_ | _154_;
  assign _156_ = ~_155_;
  assign _157_ = i_arg_B[28] | i_arg_A[28];
  assign _158_ = i_arg_B[29] | i_arg_A[29];
  assign _159_ = i_arg_B[30] | i_arg_A[30];
  assign _160_ = _158_ & _159_;
  assign _161_ = _157_ & _160_;
  assign _162_ = _156_ & _161_;
  assign _163_ = _151_ & _162_;
  assign _164_ = i_arg_B[27] & i_arg_A[27];
  assign _165_ = i_arg_B[26] & i_arg_A[26];
  assign _166_ = _164_ | _165_;
  assign _167_ = i_arg_B[27] | i_arg_A[27];
  assign _168_ = i_arg_B[27] ^ i_arg_A[27];
  assign _169_ = i_arg_B[26] ^ i_arg_A[26];
  assign _170_ = _168_ & _169_;
  assign _171_ = i_arg_B[25] & i_arg_A[25];
  assign _172_ = i_arg_B[24] & i_arg_A[24];
  assign _173_ = _171_ | _172_;
  assign _174_ = i_arg_B[25] | i_arg_A[25];
  assign _175_ = i_arg_B[24] ^ i_arg_A[24];
  assign _176_ = i_arg_B[25] ^ i_arg_A[25];
  assign _177_ = _170_ & _176_;
  assign _178_ = _163_ & _177_;
  assign _000_ = _175_ & _178_;
  assign _001_ = i_arg_B[17] & i_arg_A[17];
  assign _002_ = i_arg_B[16] & i_arg_A[16];
  assign _003_ = _001_ | _002_;
  assign _004_ = ~_003_;
  assign _005_ = i_arg_B[23] & i_arg_A[23];
  assign _006_ = i_arg_B[22] & i_arg_A[22];
  assign _007_ = _005_ | _006_;
  assign _008_ = i_arg_B[23] | i_arg_A[23];
  assign _009_ = i_arg_B[23] ^ i_arg_A[23];
  assign _010_ = i_arg_B[22] ^ i_arg_A[22];
  assign _011_ = _009_ & _010_;
  assign _012_ = i_arg_B[21] & i_arg_A[21];
  assign _013_ = i_arg_B[20] & i_arg_A[20];
  assign _014_ = _012_ | _013_;
  assign _015_ = i_arg_B[21] | i_arg_A[21];
  assign _016_ = i_arg_B[20] ^ i_arg_A[20];
  assign _017_ = i_arg_B[21] ^ i_arg_A[21];
  assign _018_ = _011_ & _017_;
  assign _019_ = _016_ & _018_;
  assign _020_ = i_arg_B[19] & i_arg_A[19];
  assign _021_ = i_arg_B[18] & i_arg_A[18];
  assign _022_ = i_arg_B[19] | i_arg_A[19];
  assign _023_ = i_arg_B[17] | i_arg_A[17];
  assign _024_ = i_arg_B[18] ^ i_arg_A[18];
  assign _025_ = i_arg_B[19] ^ i_arg_A[19];
  assign _026_ = _024_ & _025_;
  assign _027_ = _023_ & _026_;
  assign _028_ = _019_ & _027_;
  assign _029_ = _003_ & _028_;
  assign _030_ = _007_ & _008_;
  assign _031_ = _014_ & _015_;
  assign _032_ = _011_ & _031_;
  assign _033_ = _030_ | _032_;
  assign _034_ = _021_ & _022_;
  assign _035_ = _020_ | _034_;
  assign _036_ = _019_ & _035_;
  assign _037_ = _033_ | _036_;
  assign _038_ = _029_ | _037_;
  assign _039_ = _000_ & _038_;
  assign _040_ = _166_ & _167_;
  assign _041_ = _173_ & _174_;
  assign _042_ = _170_ & _041_;
  assign _043_ = _040_ | _042_;
  assign _044_ = _163_ & _043_;
  assign _045_ = _155_ & _160_;
  assign _046_ = _152_ | _045_;
  assign _047_ = _044_ | _046_;
  assign _048_ = _039_ | _047_;
  assign _049_ = i_arg_B[15] | i_arg_A[15];
  assign _050_ = i_arg_B[14] & i_arg_A[14];
  assign _051_ = i_arg_B[15] & i_arg_A[15];
  assign _052_ = i_arg_B[15] ^ i_arg_A[15];
  assign _053_ = i_arg_B[14] ^ i_arg_A[14];
  assign _054_ = _052_ & _053_;
  assign _055_ = i_arg_B[12] & i_arg_A[12];
  assign _056_ = i_arg_B[13] & i_arg_A[13];
  assign _057_ = _055_ | _056_;
  assign _058_ = i_arg_B[13] | i_arg_A[13];
  assign _059_ = i_arg_B[12] ^ i_arg_A[12];
  assign _060_ = i_arg_B[13] ^ i_arg_A[13];
  assign _061_ = _054_ & _060_;
  assign _062_ = _059_ & _061_;
  assign _063_ = i_arg_B[11] | i_arg_A[11];
  assign _064_ = i_arg_B[11] & i_arg_A[11];
  assign _065_ = i_arg_B[10] & i_arg_A[10];
  assign _066_ = _064_ | _065_;
  assign _067_ = _063_ & _066_;
  assign _068_ = i_arg_B[11] ^ i_arg_A[11];
  assign _069_ = i_arg_B[10] ^ i_arg_A[10];
  assign _070_ = _068_ & _069_;
  assign _071_ = i_arg_B[9] | i_arg_A[9];
  assign _072_ = i_arg_B[9] & i_arg_A[9];
  assign _073_ = i_arg_B[8] & i_arg_A[8];
  assign _074_ = _072_ | _073_;
  assign _075_ = ~_074_;
  assign _076_ = _071_ & _074_;
  assign _077_ = _070_ & _076_;
  assign _078_ = _067_ | _077_;
  assign _079_ = _062_ & _078_;
  assign _080_ = _050_ | _051_;
  assign _081_ = _049_ & _080_;
  assign _082_ = _057_ & _058_;
  assign _083_ = _054_ & _082_;
  assign _084_ = _081_ | _083_;
  assign _085_ = _079_ | _084_;
  assign _086_ = i_arg_B[7] | i_arg_A[7];
  assign _087_ = i_arg_B[6] & i_arg_A[6];
  assign _088_ = i_arg_B[7] & i_arg_A[7];
  assign _089_ = i_arg_B[7] ^ i_arg_A[7];
  assign _090_ = i_arg_B[6] ^ i_arg_A[6];
  assign _091_ = _089_ & _090_;
  assign _092_ = i_arg_B[4] & i_arg_A[4];
  assign _093_ = i_arg_B[5] & i_arg_A[5];
  assign _094_ = _092_ | _093_;
  assign _095_ = i_arg_B[5] | i_arg_A[5];
  assign _096_ = i_arg_B[4] ^ i_arg_A[4];
  assign _097_ = i_arg_B[5] ^ i_arg_A[5];
  assign _098_ = _091_ & _097_;
  assign _099_ = _096_ & _098_;
  assign _100_ = i_arg_B[3] & i_arg_A[3];
  assign _101_ = i_arg_B[3] | i_arg_A[3];
  assign _102_ = i_arg_B[2] & i_arg_A[2];
  assign _103_ = _101_ & _102_;
  assign _104_ = _100_ | _103_;
  assign _105_ = i_arg_B[3] ^ i_arg_A[3];
  assign _106_ = i_arg_B[2] ^ i_arg_A[2];
  assign _107_ = _105_ & _106_;
  assign _108_ = i_arg_B[1] & i_arg_A[1];
  assign _109_ = i_arg_B[0] | i_arg_A[0];
  assign _110_ = i_arg_B[1] | i_arg_A[1];
  assign _111_ = _109_ & _110_;
  assign _112_ = _108_ | _111_;
  assign _113_ = _107_ & _112_;
  assign _114_ = _104_ | _113_;
  assign _115_ = _099_ & _114_;
  assign _116_ = _094_ & _095_;
  assign _117_ = _091_ & _116_;
  assign _118_ = _086_ & _087_;
  assign _119_ = _088_ | _118_;
  assign _120_ = _117_ | _119_;
  assign _121_ = _115_ | _120_;
  assign _122_ = i_arg_B[8] | i_arg_A[8];
  assign _123_ = _071_ & _122_;
  assign _124_ = _075_ & _123_;
  assign _125_ = _070_ & _124_;
  assign _126_ = _062_ & _125_;
  assign _127_ = _121_ & _126_;
  assign _128_ = _085_ | _127_;
  assign _129_ = i_arg_B[16] | i_arg_A[16];
  assign _130_ = _004_ & _129_;
  assign _131_ = _028_ & _130_;
  assign _132_ = _000_ & _131_;
  assign _133_ = _128_ & _132_;
  assign _134_ = _048_ | _133_;
  assign _135_ = i_arg_B[0] & i_arg_A[0];
endmodule

WORK/Verilog_modul_porownanie/porownanie.sv
//moduł porównania wartości sygnałów wejściowych A i B

module porownanie (i_arg_A, i_arg_B, o_result);
    parameter BITS = 32;

    //deklarowanie wejść i wyjść
    input logic [BITS-1:0] i_arg_A;
    input logic [BITS-1:0] i_arg_B;
    output logic o_result;

    //blok opisujący logikę
    always_comb 
    begin
        //defaultowe zerowanie wyjścia
        o_result = 0;
        //zaczynamy porównywanie

        if (i_arg_A > (~i_arg_B)) begin
            o_result = 1;
        end

        else begin
            o_result = 0;
        end
    end
endmodule

WORK/Verilog_modul_porownanie/porownanie_tb.sv
//testbench modułu porowananie.sv
//wstępnie przewidziany bez żadnych błędów ani przepełnienia w środku

module porownanie_tb;

parameter BITS=32;

// sygnały wewnętrzne
logic [BITS-1:0] s_i_arg_A;
logic [BITS-1:0] s_i_arg_B;
logic  s_o_model;
logic  s_o_synthesis;

// instancjowanie wejść i wyjść, jawne przypisywanie portów

porownanie     #(.BITS(BITS))        
porownanie     (
    .i_arg_A(s_i_arg_A), 
    .i_arg_B(s_i_arg_B), 
    .o_result(s_o_model)
    );    

porownanie_rtl           
Porownanie_rtl (
    .i_arg_A(s_i_arg_A), 
    .i_arg_B(s_i_arg_B), 
    .o_result(s_o_synthesis)
    );    

// Dostarczenie zmiennych do testu, rozpoczęcie bloku initial
initial 
begin
    //w tym pliku zostaną zapisane zapisane sygnały zarejestrowane w symulacji
        $dumpfile("signals_porownanie.vcd");  

        //Wskazania, że wszystkie sygnały z testbencha i niżej mają być rejestrowane podczas symulacji
        $dumpvars(0, porownanie_tb);   

        //początkowe wyzerowanie wartości sygnałów A i B
        s_i_arg_A = 0;
        s_i_arg_B = 0;      
        #1

                // Pętla for przypisująca losowe wartości argumentom wejścia dla pięciu iteracji, rozpoczęcie symulacji
        for (int i=0; i<=10; i++) begin
            #1
            s_i_arg_A = $urandom;
            s_i_arg_B = $urandom;
        end
        
        #1 
        s_i_arg_A = '0;
        s_i_arg_B = '0;
        #1
        s_i_arg_B = {1'b1, '0};
        #1
        s_i_arg_A = {1'b1, '0};
        #1
        s_i_arg_B = '0;
end
endmodule

WORK/Verilog_modul_porownanie/signals_porownanie.vcd
$date
	Tue Nov 28 00:44:58 2023
$end
$version
	Icarus Verilog
$end
$timescale
	1s
$end
$scope module porownanie_tb $end
$var wire 1 ! s_o_synthesis $end
$var wire 1 " s_o_model $end
$var reg 32 # s_i_arg_A [31:0] $end
$var reg 32 $ s_i_arg_B [31:0] $end
$scope module Porownanie_rtl $end
$var wire 1 % _000_ $end
$var wire 1 & _001_ $end
$var wire 1 ' _002_ $end
$var wire 1 ( _003_ $end
$var wire 1 ) _004_ $end
$var wire 1 * _005_ $end
$var wire 1 + _006_ $end
$var wire 1 , _007_ $end
$var wire 1 - _008_ $end
$var wire 1 . _009_ $end
$var wire 1 / _010_ $end
$var wire 1 0 _011_ $end
$var wire 1 1 _012_ $end
$var wire 1 2 _013_ $end
$var wire 1 3 _014_ $end
$var wire 1 4 _015_ $end
$var wire 1 5 _016_ $end
$var wire 1 6 _017_ $end
$var wire 1 7 _018_ $end
$var wire 1 8 _019_ $end
$var wire 1 9 _020_ $end
$var wire 1 : _021_ $end
$var wire 1 ; _022_ $end
$var wire 1 < _023_ $end
$var wire 1 = _024_ $end
$var wire 1 > _025_ $end
$var wire 1 ? _026_ $end
$var wire 1 @ _027_ $end
$var wire 1 A _028_ $end
$var wire 1 B _029_ $end
$var wire 1 C _030_ $end
$var wire 1 D _031_ $end
$var wire 1 E _032_ $end
$var wire 1 F _033_ $end
$var wire 1 G _034_ $end
$var wire 1 H _035_ $end
$var wire 1 I _036_ $end
$var wire 1 J _037_ $end
$var wire 1 K _038_ $end
$var wire 1 L _039_ $end
$var wire 1 M _040_ $end
$var wire 1 N _041_ $end
$var wire 1 O _042_ $end
$var wire 1 P _043_ $end
$var wire 1 Q _044_ $end
$var wire 1 R _045_ $end
$var wire 1 S _046_ $end
$var wire 1 T _047_ $end
$var wire 1 U _048_ $end
$var wire 1 V _049_ $end
$var wire 1 W _050_ $end
$var wire 1 X _051_ $end
$var wire 1 Y _052_ $end
$var wire 1 Z _053_ $end
$var wire 1 [ _054_ $end
$var wire 1 \ _055_ $end
$var wire 1 ] _056_ $end
$var wire 1 ^ _057_ $end
$var wire 1 _ _058_ $end
$var wire 1 ` _059_ $end
$var wire 1 a _060_ $end
$var wire 1 b _061_ $end
$var wire 1 c _062_ $end
$var wire 1 d _063_ $end
$var wire 1 e _064_ $end
$var wire 1 f _065_ $end
$var wire 1 g _066_ $end
$var wire 1 h _067_ $end
$var wire 1 i _068_ $end
$var wire 1 j _069_ $end
$var wire 1 k _070_ $end
$var wire 1 l _071_ $end
$var wire 1 m _072_ $end
$var wire 1 n _073_ $end
$var wire 1 o _074_ $end
$var wire 1 p _075_ $end
$var wire 1 q _076_ $end
$var wire 1 r _077_ $end
$var wire 1 s _078_ $end
$var wire 1 t _079_ $end
$var wire 1 u _080_ $end
$var wire 1 v _081_ $end
$var wire 1 w _082_ $end
$var wire 1 x _083_ $end
$var wire 1 y _084_ $end
$var wire 1 z _085_ $end
$var wire 1 { _086_ $end
$var wire 1 | _087_ $end
$var wire 1 } _088_ $end
$var wire 1 ~ _089_ $end
$var wire 1 !" _090_ $end
$var wire 1 "" _091_ $end
$var wire 1 #" _092_ $end
$var wire 1 $" _093_ $end
$var wire 1 %" _094_ $end
$var wire 1 &" _095_ $end
$var wire 1 '" _096_ $end
$var wire 1 (" _097_ $end
$var wire 1 )" _098_ $end
$var wire 1 *" _099_ $end
$var wire 1 +" _100_ $end
$var wire 1 ," _101_ $end
$var wire 1 -" _102_ $end
$var wire 1 ." _103_ $end
$var wire 1 /" _104_ $end
$var wire 1 0" _105_ $end
$var wire 1 1" _106_ $end
$var wire 1 2" _107_ $end
$var wire 1 3" _108_ $end
$var wire 1 4" _109_ $end
$var wire 1 5" _110_ $end
$var wire 1 6" _111_ $end
$var wire 1 7" _112_ $end
$var wire 1 8" _113_ $end
$var wire 1 9" _114_ $end
$var wire 1 :" _115_ $end
$var wire 1 ;" _116_ $end
$var wire 1 <" _117_ $end
$var wire 1 =" _118_ $end
$var wire 1 >" _119_ $end
$var wire 1 ?" _120_ $end
$var wire 1 @" _121_ $end
$var wire 1 A" _122_ $end
$var wire 1 B" _123_ $end
$var wire 1 C" _124_ $end
$var wire 1 D" _125_ $end
$var wire 1 E" _126_ $end
$var wire 1 F" _127_ $end
$var wire 1 G" _128_ $end
$var wire 1 H" _129_ $end
$var wire 1 I" _130_ $end
$var wire 1 J" _131_ $end
$var wire 1 K" _132_ $end
$var wire 1 L" _133_ $end
$var wire 1 M" _134_ $end
$var wire 1 N" _135_ $end
$var wire 1 O" _136_ $end
$var wire 1 P" _137_ $end
$var wire 1 Q" _138_ $end
$var wire 1 R" _139_ $end
$var wire 1 S" _140_ $end
$var wire 1 T" _141_ $end
$var wire 1 U" _142_ $end
$var wire 1 V" _143_ $end
$var wire 1 W" _144_ $end
$var wire 1 X" _145_ $end
$var wire 1 Y" _146_ $end
$var wire 1 Z" _147_ $end
$var wire 1 [" _148_ $end
$var wire 1 \" _149_ $end
$var wire 1 ]" _150_ $end
$var wire 1 ^" _151_ $end
$var wire 1 _" _152_ $end
$var wire 1 `" _153_ $end
$var wire 1 a" _154_ $end
$var wire 1 b" _155_ $end
$var wire 1 c" _156_ $end
$var wire 1 d" _157_ $end
$var wire 1 e" _158_ $end
$var wire 1 f" _159_ $end
$var wire 1 g" _160_ $end
$var wire 1 h" _161_ $end
$var wire 1 i" _162_ $end
$var wire 1 j" _163_ $end
$var wire 1 k" _164_ $end
$var wire 1 l" _165_ $end
$var wire 1 m" _166_ $end
$var wire 1 n" _167_ $end
$var wire 1 o" _168_ $end
$var wire 1 p" _169_ $end
$var wire 1 q" _170_ $end
$var wire 1 r" _171_ $end
$var wire 1 s" _172_ $end
$var wire 1 t" _173_ $end
$var wire 1 u" _174_ $end
$var wire 1 v" _175_ $end
$var wire 1 w" _176_ $end
$var wire 1 x" _177_ $end
$var wire 1 y" _178_ $end
$var wire 32 z" i_arg_A [31:0] $end
$var wire 32 {" i_arg_B [31:0] $end
$var wire 1 ! o_result $end
$upscope $end
$scope module porownanie $end
$var wire 32 |" i_arg_A [31:0] $end
$var wire 32 }" i_arg_B [31:0] $end
$var reg 1 " o_result $end
$upscope $end
$scope begin $ivl_for_loop0 $end
$var integer 32 ~" i [31:0] $end
$upscope $end
$upscope $end
$enddefinitions $end
#0
$dumpvars
b0 ~"
b0 }"
b0 |"
b0 {"
b0 z"
0y"
0x"
0w"
0v"
0u"
0t"
0s"
0r"
0q"
0p"
0o"
0n"
0m"
0l"
0k"
0j"
0i"
0h"
0g"
0f"
0e"
0d"
1c"
0b"
0a"
0`"
1_"
0^"
1]"
0\"
0["
1Z"
0Y"
1X"
1W"
0V"
0U"
0T"
0S"
0R"
0Q"
1P"
0O"
0N"
1M"
0L"
0K"
0J"
0I"
0H"
0G"
0F"
0E"
0D"
0C"
0B"
0A"
0@"
0?"
0>"
0="
0<"
0;"
0:"
09"
08"
07"
06"
05"
04"
03"
02"
01"
00"
0/"
0."
0-"
0,"
0+"
0*"
0)"
0("
0'"
0&"
0%"
0$"
0#"
0""
0!"
0~
0}
0|
0{
0z
0y
0x
0w
0v
0u
0t
0s
0r
0q
1p
0o
0n
0m
0l
0k
0j
0i
0h
0g
0f
0e
0d
0c
0b
0a
0`
0_
0^
0]
0\
0[
0Z
0Y
0X
0W
0V
1U
1T
1S
0R
0Q
0P
0O
0N
0M
0L
0K
0J
0I
0H
0G
0F
0E
0D
0C
0B
0A
0@
0?
0>
0=
0<
0;
0:
09
08
07
06
05
04
03
02
01
00
0/
0.
0-
0,
0+
0*
1)
0(
0'
0&
0%
b0 $
b0 #
1"
1!
$end
#2
0!
0M"
0U
0T
1s
0S
0)
1w
1C"
1h
1^"
0_"
1(
1?
1^
1g
1B"
0I"
1f"
1-
1.
1;
1>
1Z
1d
1i
1l
1{
1~
14"
1\"
0]"
1d"
1u"
1w"
1'
15
1=
1\
1_
1a
1f
1&"
1("
11"
1A"
1H"
0"
b1 ~"
b1000000100010010101111010000001 $
b1000000100010010101111010000001 {"
b1000000100010010101111010000001 }"
b10010010000101010011010100100100 #
b10010010000101010011010100100100 z"
b10010010000101010011010100100100 |"
#3
1!
1M"
1K
1U
1J
1G"
1T
1F
1z
0s
17"
1S
1)
1C
1y
0p
1q
0C"
0P"
0?
0h
16"
0^"
1_"
0(
1,
1v
1u
0w
1o
0B"
1O"
1e"
0f"
1v"
1/
14
16
0;
0>
0d
0i
0{
0~
1!"
15"
0\"
1]"
1p"
0u"
0w"
0'
1*
0.
1V
1W
1Y
0Z
0_
0a
1m
1,"
10"
01"
0A"
0H"
1N"
1"
b10 ~"
b110001111100000101011001100011 $
b110001111100000101011001100011 {"
b110001111100000101011001100011 }"
b100100001001101011000001001 #
b100100001001101011000001001 z"
b100100001001101011000001001 |"
#4
1M"
1U
0!
1T
0v
1b
19"
07"
0W"
1S
1N
0)
1D
1x
1s
1m"
0u
1[
1/"
06"
1V"
1_"
1t"
1(
13
1H
1w
1h
1."
1B"
0I"
0X"
0d"
0e"
1f"
1l"
0p"
0v"
1<
0W
1Z
0m
1{
1~
0!"
0&"
0("
1+"
00"
05"
1["
1]"
1r"
1u"
1'
12
05
19
1;
1_
1a
1d
1e
0f
1n
1-"
1A"
1H"
0"
b11 ~"
b11000110110111111001100110001101 $
b11000110110111111001100110001101 {"
b11000110110111111001100110001101 }"
b10000110101110010111101100001101 #
b10000110101110010111101100001101 z"
b10000110101110010111101100001101 |"
#5
0K
1M"
0G"
0J
1U
0z
0F
18
1!
1T
0y
0N
0C
17
17"
1Q"
1P"
1W"
1S
0D
0x
0s
1p
0q
09"
0t"
0,
10
16"
0O"
0V"
1_"
0m"
03
0H
0^
0w
0b
0h
0g
0o
0/"
0."
0B"
1X"
0f"
1n"
1o"
0r"
1v"
1w"
0*
1.
0{
0~
1'"
0-"
11"
15"
0N"
0["
1]"
1d"
1e"
0l"
1&
0'
02
15
09
0;
0\
0_
1`
0a
0d
0e
1j
0n
1!"
1&"
1("
0+"
0,"
0A"
1"
b100 ~"
b1001001101110101001000010010 $
b1001001101110101001000010010 {"
b1001001101110101001000010010 }"
b110010110000101000010001100101 #
b110010110000101000010001100101 z"
b110010110000101000010001100101 |"
#6
1K
1M"
1G"
1J
1U
1z
1F
1s
0!
1T
1y
1C
07
1r
0D"
07"
0Q"
0P"
0W"
1S
1D
1v
0p
1q
0C"
1,
00
1k
12"
06"
1O"
1V"
1_"
13
08
1u
0[
0b
1o
1B"
0X"
0n"
0o"
1p"
0v"
1*
1+
0.
0/
1X
0Y
0`
1d
1i
0'"
1,"
10"
05"
1N"
1["
1]"
0d"
0e"
1'
12
05
1W
0Z
1_
1a
1n
0!"
0&"
0("
1A"
0"
b101 ~"
b10000110110101111100110100001101 $
b10000110110101111100110100001101 {"
b10000110110101111100110100001101 }"
b10000000111100111110001100000001 #
b10000000111100111110001100000001 z"
b10000000111100111110001100000001 |"
#7
0K
0J
1P
0F
0s
19"
1@
0c"
1M
1N
0C
0D
0r
1;"
1/"
17"
1Q"
1P"
1?
1b"
1m"
1t"
0,
03
0q
0B"
1%"
1."
02"
16"
0O"
0&
1;
1>
1a"
1d"
1e"
1k"
1n"
1r"
1v"
0w"
0*
0+
1.
02
1`
0l
1!"
1#"
1$"
1&"
1-"
01"
15"
0N"
b110 ~"
b10011110100011011100110100111101 $
b10011110100011011100110100111101 {"
b10011110100011011100110100111101 }"
b10111011001000111111000101110110 #
b10111011001000111111000101110110 z"
b10111011001000111111000101110110 |"
#8
1K
1J
1I
1i"
1I"
18
1@"
1c"
1w
1h"
0P
1)
17
1H
1?"
0;"
07"
0Q"
0b"
1^
0Z"
1g"
0M
0(
10
1G
0@
0?
1g
0k
1q
1B"
1>"
0%"
06"
0a"
1\
0`
0d
0i
0$"
1("
1Y"
1f"
0k"
1l"
0n"
0p"
0v"
0'
1/
15
1:
0<
0=
0X
1Y
1f
0j
1l
1m
1{
1}
0#"
1+"
00"
05"
b111 ~"
b11000110001011011111011110001100 $
b11000110001011011111011110001100 {"
b11000110001011011111011110001100 }"
b11110110110101000101011111101101 #
b11110110110101000101011111101101 z"
b11110110110101000101011111101101 |"
#9
1K
1F
1!
0i"
1J
18"
1R"
0I"
1E
1W"
0c"
1R
0I
0v
1x
19"
17"
1Q"
0P
1x"
0N
0)
1D
1p
0]"
0V"
1b"
0m"
08
0u
1[
1="
0/"
16"
0M
1q"
0t"
1(
13
07
0g
1k
0q
0B"
0o
0."
12"
1X"
0["
1\"
1`"
0l"
1p"
1v"
12
05
1<
0W
1Z
0n
1|
0!"
0+"
10"
15"
1n"
1o"
0r"
1w"
1'
11
06
0\
1]
0a
1d
0f
1i
1j
0l
0m
1'"
0-"
11"
1"
b1000 ~"
b1100011001101110010010011000110 $
b1100011001101110010010011000110 {"
b1100011001101110010010011000110 }"
b11111100111111011110100111111001 #
b11111100111111011110100111111001 z"
b11111100111111011110100111111001 |"
#10
1i"
1c"
0R
1v
0x"
0H
0x
0b"
17
1u
0[
0="
0q"
0G
0^
0w
0k
0`"
01
16
0:
1=
1X
0Y
1`
1l
0|
1!"
0\"
1]"
0n"
0o"
1&
0;
0>
0]
0_
0d
0i
0'"
0A"
1"
b1001 ~"
b1010101000100111101001010101010 $
b1010101000100111101001010101010 {"
b1010101000100111101001010101010 }"
b1100010111101111000010011000101 #
b1100010111101111000010011000101 z"
b1100010111101111000010011000101 |"
#11
1@"
09"
0Q"
0i"
0B
1^"
1N
1C
07
0E
1?"
08"
0R"
0P"
0c"
1R
0D
0A
1@
1w
0p
1q
1;"
0C"
1Z"
1t"
1,
00
1="
1>"
02"
1O"
0_"
1b"
03
08
1?
1^
1o
1%"
1B"
0Y"
1`"
1n"
1o"
0p"
1r"
0w"
0'
1*
0.
0X
1Y
1|
0}
1~
0!"
1'"
0,"
1-"
00"
01"
1N"
1\"
0]"
1a"
02
15
1;
1>
1W
0Z
1\
1]
1_
0`
1m
1$"
0("
1A"
1"
b1010 ~"
b111011110100100111001001110111 $
b111011110100100111001001110111 {"
b111011110100100111001001110111 }"
b11110010101011111111011111100101 #
b11110010101011111111011111100101 z"
b11110010101011111111011111100101 |"
#12
0!
0M"
0U
1K
0T
1J
0@"
0S
1P
1E
1s
1F
0?"
19"
1x"
1O
1)
1D
1r
1c"
0R
0C
0>"
18"
1q"
0(
13
1k
0_"
0b"
0h"
0g"
0,
10
0w
0="
0%"
0;"
12"
0X"
1p"
0&
11
06
1X
0Y
1d
1i
1,"
10"
0]"
0`"
0a"
0d"
0e"
0r"
1s"
0v"
1w"
0*
1.
0]
0_
0|
0$"
0&"
0-"
11"
13"
0H"
0N"
0"
b1011 ~"
b11000111111011001101101110001111 $
b11000111111011001101101110001111 {"
b11000111111011001101101110001111 }"
b1001001100101101011000010010 #
b1001001100101101011000010010 z"
b1001001100101101011000010010 |"
#13
1!
1M"
1U
0K
1T
0J
0G"
1S
0P
0F
0z
0s
09"
1_"
0O
0E
0y
0r
1p
08"
1P"
1]"
0^"
0N
0x"
00
0?
02"
0q"
0t"
03
0D
0@
0v
0u
0^
0k
0q
0B"
0o
07"
0O"
06"
1X"
0\"
0f"
0p"
0u"
0w"
0-
0.
0/
0;
0=
0>
0d
0i
0{
0~
0,"
00"
01"
04"
0A"
0n"
0o"
0s"
01
04
05
0<
0V
0W
0X
0\
0j
0l
0m
0'"
03"
05"
1"
b0 $
b0 {"
b0 }"
b0 #
b0 z"
b0 |"
#14
15"
1"
b10 $
b10 {"
b10 }"
#15
0P"
17"
1O"
13"
1"
b10 #
b10 z"
b10 |"
#16
1P"
07"
0O"
03"
1"
b0 $
b0 {"
b0 }"
