WORK/Verilog_modul_porownanie/porownanie_rtl.sv
/* Generated by Yosys 0.36 (git sha1 8f07a0d8404, clang 14.0.0-1ubuntu1.1 -fPIC -Os) */

module porownanie_rtl(i_arg_A, i_arg_B, o_result);
  wire _000_;
  wire _001_;
  wire _002_;
  wire _003_;
  wire _004_;
  wire _005_;
  wire _006_;
  wire _007_;
  wire _008_;
  wire _009_;
  wire _010_;
  wire _011_;
  wire _012_;
  wire _013_;
  wire _014_;
  wire _015_;
  wire _016_;
  wire _017_;
  wire _018_;
  wire _019_;
  wire _020_;
  wire _021_;
  wire _022_;
  wire _023_;
  wire _024_;
  wire _025_;
  wire _026_;
  wire _027_;
  wire _028_;
  wire _029_;
  wire _030_;
  wire _031_;
  wire _032_;
  wire _033_;
  wire _034_;
  wire _035_;
  wire _036_;
  wire _037_;
  wire _038_;
  wire _039_;
  wire _040_;
  wire _041_;
  wire _042_;
  wire _043_;
  wire _044_;
  wire _045_;
  wire _046_;
  wire _047_;
  wire _048_;
  wire _049_;
  wire _050_;
  wire _051_;
  wire _052_;
  wire _053_;
  wire _054_;
  wire _055_;
  wire _056_;
  wire _057_;
  wire _058_;
  wire _059_;
  wire _060_;
  wire _061_;
  wire _062_;
  wire _063_;
  wire _064_;
  wire _065_;
  wire _066_;
  wire _067_;
  wire _068_;
  wire _069_;
  wire _070_;
  wire _071_;
  wire _072_;
  wire _073_;
  wire _074_;
  wire _075_;
  wire _076_;
  wire _077_;
  wire _078_;
  wire _079_;
  wire _080_;
  wire _081_;
  wire _082_;
  wire _083_;
  wire _084_;
  wire _085_;
  wire _086_;
  wire _087_;
  wire _088_;
  wire _089_;
  wire _090_;
  wire _091_;
  wire _092_;
  wire _093_;
  wire _094_;
  wire _095_;
  wire _096_;
  wire _097_;
  wire _098_;
  wire _099_;
  wire _100_;
  wire _101_;
  wire _102_;
  wire _103_;
  wire _104_;
  wire _105_;
  wire _106_;
  wire _107_;
  wire _108_;
  wire _109_;
  wire _110_;
  wire _111_;
  wire _112_;
  wire _113_;
  wire _114_;
  wire _115_;
  wire _116_;
  wire _117_;
  wire _118_;
  wire _119_;
  wire _120_;
  wire _121_;
  wire _122_;
  wire _123_;
  wire _124_;
  wire _125_;
  wire _126_;
  wire _127_;
  wire _128_;
  wire _129_;
  wire _130_;
  wire _131_;
  wire _132_;
  wire _133_;
  wire _134_;
  wire _135_;
  wire _136_;
  wire _137_;
  wire _138_;
  wire _139_;
  wire _140_;
  wire _141_;
  wire _142_;
  wire _143_;
  wire _144_;
  wire _145_;
  wire _146_;
  wire _147_;
  wire _148_;
  wire _149_;
  wire _150_;
  wire _151_;
  wire _152_;
  wire _153_;
  wire _154_;
  wire _155_;
  wire _156_;
  wire _157_;
  wire _158_;
  wire _159_;
  wire _160_;
  wire _161_;
  wire _162_;
  wire _163_;
  wire _164_;
  wire _165_;
  wire _166_;
  wire _167_;
  wire _168_;
  wire _169_;
  wire _170_;
  wire _171_;
  wire _172_;
  wire _173_;
  wire _174_;
  wire _175_;
  wire _176_;
  wire _177_;
  wire _178_;
  input [31:0] i_arg_A;
  wire [31:0] i_arg_A;
  input [31:0] i_arg_B;
  wire [31:0] i_arg_B;
  output o_result;
  wire o_result;
  assign _094_ = i_arg_B[5] & i_arg_A[5];
  assign _095_ = _093_ | _094_;
  assign _096_ = i_arg_B[5] | i_arg_A[5];
  assign _097_ = i_arg_B[4] ^ i_arg_A[4];
  assign _098_ = i_arg_B[5] ^ i_arg_A[5];
  assign _099_ = _092_ & _098_;
  assign _100_ = _097_ & _099_;
  assign _101_ = i_arg_B[3] & i_arg_A[3];
  assign _102_ = i_arg_B[2] & i_arg_A[2];
  assign _103_ = _101_ | _102_;
  assign _104_ = i_arg_B[3] | i_arg_A[3];
  assign _105_ = i_arg_B[3] ^ i_arg_A[3];
  assign _106_ = i_arg_B[2] ^ i_arg_A[2];
  assign _107_ = _105_ & _106_;
  assign _108_ = i_arg_B[1] & i_arg_A[1];
  assign _109_ = _107_ & _108_;
  assign _110_ = i_arg_B[0] | i_arg_A[0];
  assign _111_ = i_arg_B[1] ^ i_arg_A[1];
  assign _112_ = _110_ & _111_;
  assign _113_ = _107_ & _112_;
  assign _114_ = _103_ & _104_;
  assign _115_ = _109_ | _114_;
  assign _116_ = _113_ | _115_;
  assign _117_ = _100_ & _116_;
  assign _118_ = _088_ & _089_;
  assign _119_ = _095_ & _096_;
  assign _120_ = _092_ & _119_;
  assign _121_ = _118_ | _120_;
  assign _122_ = _117_ | _121_;
  assign _123_ = i_arg_B[8] ^ i_arg_A[8];
  assign _124_ = i_arg_B[9] ^ i_arg_A[9];
  assign _125_ = _072_ & _124_;
  assign _126_ = _064_ & _125_;
  assign _127_ = _123_ & _126_;
  assign _128_ = _122_ & _127_;
  assign _129_ = _085_ | _128_;
  assign _130_ = i_arg_B[16] | i_arg_A[16];
  assign _131_ = _002_ & _130_;
  assign _132_ = _026_ & _131_;
  assign _133_ = _177_ & _132_;
  assign _134_ = _129_ & _133_;
  assign _135_ = _049_ | _134_;
  assign _136_ = _148_ & _135_;
  assign _137_ = _146_ | _136_;
  assign _138_ = i_arg_B[0] & i_arg_A[0];
  assign _139_ = ~_138_;
  assign _140_ = _113_ & _139_;
  assign _141_ = _100_ & _140_;
  assign _142_ = _133_ & _141_;
  assign _143_ = _127_ & _142_;
  assign _144_ = ~_143_;
  assign o_result = _137_ & _144_;
  assign _145_ = i_arg_B[31] | i_arg_A[31];
  assign _146_ = ~_145_;
  assign _147_ = i_arg_B[31] & i_arg_A[31];
  assign _148_ = i_arg_B[31] ^ i_arg_A[31];
  assign _149_ = i_arg_B[29] | i_arg_A[29];
  assign _150_ = i_arg_B[30] & i_arg_A[30];
  assign _151_ = i_arg_B[30] ^ i_arg_A[30];
  assign _152_ = _148_ & _151_;
  assign _153_ = _149_ & _152_;
  assign _154_ = i_arg_B[29] & i_arg_A[29];
  assign _155_ = ~_154_;
  assign _156_ = i_arg_B[28] & i_arg_A[28];
  assign _157_ = _154_ | _156_;
  assign _158_ = i_arg_B[28] ^ i_arg_A[28];
  assign _159_ = _155_ & _158_;
  assign _160_ = _153_ & _159_;
  assign _161_ = i_arg_B[27] & i_arg_A[27];
  assign _162_ = i_arg_B[26] & i_arg_A[26];
  assign _163_ = _161_ | _162_;
  assign _164_ = i_arg_B[27] | i_arg_A[27];
  assign _165_ = i_arg_B[27] ^ i_arg_A[27];
  assign _166_ = i_arg_B[26] ^ i_arg_A[26];
  assign _167_ = _165_ & _166_;
  assign _168_ = i_arg_B[25] | i_arg_A[25];
  assign _169_ = i_arg_B[24] & i_arg_A[24];
  assign _170_ = ~_169_;
  assign _171_ = i_arg_B[25] & i_arg_A[25];
  assign _172_ = i_arg_B[24] | i_arg_A[24];
  assign _173_ = i_arg_B[25] ^ i_arg_A[25];
  assign _174_ = _167_ & _173_;
  assign _175_ = _172_ & _174_;
  assign _176_ = _170_ & _175_;
  assign _177_ = _160_ & _176_;
  assign _178_ = i_arg_B[17] & i_arg_A[17];
  assign _000_ = i_arg_B[16] & i_arg_A[16];
  assign _001_ = _178_ | _000_;
  assign _002_ = ~_001_;
  assign _003_ = i_arg_B[23] & i_arg_A[23];
  assign _004_ = i_arg_B[22] & i_arg_A[22];
  assign _005_ = _003_ | _004_;
  assign _006_ = i_arg_B[23] | i_arg_A[23];
  assign _007_ = i_arg_B[23] ^ i_arg_A[23];
  assign _008_ = i_arg_B[22] ^ i_arg_A[22];
  assign _009_ = _007_ & _008_;
  assign _010_ = i_arg_B[21] & i_arg_A[21];
  assign _011_ = i_arg_B[20] & i_arg_A[20];
  assign _012_ = _010_ | _011_;
  assign _013_ = i_arg_B[21] | i_arg_A[21];
  assign _014_ = i_arg_B[20] ^ i_arg_A[20];
  assign _015_ = i_arg_B[21] ^ i_arg_A[21];
  assign _016_ = _009_ & _015_;
  assign _017_ = _014_ & _016_;
  assign _018_ = i_arg_B[19] & i_arg_A[19];
  assign _019_ = i_arg_B[18] & i_arg_A[18];
  assign _020_ = i_arg_B[19] | i_arg_A[19];
  assign _021_ = i_arg_B[17] | i_arg_A[17];
  assign _022_ = i_arg_B[18] ^ i_arg_A[18];
  assign _023_ = i_arg_B[19] ^ i_arg_A[19];
  assign _024_ = _022_ & _023_;
  assign _025_ = _021_ & _024_;
  assign _026_ = _017_ & _025_;
  assign _027_ = _001_ & _026_;
  assign _028_ = _005_ & _006_;
  assign _029_ = _012_ & _013_;
  assign _030_ = _009_ & _029_;
  assign _031_ = _028_ | _030_;
  assign _032_ = _019_ & _020_;
  assign _033_ = _018_ | _032_;
  assign _034_ = _017_ & _033_;
  assign _035_ = _031_ | _034_;
  assign _036_ = _027_ | _035_;
  assign _037_ = _177_ & _036_;
  assign _038_ = _168_ & _169_;
  assign _039_ = _171_ | _038_;
  assign _040_ = _167_ & _039_;
  assign _041_ = _163_ & _164_;
  assign _042_ = _040_ | _041_;
  assign _043_ = _160_ & _042_;
  assign _044_ = _153_ & _157_;
  assign _045_ = _145_ & _150_;
  assign _046_ = _147_ | _045_;
  assign _047_ = _044_ | _046_;
  assign _048_ = _043_ | _047_;
  assign _049_ = _037_ | _048_;
  assign _050_ = i_arg_B[15] & i_arg_A[15];
  assign _051_ = i_arg_B[14] & i_arg_A[14];
  assign _052_ = _050_ | _051_;
  assign _053_ = i_arg_B[15] | i_arg_A[15];
  assign _054_ = i_arg_B[15] ^ i_arg_A[15];
  assign _055_ = i_arg_B[14] ^ i_arg_A[14];
  assign _056_ = _054_ & _055_;
  assign _057_ = i_arg_B[12] & i_arg_A[12];
  assign _058_ = i_arg_B[13] & i_arg_A[13];
  assign _059_ = _057_ | _058_;
  assign _060_ = i_arg_B[13] | i_arg_A[13];
  assign _061_ = i_arg_B[12] ^ i_arg_A[12];
  assign _062_ = i_arg_B[13] ^ i_arg_A[13];
  assign _063_ = _056_ & _062_;
  assign _064_ = _061_ & _063_;
  assign _065_ = i_arg_B[11] | i_arg_A[11];
  assign _066_ = i_arg_B[11] & i_arg_A[11];
  assign _067_ = i_arg_B[10] & i_arg_A[10];
  assign _068_ = _066_ | _067_;
  assign _069_ = _065_ & _068_;
  assign _070_ = i_arg_B[11] ^ i_arg_A[11];
  assign _071_ = i_arg_B[10] ^ i_arg_A[10];
  assign _072_ = _070_ & _071_;
  assign _073_ = i_arg_B[9] | i_arg_A[9];
  assign _074_ = i_arg_B[9] & i_arg_A[9];
  assign _075_ = i_arg_B[8] & i_arg_A[8];
  assign _076_ = _074_ | _075_;
  assign _077_ = _073_ & _076_;
  assign _078_ = _072_ & _077_;
  assign _079_ = _069_ | _078_;
  assign _080_ = _064_ & _079_;
  assign _081_ = _052_ & _053_;
  assign _082_ = _059_ & _060_;
  assign _083_ = _056_ & _082_;
  assign _084_ = _081_ | _083_;
  assign _085_ = _080_ | _084_;
  assign _086_ = i_arg_B[7] & i_arg_A[7];
  assign _087_ = i_arg_B[6] & i_arg_A[6];
  assign _088_ = _086_ | _087_;
  assign _089_ = i_arg_B[7] | i_arg_A[7];
  assign _090_ = i_arg_B[7] ^ i_arg_A[7];
  assign _091_ = i_arg_B[6] ^ i_arg_A[6];
  assign _092_ = _090_ & _091_;
  assign _093_ = i_arg_B[4] & i_arg_A[4];
endmodule

WORK/Verilog_modul_porownanie/porownanie.sv
//moduł porównania wartości sygnałów wejściowych A i B

module porownanie (i_arg_A, i_arg_B, o_result);
    parameter BITS = 32;
    localparam MOD_NUMBER = BITS-1;

    //deklarowanie wejść i wyjść
    input logic signed [BITS-1:0] i_arg_A;
    input logic signed [BITS-1:0] i_arg_B;
    output logic signed o_result;

    //blok opisujący logikę
    always_comb begin
        //zaczynamy porównywanie
        if (i_arg_A > (~i_arg_B)) begin
            o_result = 1;
        end

//||i_arg_A == {1'b1, {MOD_NUMBER{1'b0}}}) && (~i_arg_B == {MOD_NUMBER{1'b0}}
//||~i_arg_B == {1'b1, {MOD_NUMBER{1'b0}}}))

        else if (i_arg_A == {MOD_NUMBER{1'b0}}&&~i_arg_B == {MOD_NUMBER{1'b0}}) begin
            o_result = 0;
        end

        else if (i_arg_A == {MOD_NUMBER{1'b0}}&&~i_arg_B == {1'b1, {MOD_NUMBER{1'b0}}}) begin
            o_result = 0;
        end

        else if (i_arg_A == {1'b1, {MOD_NUMBER{1'b0}}} &&~i_arg_B == {1'b1, {MOD_NUMBER{1'b0}}}) begin
            o_result = 0;
        end
 
        else if (i_arg_A == {1'b1, {MOD_NUMBER{1'b0}}}&&~i_arg_B == {MOD_NUMBER{1'b0}}) begin
            o_result = 0;
        end

        else begin
            o_result = 0;
        end
    end
endmodule

TEST/porownanie_tb.sv
//testbench modułu porowananie.sv
//wstępnie przewidziany bez żadnych błędów ani przepełnienia w środku

module porownanie_tb;

parameter BITS=32;
localparam MOD_NUMBER = BITS-1;

// sygnały wewnętrzne
logic [BITS-1:0] s_i_arg_A;
logic [BITS-1:0] s_i_arg_B;
logic  s_o_model;
logic  s_o_synthesis;

// instancjowanie wejść i wyjść, jawne przypisywanie portów

porownanie     #(.BITS(BITS))        
porownanie     (
    .i_arg_A(s_i_arg_A), 
    .i_arg_B(s_i_arg_B), 
    .o_result(s_o_model)
    );    

porownanie_rtl           
Porownanie_rtl (
    .i_arg_A(s_i_arg_A), 
    .i_arg_B(s_i_arg_B), 
    .o_result(s_o_synthesis)
    );    

// Dostarczenie zmiennych do testu, rozpoczęcie bloku initial
initial begin
    //w tym pliku zostaną zapisane zapisane sygnały zarejestrowane w symulacji
        $dumpfile("signals_porownanie.vcd");  

        //Wskazania, że wszystkie sygnały z testbencha i niżej mają być rejestrowane podczas symulacji
        $dumpvars(0, porownanie_tb);   

        //początkowe wyzerowanie wartości sygnałów A i B
        s_i_arg_A = 0;
        s_i_arg_B = '1;      
        #1

                // Pętla for przypisująca losowe wartości argumentom wejścia dla pięciu iteracji, rozpoczęcie symulacji
        for (int i=0; i<=10; i++) begin
            #1
            s_i_arg_A = $urandom;
            s_i_arg_B = $urandom;
        end
        
       for (int i = 0; i<5; i++) begin
            #1
            s_i_arg_A = '0;
            //przesunięcie równe zero, to każde B jest 0, ale krwa znaczone, ofc, że znaczone
            s_i_arg_B = '1;
            #1
            s_i_arg_B = ~{1'b0, {MOD_NUMBER{1'b1}}};
        end

        for (int i = 0; i<5; i++) begin
            #1
            s_i_arg_A = {1'b1, {MOD_NUMBER{1'b0}}};
            //przesunięcie równe zero, to każde B jest 0, ale krwa znaczone, ofc, że znaczone
            s_i_arg_B = '1;
            #1
            s_i_arg_B = ~{1'b0, {MOD_NUMBER{1'b1}}};
        end

    end
endmodule

WORK/Verilog_modul_porownanie/signals_porownanie.vcd
$date
	Tue Dec 19 06:38:37 2023
$end
$version
	Icarus Verilog
$end
$timescale
	1s
$end
$scope module porownanie_tb $end
$var wire 1 ! s_o_synthesis $end
$var wire 1 " s_o_model $end
$var parameter 32 # BITS $end
$var parameter 33 $ MOD_NUMBER $end
$var reg 32 % s_i_arg_A [31:0] $end
$var reg 32 & s_i_arg_B [31:0] $end
$scope module Porownanie_rtl $end
$var wire 1 ' _000_ $end
$var wire 1 ( _001_ $end
$var wire 1 ) _002_ $end
$var wire 1 * _003_ $end
$var wire 1 + _004_ $end
$var wire 1 , _005_ $end
$var wire 1 - _006_ $end
$var wire 1 . _007_ $end
$var wire 1 / _008_ $end
$var wire 1 0 _009_ $end
$var wire 1 1 _010_ $end
$var wire 1 2 _011_ $end
$var wire 1 3 _012_ $end
$var wire 1 4 _013_ $end
$var wire 1 5 _014_ $end
$var wire 1 6 _015_ $end
$var wire 1 7 _016_ $end
$var wire 1 8 _017_ $end
$var wire 1 9 _018_ $end
$var wire 1 : _019_ $end
$var wire 1 ; _020_ $end
$var wire 1 < _021_ $end
$var wire 1 = _022_ $end
$var wire 1 > _023_ $end
$var wire 1 ? _024_ $end
$var wire 1 @ _025_ $end
$var wire 1 A _026_ $end
$var wire 1 B _027_ $end
$var wire 1 C _028_ $end
$var wire 1 D _029_ $end
$var wire 1 E _030_ $end
$var wire 1 F _031_ $end
$var wire 1 G _032_ $end
$var wire 1 H _033_ $end
$var wire 1 I _034_ $end
$var wire 1 J _035_ $end
$var wire 1 K _036_ $end
$var wire 1 L _037_ $end
$var wire 1 M _038_ $end
$var wire 1 N _039_ $end
$var wire 1 O _040_ $end
$var wire 1 P _041_ $end
$var wire 1 Q _042_ $end
$var wire 1 R _043_ $end
$var wire 1 S _044_ $end
$var wire 1 T _045_ $end
$var wire 1 U _046_ $end
$var wire 1 V _047_ $end
$var wire 1 W _048_ $end
$var wire 1 X _049_ $end
$var wire 1 Y _050_ $end
$var wire 1 Z _051_ $end
$var wire 1 [ _052_ $end
$var wire 1 \ _053_ $end
$var wire 1 ] _054_ $end
$var wire 1 ^ _055_ $end
$var wire 1 _ _056_ $end
$var wire 1 ` _057_ $end
$var wire 1 a _058_ $end
$var wire 1 b _059_ $end
$var wire 1 c _060_ $end
$var wire 1 d _061_ $end
$var wire 1 e _062_ $end
$var wire 1 f _063_ $end
$var wire 1 g _064_ $end
$var wire 1 h _065_ $end
$var wire 1 i _066_ $end
$var wire 1 j _067_ $end
$var wire 1 k _068_ $end
$var wire 1 l _069_ $end
$var wire 1 m _070_ $end
$var wire 1 n _071_ $end
$var wire 1 o _072_ $end
$var wire 1 p _073_ $end
$var wire 1 q _074_ $end
$var wire 1 r _075_ $end
$var wire 1 s _076_ $end
$var wire 1 t _077_ $end
$var wire 1 u _078_ $end
$var wire 1 v _079_ $end
$var wire 1 w _080_ $end
$var wire 1 x _081_ $end
$var wire 1 y _082_ $end
$var wire 1 z _083_ $end
$var wire 1 { _084_ $end
$var wire 1 | _085_ $end
$var wire 1 } _086_ $end
$var wire 1 ~ _087_ $end
$var wire 1 !" _088_ $end
$var wire 1 "" _089_ $end
$var wire 1 #" _090_ $end
$var wire 1 $" _091_ $end
$var wire 1 %" _092_ $end
$var wire 1 &" _093_ $end
$var wire 1 '" _094_ $end
$var wire 1 (" _095_ $end
$var wire 1 )" _096_ $end
$var wire 1 *" _097_ $end
$var wire 1 +" _098_ $end
$var wire 1 ," _099_ $end
$var wire 1 -" _100_ $end
$var wire 1 ." _101_ $end
$var wire 1 /" _102_ $end
$var wire 1 0" _103_ $end
$var wire 1 1" _104_ $end
$var wire 1 2" _105_ $end
$var wire 1 3" _106_ $end
$var wire 1 4" _107_ $end
$var wire 1 5" _108_ $end
$var wire 1 6" _109_ $end
$var wire 1 7" _110_ $end
$var wire 1 8" _111_ $end
$var wire 1 9" _112_ $end
$var wire 1 :" _113_ $end
$var wire 1 ;" _114_ $end
$var wire 1 <" _115_ $end
$var wire 1 =" _116_ $end
$var wire 1 >" _117_ $end
$var wire 1 ?" _118_ $end
$var wire 1 @" _119_ $end
$var wire 1 A" _120_ $end
$var wire 1 B" _121_ $end
$var wire 1 C" _122_ $end
$var wire 1 D" _123_ $end
$var wire 1 E" _124_ $end
$var wire 1 F" _125_ $end
$var wire 1 G" _126_ $end
$var wire 1 H" _127_ $end
$var wire 1 I" _128_ $end
$var wire 1 J" _129_ $end
$var wire 1 K" _130_ $end
$var wire 1 L" _131_ $end
$var wire 1 M" _132_ $end
$var wire 1 N" _133_ $end
$var wire 1 O" _134_ $end
$var wire 1 P" _135_ $end
$var wire 1 Q" _136_ $end
$var wire 1 R" _137_ $end
$var wire 1 S" _138_ $end
$var wire 1 T" _139_ $end
$var wire 1 U" _140_ $end
$var wire 1 V" _141_ $end
$var wire 1 W" _142_ $end
$var wire 1 X" _143_ $end
$var wire 1 Y" _144_ $end
$var wire 1 Z" _145_ $end
$var wire 1 [" _146_ $end
$var wire 1 \" _147_ $end
$var wire 1 ]" _148_ $end
$var wire 1 ^" _149_ $end
$var wire 1 _" _150_ $end
$var wire 1 `" _151_ $end
$var wire 1 a" _152_ $end
$var wire 1 b" _153_ $end
$var wire 1 c" _154_ $end
$var wire 1 d" _155_ $end
$var wire 1 e" _156_ $end
$var wire 1 f" _157_ $end
$var wire 1 g" _158_ $end
$var wire 1 h" _159_ $end
$var wire 1 i" _160_ $end
$var wire 1 j" _161_ $end
$var wire 1 k" _162_ $end
$var wire 1 l" _163_ $end
$var wire 1 m" _164_ $end
$var wire 1 n" _165_ $end
$var wire 1 o" _166_ $end
$var wire 1 p" _167_ $end
$var wire 1 q" _168_ $end
$var wire 1 r" _169_ $end
$var wire 1 s" _170_ $end
$var wire 1 t" _171_ $end
$var wire 1 u" _172_ $end
$var wire 1 v" _173_ $end
$var wire 1 w" _174_ $end
$var wire 1 x" _175_ $end
$var wire 1 y" _176_ $end
$var wire 1 z" _177_ $end
$var wire 1 {" _178_ $end
$var wire 32 |" i_arg_A [31:0] $end
$var wire 32 }" i_arg_B [31:0] $end
$var wire 1 ! o_result $end
$upscope $end
$scope module porownanie $end
$var wire 32 ~" i_arg_A [31:0] $end
$var wire 32 !# i_arg_B [31:0] $end
$var parameter 32 "# BITS $end
$var parameter 33 ## MOD_NUMBER $end
$var reg 1 " o_result $end
$upscope $end
$scope begin $ivl_for_loop0 $end
$var integer 32 $# i [31:0] $end
$upscope $end
$scope begin $ivl_for_loop1 $end
$var integer 32 %# i [31:0] $end
$upscope $end
$scope begin $ivl_for_loop2 $end
$var integer 32 &# i [31:0] $end
$upscope $end
$upscope $end
$enddefinitions $end
$comment Show the parameter values. $end
$dumpall
b11111 ##
b100000 "#
b11111 $
b100000 #
$end
#0
$dumpvars
b0 &#
b0 %#
b0 $#
b11111111111111111111111111111111 !#
b0 ~"
b11111111111111111111111111111111 }"
b0 |"
0{"
1z"
1y"
1x"
1w"
1v"
1u"
0t"
1s"
0r"
1q"
1p"
1o"
1n"
1m"
0l"
0k"
0j"
1i"
1h"
1g"
0f"
0e"
1d"
0c"
1b"
1a"
1`"
0_"
1^"
1]"
0\"
0["
1Z"
0Y"
1X"
1W"
1V"
1U"
1T"
0S"
1R"
1Q"
1P"
1O"
1N"
1M"
1L"
1K"
1J"
1I"
1H"
1G"
1F"
1E"
1D"
1C"
0B"
0A"
0@"
0?"
1>"
1="
0<"
0;"
1:"
19"
18"
17"
06"
05"
14"
13"
12"
11"
00"
0/"
0."
1-"
1,"
1+"
1*"
1)"
0("
0'"
0&"
1%"
1$"
1#"
1""
0!"
0~
0}
0|
0{
0z
0y
0x
0w
0v
0u
0t
0s
0r
0q
1p
1o
1n
1m
0l
0k
0j
0i
1h
1g
1f
1e
1d
1c
0b
0a
0`
1_
1^
1]
1\
0[
0Z
0Y
0X
0W
0V
0U
0T
0S
0R
0Q
0P
0O
0N
0M
0L
0K
0J
0I
0H
0G
0F
0E
0D
0C
0B
1A
1@
1?
1>
1=
1<
1;
0:
09
18
17
16
15
14
03
02
01
10
1/
1.
1-
0,
0+
0*
1)
0(
0'
b11111111111111111111111111111111 &
b0 %
0"
0!
$end
#2
0R"
0Q"
0P"
0!
0O"
0J"
1Y"
0N"
0I"
0X"
0C"
0W"
0="
0U"
0z"
0M"
0L"
0K
0H"
1v
0>"
0V"
0:"
0i"
0w"
0y"
08
0A
0f
0,"
0)
0B
1y
0G"
1l
0F"
0-"
04"
09"
0b"
0p"
0x"
00
07
0@
0_
0%"
1(
1b
0g
1k
0o
0*"
01"
02"
08"
0^"
0m"
0n"
0o"
0u"
0/
04
06
0<
0\
0]
0$"
1'
1`
0d
1j
0n
b1 $#
b1000000100010010101111010000001 &
b1000000100010010101111010000001 }"
b1000000100010010101111010000001 !#
b10010010000101010011010100100100 %
b10010010000101010011010100100100 |"
b10010010000101010011010100100100 ~"
#3
1K
1J"
1J
1|
1!
1F
1{
0v
1R"
1)
1C
1x
1t
19"
0?
0l
0T"
1["
0a"
0(
1,
1[
0y
1s
18"
1^"
0`"
1u"
1/
14
16
0;
0>
0h
0m
0""
0#"
1$"
11"
12"
03"
0D"
0E"
0K"
1S"
0Z"
0]"
1o"
0q"
0v"
0'
1*
0.
1Z
1\
1]
0^
0c
0e
1q
1"
b10 $#
b110001111100000101011001100011 &
b110001111100000101011001100011 }"
b110001111100000101011001100011 !#
b100100001001101011000001001 %
b100100001001101011000001001 |"
b100100001001101011000001001 ~"
#4
1P"
1="
1X
1<"
0!
1W
0x
1f
1;"
0R"
1V
0)
1D
1z
1v
09"
0h"
1l"
0[
1_
10"
0L"
0["
1U
1N
1(
13
1H
1y
1l
0)"
0+"
1."
02"
08"
1E"
0^"
1`"
0g"
1k"
0o"
0u"
1<
0Z
1^
0q
1""
1#"
0$"
1/"
1K"
1Z"
1\"
1q"
1t"
1'
12
05
19
1;
1c
1e
1h
1i
0j
1r
0"
b11 $#
b11000110110111111001100110001101 &
b11000110110111111001100110001101 }"
b11000110110111111001100110001101 !#
b10000110101110010111101100001101 %
b10000110101110010111101100001101 |"
b10000110101110010111101100001101 ~"
#5
0K
0P"
0J"
0J
0X
0|
0F
18
0="
1!
0W
0{
0C
17
0<"
1R"
0V
0D
0z
0v
0t
19"
1T"
0N
0,
10
00"
0;"
1["
0U
1h"
0l"
03
0H
0b
0y
0f
0l
0k
0s
1*"
0/"
13"
18"
0S"
0`"
1m"
1n"
0t"
1u"
1v"
0*
1.
0""
0#"
1)"
1+"
0."
01"
0Z"
0\"
1^"
1g"
0k"
1{"
0'
02
15
09
0;
0`
0c
1d
0e
0h
0i
1n
0r
1$"
1"
b100 $#
b1001001101110101001000010010 &
b1001001101110101001000010010 }"
b1001001101110101001000010010 !#
b110010110000101000010001100101 %
b110010110000101000010001100101 |"
b110010110000101000010001100101 ~"
#6
1K
1P"
1J"
1J
1X
1|
1F
1v
0!
1W
1{
1C
07
1u
1F"
0R"
1V
1D
1x
1t
14"
09"
0T"
1,
00
1o
0["
1U
0h"
13
08
1[
0_
0f
1s
0*"
11"
12"
08"
1S"
0m"
0n"
1o"
0u"
1*
1+
0.
0/
1Y
0]
0d
1h
1m
0)"
0+"
1Z"
1\"
0^"
0g"
1'
12
05
1Z
0^
1c
1e
1r
0$"
0"
b101 $#
b10000110110101111100110100001101 &
b10000110110101111100110100001101 }"
b10000110110101111100110100001101 !#
b10000000111100111110001100000001 %
b10000000111100111110001100000001 |"
b10000000111100111110001100000001 ~"
#7
0K
1="
0J
1<"
1Q
0F
0v
1@
1;"
1P
0C
0D
0u
1?
1@"
10"
04"
19"
0F"
1T"
1f"
1l"
1N
0,
03
0t
1("
0{"
1;
1>
1'"
1)"
1/"
03"
18"
0E"
0S"
1^"
1e"
1j"
1m"
1t"
1u"
0v"
0*
0+
1.
02
1d
0p
1$"
1&"
b110 $#
b10011110100011011100110100111101 &
b10011110100011011100110100111101 }"
b10011110100011011100110100111101 !#
b10111011001000111111000101110110 %
b10111011001000111111000101110110 |"
b10111011001000111111000101110110 ~"
#8
1K
1J
1I
1C"
1L"
18
1B"
1y
0Q
1)
17
1H
1?"
0@"
0f"
1h"
1b
09"
1T
0P
0(
10
1G
0@
0?
1k
0o
1t
1!"
0("
0'"
1+"
0e"
1g"
1`
0d
0h
0m
1."
02"
08"
1_"
0j"
1k"
0m"
0o"
0u"
0'
1/
15
1:
0<
0=
0Y
1]
1j
0n
1p
1q
1}
1""
0&"
b111 $#
b11000110001011011111011110001100 &
b11000110001011011111011110001100 }"
b11000110001011011111011110001100 !#
b11110110110101000101011111101101 %
b11110110110101000101011111101101 |"
b11110110110101000101011111101101 ~"
#9
1K
1y"
1F
1!
1J
0<"
1U"
1x"
0L"
1E
1R"
0h"
0I
0x
1z
0;"
1:"
0Q
1w"
0)
1D
19"
1Q"
0d"
1f"
0l"
08
0[
1_
00"
14"
0P
1p"
0N
1(
13
07
0k
1o
0t
0s
0."
12"
18"
1D"
0\"
1]"
1c"
0k"
1o"
1u"
12
05
1<
0Z
1^
0r
1~
0$"
1*"
0/"
13"
1m"
1n"
0t"
1v"
1'
11
06
0`
1a
0e
1h
0j
1m
1n
0p
0q
1"
b1000 $#
b1100011001101110010010011000110 &
b1100011001101110010010011000110 }"
b1100011001101110010010011000110 !#
b11111100111111011110100111111001 %
b11111100111111011110100111111001 |"
b11111100111111011110100111111001 ~"
#10
0P"
0X
0W
0y"
0V
0x"
1h"
1x
0U
0w"
0H
0z
1d"
0f"
17
1[
0_
1["
0T
0Q"
0p"
0G
0b
0y
0o
1E"
0c"
01
16
0:
1=
1Y
0]
1d
1p
0~
1$"
0*"
0D"
0Z"
0]"
0m"
0n"
1{"
0;
0>
0a
0c
0h
0m
b1001 $#
b1010101000100111101001010101010 &
b1010101000100111101001010101010 }"
b1010101000100111101001010101010 !#
b1100010111101111000010011000101 %
b1100010111101111000010011000101 |"
b1100010111101111000010011000101 ~"
#11
1Q"
1P"
1X
1W
1V
0="
1!
1S
0B
0:"
0U"
1C
07
0E
1@"
1R"
1b"
0D
0A
1@
1y
1t
10"
04"
0T"
0d"
1N
1,
00
1("
0["
1a"
1f"
0h"
03
08
1?
1b
1s
1*"
1/"
01"
02"
03"
1S"
0_"
1`"
1c"
1m"
1n"
0o"
1t"
0v"
0'
1*
0.
0Y
1]
0}
1~
1#"
0$"
1'"
0+"
1D"
0E"
1Z"
1]"
1e"
0g"
02
15
1;
1>
1Z
0^
1`
1a
1c
0d
1q
b1010 $#
b111011110100100111001001110111 &
b111011110100100111001001110111 }"
b111011110100100111001001110111 !#
b11110010101011111111011111100101 %
b11110010101011111111011111100101 |"
b11110010101011111111011111100101 ~"
