WORK/Verilog_modul_porownanie/porownanie_rtl.sv
/* Generated by Yosys 0.9 (git sha1 1979e0b) */

module porownanie_rtl(i_arg_A, i_arg_B, o_result);
  wire _000_;
  wire _001_;
  wire _002_;
  wire _003_;
  wire _004_;
  wire _005_;
  wire _006_;
  wire _007_;
  wire _008_;
  wire _009_;
  wire _010_;
  wire _011_;
  wire _012_;
  wire _013_;
  wire _014_;
  wire _015_;
  wire _016_;
  wire _017_;
  wire _018_;
  wire _019_;
  wire _020_;
  wire _021_;
  wire _022_;
  wire _023_;
  wire _024_;
  wire _025_;
  wire _026_;
  wire _027_;
  wire _028_;
  wire _029_;
  wire _030_;
  wire _031_;
  wire _032_;
  wire _033_;
  wire _034_;
  wire _035_;
  wire _036_;
  wire _037_;
  wire _038_;
  wire _039_;
  wire _040_;
  wire _041_;
  wire _042_;
  wire _043_;
  wire _044_;
  wire _045_;
  wire _046_;
  wire _047_;
  wire _048_;
  wire _049_;
  wire _050_;
  wire _051_;
  wire _052_;
  wire _053_;
  wire _054_;
  wire _055_;
  wire _056_;
  wire _057_;
  wire _058_;
  wire _059_;
  wire _060_;
  wire _061_;
  wire _062_;
  wire _063_;
  wire _064_;
  wire _065_;
  wire _066_;
  wire _067_;
  wire _068_;
  wire _069_;
  wire _070_;
  wire _071_;
  wire _072_;
  wire _073_;
  wire _074_;
  wire _075_;
  wire _076_;
  wire _077_;
  wire _078_;
  wire _079_;
  wire _080_;
  wire _081_;
  wire _082_;
  wire _083_;
  wire _084_;
  wire _085_;
  wire _086_;
  wire _087_;
  wire _088_;
  wire _089_;
  wire _090_;
  wire _091_;
  wire _092_;
  wire _093_;
  wire _094_;
  wire _095_;
  wire _096_;
  wire _097_;
  wire _098_;
  wire _099_;
  wire _100_;
  wire _101_;
  wire _102_;
  wire _103_;
  wire _104_;
  wire _105_;
  wire _106_;
  wire _107_;
  wire _108_;
  wire _109_;
  wire _110_;
  wire _111_;
  wire _112_;
  wire _113_;
  wire _114_;
  wire _115_;
  wire _116_;
  wire _117_;
  wire _118_;
  wire _119_;
  wire _120_;
  wire _121_;
  wire _122_;
  wire _123_;
  wire _124_;
  wire _125_;
  wire _126_;
  wire _127_;
  wire _128_;
  wire _129_;
  wire _130_;
  wire _131_;
  wire _132_;
  wire _133_;
  wire _134_;
  wire _135_;
  wire _136_;
  wire _137_;
  wire _138_;
  wire _139_;
  wire _140_;
  wire _141_;
  wire _142_;
  wire _143_;
  wire _144_;
  wire _145_;
  wire _146_;
  wire _147_;
  wire _148_;
  wire _149_;
  wire _150_;
  wire _151_;
  wire _152_;
  wire _153_;
  wire _154_;
  wire _155_;
  wire _156_;
  wire _157_;
  wire _158_;
  wire _159_;
  wire _160_;
  wire _161_;
  wire _162_;
  wire _163_;
  wire _164_;
  wire _165_;
  wire _166_;
  wire _167_;
  wire _168_;
  wire _169_;
  wire _170_;
  wire _171_;
  wire _172_;
  wire _173_;
  wire _174_;
  wire _175_;
  wire _176_;
  wire _177_;
  input [31:0] i_arg_A;
  input [31:0] i_arg_B;
  output o_result;
  assign _144_ = i_arg_B[31] & i_arg_A[31];
  assign _145_ = i_arg_B[30] & i_arg_A[30];
  assign _146_ = _144_ | _145_;
  assign _147_ = i_arg_B[31] | i_arg_A[31];
  assign _148_ = i_arg_B[30] ^ i_arg_A[30];
  assign _149_ = i_arg_B[31] ^ i_arg_A[31];
  assign _150_ = _148_ & _149_;
  assign _151_ = i_arg_B[29] & i_arg_A[29];
  assign _152_ = i_arg_B[28] & i_arg_A[28];
  assign _153_ = _151_ | _152_;
  assign _154_ = ~_153_;
  assign _155_ = i_arg_B[29] | i_arg_A[29];
  assign _156_ = i_arg_B[28] | i_arg_A[28];
  assign _157_ = _155_ & _156_;
  assign _158_ = _154_ & _157_;
  assign _159_ = _150_ & _158_;
  assign _160_ = i_arg_B[27] & i_arg_A[27];
  assign _161_ = i_arg_B[26] & i_arg_A[26];
  assign _162_ = _160_ | _161_;
  assign _163_ = i_arg_B[27] | i_arg_A[27];
  assign _164_ = i_arg_B[27] ^ i_arg_A[27];
  assign _165_ = i_arg_B[26] ^ i_arg_A[26];
  assign _166_ = _164_ & _165_;
  assign _167_ = i_arg_B[25] & i_arg_A[25];
  assign _168_ = i_arg_B[24] & i_arg_A[24];
  assign _169_ = _167_ | _168_;
  assign _170_ = i_arg_B[25] | i_arg_A[25];
  assign _171_ = i_arg_B[24] ^ i_arg_A[24];
  assign _172_ = i_arg_B[25] ^ i_arg_A[25];
  assign _173_ = _166_ & _172_;
  assign _174_ = _159_ & _173_;
  assign _175_ = _171_ & _174_;
  assign _176_ = i_arg_B[23] & i_arg_A[23];
  assign _177_ = i_arg_B[22] & i_arg_A[22];
  assign _000_ = _176_ | _177_;
  assign _001_ = i_arg_B[23] | i_arg_A[23];
  assign _002_ = i_arg_B[23] ^ i_arg_A[23];
  assign _003_ = i_arg_B[22] ^ i_arg_A[22];
  assign _004_ = _002_ & _003_;
  assign _005_ = i_arg_B[20] & i_arg_A[20];
  assign _006_ = i_arg_B[21] & i_arg_A[21];
  assign _007_ = _005_ | _006_;
  assign _008_ = i_arg_B[21] | i_arg_A[21];
  assign _009_ = i_arg_B[20] ^ i_arg_A[20];
  assign _010_ = i_arg_B[21] ^ i_arg_A[21];
  assign _011_ = _004_ & _010_;
  assign _012_ = _009_ & _011_;
  assign _013_ = i_arg_B[19] | i_arg_A[19];
  assign _014_ = i_arg_B[19] & i_arg_A[19];
  assign _015_ = i_arg_B[18] & i_arg_A[18];
  assign _016_ = _014_ | _015_;
  assign _017_ = _013_ & _016_;
  assign _018_ = i_arg_B[19] ^ i_arg_A[19];
  assign _019_ = i_arg_B[18] ^ i_arg_A[18];
  assign _020_ = _018_ & _019_;
  assign _021_ = i_arg_B[17] | i_arg_A[17];
  assign _022_ = i_arg_B[17] & i_arg_A[17];
  assign _023_ = i_arg_B[16] & i_arg_A[16];
  assign _024_ = _022_ | _023_;
  assign _025_ = ~_024_;
  assign _026_ = _021_ & _024_;
  assign _027_ = _020_ & _026_;
  assign _028_ = _017_ | _027_;
  assign _029_ = _012_ & _028_;
  assign _030_ = _000_ & _001_;
  assign _031_ = _007_ & _008_;
  assign _032_ = _004_ & _031_;
  assign _033_ = _030_ | _032_;
  assign _034_ = _029_ | _033_;
  assign _035_ = _175_ & _034_;
  assign _036_ = _162_ & _163_;
  assign _037_ = _169_ & _170_;
  assign _038_ = _166_ & _037_;
  assign _039_ = _036_ | _038_;
  assign _040_ = _159_ & _039_;
  assign _041_ = _153_ & _155_;
  assign _042_ = _150_ & _041_;
  assign _043_ = _146_ & _147_;
  assign _044_ = _042_ | _043_;
  assign _045_ = _040_ | _044_;
  assign _046_ = _035_ | _045_;
  assign _047_ = i_arg_B[15] & i_arg_A[15];
  assign _048_ = i_arg_B[14] & i_arg_A[14];
  assign _049_ = _047_ | _048_;
  assign _050_ = i_arg_B[15] | i_arg_A[15];
  assign _051_ = i_arg_B[15] ^ i_arg_A[15];
  assign _052_ = i_arg_B[14] ^ i_arg_A[14];
  assign _053_ = _051_ & _052_;
  assign _054_ = i_arg_B[12] & i_arg_A[12];
  assign _055_ = i_arg_B[13] & i_arg_A[13];
  assign _056_ = _054_ | _055_;
  assign _057_ = i_arg_B[13] | i_arg_A[13];
  assign _058_ = i_arg_B[12] ^ i_arg_A[12];
  assign _059_ = i_arg_B[13] ^ i_arg_A[13];
  assign _060_ = _053_ & _059_;
  assign _061_ = _058_ & _060_;
  assign _062_ = i_arg_B[11] | i_arg_A[11];
  assign _063_ = i_arg_B[11] & i_arg_A[11];
  assign _064_ = i_arg_B[10] & i_arg_A[10];
  assign _065_ = _063_ | _064_;
  assign _066_ = _062_ & _065_;
  assign _067_ = i_arg_B[11] ^ i_arg_A[11];
  assign _068_ = i_arg_B[10] ^ i_arg_A[10];
  assign _069_ = _067_ & _068_;
  assign _070_ = i_arg_B[9] | i_arg_A[9];
  assign _071_ = i_arg_B[9] & i_arg_A[9];
  assign _072_ = i_arg_B[8] & i_arg_A[8];
  assign _073_ = _071_ | _072_;
  assign _074_ = ~_073_;
  assign _075_ = _070_ & _073_;
  assign _076_ = _069_ & _075_;
  assign _077_ = _066_ | _076_;
  assign _078_ = _061_ & _077_;
  assign _079_ = _049_ & _050_;
  assign _080_ = _056_ & _057_;
  assign _081_ = _053_ & _080_;
  assign _082_ = _079_ | _081_;
  assign _083_ = _078_ | _082_;
  assign _084_ = i_arg_B[7] & i_arg_A[7];
  assign _085_ = i_arg_B[6] & i_arg_A[6];
  assign _086_ = _084_ | _085_;
  assign _087_ = i_arg_B[7] | i_arg_A[7];
  assign _088_ = i_arg_B[7] ^ i_arg_A[7];
  assign _089_ = i_arg_B[6] ^ i_arg_A[6];
  assign _090_ = _088_ & _089_;
  assign _091_ = i_arg_B[4] & i_arg_A[4];
  assign _092_ = i_arg_B[5] & i_arg_A[5];
  assign _093_ = _091_ | _092_;
  assign _094_ = i_arg_B[5] | i_arg_A[5];
  assign _095_ = i_arg_B[4] ^ i_arg_A[4];
  assign _096_ = i_arg_B[5] ^ i_arg_A[5];
  assign _097_ = _095_ & _096_;
  assign _098_ = _090_ & _097_;
  assign _099_ = i_arg_B[3] & i_arg_A[3];
  assign _100_ = i_arg_B[2] & i_arg_A[2];
  assign _101_ = _099_ | _100_;
  assign _102_ = i_arg_B[3] | i_arg_A[3];
  assign _103_ = i_arg_B[3] ^ i_arg_A[3];
  assign _104_ = i_arg_B[2] ^ i_arg_A[2];
  assign _105_ = _098_ & _104_;
  assign _106_ = _103_ & _105_;
  assign _107_ = i_arg_B[1] & i_arg_A[1];
  assign _108_ = i_arg_B[0] | i_arg_A[0];
  assign _109_ = i_arg_B[1] | i_arg_A[1];
  assign _110_ = _108_ & _109_;
  assign _111_ = _107_ | _110_;
  assign _112_ = _106_ & _111_;
  assign _113_ = _101_ & _102_;
  assign _114_ = _098_ & _113_;
  assign _115_ = _093_ & _094_;
  assign _116_ = _090_ & _115_;
  assign _117_ = _086_ & _087_;
  assign _118_ = _116_ | _117_;
  assign _119_ = _114_ | _118_;
  assign _120_ = _112_ | _119_;
  assign _121_ = i_arg_B[8] | i_arg_A[8];
  assign _122_ = _070_ & _121_;
  assign _123_ = _074_ & _122_;
  assign _124_ = _069_ & _123_;
  assign _125_ = _061_ & _124_;
  assign _126_ = _120_ & _125_;
  assign _127_ = _083_ | _126_;
  assign _128_ = i_arg_B[16] | i_arg_A[16];
  assign _129_ = _021_ & _128_;
  assign _130_ = _025_ & _129_;
  assign _131_ = _020_ & _130_;
  assign _132_ = _012_ & _131_;
  assign _133_ = _175_ & _132_;
  assign _134_ = _127_ & _133_;
  assign _135_ = _046_ | _134_;
  assign _136_ = i_arg_B[0] & i_arg_A[0];
  assign _137_ = _107_ | _136_;
  assign _138_ = ~_137_;
  assign _139_ = _110_ & _138_;
  assign _140_ = _125_ & _139_;
  assign _141_ = _106_ & _140_;
  assign _142_ = _133_ & _141_;
  assign _143_ = ~_142_;
  assign o_result = _135_ & _143_;
endmodule

WORK/Verilog_modul_porownanie/porownanie.sv
//moduł porównania wartości sygnałów wejściowych A i B

module porownanie (i_arg_A, i_arg_B, o_result);
    parameter BITS = 32;

    //deklarowanie wejść i wyjść
    input logic [BITS-1:0] i_arg_A;
    input logic [BITS-1:0] i_arg_B;
    output logic o_result;

    //blok opisujący logikę
    always_comb 
    begin
        //defaultowe zerowanie wyjścia
        o_result = 0;
        //zaczynamy porównywanie

        if (i_arg_A > (~i_arg_B)) begin
            o_result = 1;
        end

        else begin
            o_result = 0;
        end
    end
endmodule

WORK/Verilog_modul_porownanie/porownanie_tb.sv
//testbench modułu porowananie.sv
//wstępnie przewidziany bez żadnych błędów ani przepełnienia w środku

module porownanie_tb;

parameter BITS=32;

// sygnały wewnętrzne
logic [BITS-1:0] s_i_arg_A;
logic [BITS-1:0] s_i_arg_B;
logic  s_o_model;
logic  s_o_synthesis;

// instancjowanie wejść i wyjść, jawne przypisywanie portów

porownanie     #(.BITS(BITS))        
porownanie     (
    .i_arg_A(s_i_arg_A), 
    .i_arg_B(s_i_arg_B), 
    .o_result(s_o_model)
    );    

porownanie_rtl           
Porownanie_rtl (
    .i_arg_A(s_i_arg_A), 
    .i_arg_B(s_i_arg_B), 
    .o_result(s_o_synthesis)
    );    

// Dostarczenie zmiennych do testu, rozpoczęcie bloku initial
initial 
begin
    //w tym pliku zostaną zapisane zapisane sygnały zarejestrowane w symulacji
        $dumpfile("signals_porownanie.vcd");  

        //Wskazania, że wszystkie sygnały z testbencha i niżej mają być rejestrowane podczas symulacji
        $dumpvars(0, porownanie_tb);   

        //początkowe wyzerowanie wartości sygnałów A i B
        s_i_arg_A = 0;
        s_i_arg_B = 0;      
        #1

                // Pętla for przypisująca losowe wartości argumentom wejścia dla pięciu iteracji, rozpoczęcie symulacji
        for (int i=0; i<=10; i++) begin
            #1
            s_i_arg_A = $urandom;
            s_i_arg_B = $urandom;
        end
end
endmodule

WORK/Verilog_modul_porownanie/signals_porownanie.vcd
$date
	Thu Nov 23 21:22:44 2023
$end
$version
	Icarus Verilog
$end
$timescale
	1s
$end
$scope module porownanie_tb $end
$var wire 1 ! s_o_synthesis $end
$var wire 1 " s_o_model $end
$var reg 32 # s_i_arg_A [31:0] $end
$var reg 32 $ s_i_arg_B [31:0] $end
$scope module Porownanie_rtl $end
$var wire 1 % _000_ $end
$var wire 1 & _001_ $end
$var wire 1 ' _002_ $end
$var wire 1 ( _003_ $end
$var wire 1 ) _004_ $end
$var wire 1 * _005_ $end
$var wire 1 + _006_ $end
$var wire 1 , _007_ $end
$var wire 1 - _008_ $end
$var wire 1 . _009_ $end
$var wire 1 / _010_ $end
$var wire 1 0 _011_ $end
$var wire 1 1 _012_ $end
$var wire 1 2 _013_ $end
$var wire 1 3 _014_ $end
$var wire 1 4 _015_ $end
$var wire 1 5 _016_ $end
$var wire 1 6 _017_ $end
$var wire 1 7 _018_ $end
$var wire 1 8 _019_ $end
$var wire 1 9 _020_ $end
$var wire 1 : _021_ $end
$var wire 1 ; _022_ $end
$var wire 1 < _023_ $end
$var wire 1 = _024_ $end
$var wire 1 > _025_ $end
$var wire 1 ? _026_ $end
$var wire 1 @ _027_ $end
$var wire 1 A _028_ $end
$var wire 1 B _029_ $end
$var wire 1 C _030_ $end
$var wire 1 D _031_ $end
$var wire 1 E _032_ $end
$var wire 1 F _033_ $end
$var wire 1 G _034_ $end
$var wire 1 H _035_ $end
$var wire 1 I _036_ $end
$var wire 1 J _037_ $end
$var wire 1 K _038_ $end
$var wire 1 L _039_ $end
$var wire 1 M _040_ $end
$var wire 1 N _041_ $end
$var wire 1 O _042_ $end
$var wire 1 P _043_ $end
$var wire 1 Q _044_ $end
$var wire 1 R _045_ $end
$var wire 1 S _046_ $end
$var wire 1 T _047_ $end
$var wire 1 U _048_ $end
$var wire 1 V _049_ $end
$var wire 1 W _050_ $end
$var wire 1 X _051_ $end
$var wire 1 Y _052_ $end
$var wire 1 Z _053_ $end
$var wire 1 [ _054_ $end
$var wire 1 \ _055_ $end
$var wire 1 ] _056_ $end
$var wire 1 ^ _057_ $end
$var wire 1 _ _058_ $end
$var wire 1 ` _059_ $end
$var wire 1 a _060_ $end
$var wire 1 b _061_ $end
$var wire 1 c _062_ $end
$var wire 1 d _063_ $end
$var wire 1 e _064_ $end
$var wire 1 f _065_ $end
$var wire 1 g _066_ $end
$var wire 1 h _067_ $end
$var wire 1 i _068_ $end
$var wire 1 j _069_ $end
$var wire 1 k _070_ $end
$var wire 1 l _071_ $end
$var wire 1 m _072_ $end
$var wire 1 n _073_ $end
$var wire 1 o _074_ $end
$var wire 1 p _075_ $end
$var wire 1 q _076_ $end
$var wire 1 r _077_ $end
$var wire 1 s _078_ $end
$var wire 1 t _079_ $end
$var wire 1 u _080_ $end
$var wire 1 v _081_ $end
$var wire 1 w _082_ $end
$var wire 1 x _083_ $end
$var wire 1 y _084_ $end
$var wire 1 z _085_ $end
$var wire 1 { _086_ $end
$var wire 1 | _087_ $end
$var wire 1 } _088_ $end
$var wire 1 ~ _089_ $end
$var wire 1 !" _090_ $end
$var wire 1 "" _091_ $end
$var wire 1 #" _092_ $end
$var wire 1 $" _093_ $end
$var wire 1 %" _094_ $end
$var wire 1 &" _095_ $end
$var wire 1 '" _096_ $end
$var wire 1 (" _097_ $end
$var wire 1 )" _098_ $end
$var wire 1 *" _099_ $end
$var wire 1 +" _100_ $end
$var wire 1 ," _101_ $end
$var wire 1 -" _102_ $end
$var wire 1 ." _103_ $end
$var wire 1 /" _104_ $end
$var wire 1 0" _105_ $end
$var wire 1 1" _106_ $end
$var wire 1 2" _107_ $end
$var wire 1 3" _108_ $end
$var wire 1 4" _109_ $end
$var wire 1 5" _110_ $end
$var wire 1 6" _111_ $end
$var wire 1 7" _112_ $end
$var wire 1 8" _113_ $end
$var wire 1 9" _114_ $end
$var wire 1 :" _115_ $end
$var wire 1 ;" _116_ $end
$var wire 1 <" _117_ $end
$var wire 1 =" _118_ $end
$var wire 1 >" _119_ $end
$var wire 1 ?" _120_ $end
$var wire 1 @" _121_ $end
$var wire 1 A" _122_ $end
$var wire 1 B" _123_ $end
$var wire 1 C" _124_ $end
$var wire 1 D" _125_ $end
$var wire 1 E" _126_ $end
$var wire 1 F" _127_ $end
$var wire 1 G" _128_ $end
$var wire 1 H" _129_ $end
$var wire 1 I" _130_ $end
$var wire 1 J" _131_ $end
$var wire 1 K" _132_ $end
$var wire 1 L" _133_ $end
$var wire 1 M" _134_ $end
$var wire 1 N" _135_ $end
$var wire 1 O" _136_ $end
$var wire 1 P" _137_ $end
$var wire 1 Q" _138_ $end
$var wire 1 R" _139_ $end
$var wire 1 S" _140_ $end
$var wire 1 T" _141_ $end
$var wire 1 U" _142_ $end
$var wire 1 V" _143_ $end
$var wire 1 W" _144_ $end
$var wire 1 X" _145_ $end
$var wire 1 Y" _146_ $end
$var wire 1 Z" _147_ $end
$var wire 1 [" _148_ $end
$var wire 1 \" _149_ $end
$var wire 1 ]" _150_ $end
$var wire 1 ^" _151_ $end
$var wire 1 _" _152_ $end
$var wire 1 `" _153_ $end
$var wire 1 a" _154_ $end
$var wire 1 b" _155_ $end
$var wire 1 c" _156_ $end
$var wire 1 d" _157_ $end
$var wire 1 e" _158_ $end
$var wire 1 f" _159_ $end
$var wire 1 g" _160_ $end
$var wire 1 h" _161_ $end
$var wire 1 i" _162_ $end
$var wire 1 j" _163_ $end
$var wire 1 k" _164_ $end
$var wire 1 l" _165_ $end
$var wire 1 m" _166_ $end
$var wire 1 n" _167_ $end
$var wire 1 o" _168_ $end
$var wire 1 p" _169_ $end
$var wire 1 q" _170_ $end
$var wire 1 r" _171_ $end
$var wire 1 s" _172_ $end
$var wire 1 t" _173_ $end
$var wire 1 u" _174_ $end
$var wire 1 v" _175_ $end
$var wire 1 w" _176_ $end
$var wire 1 x" _177_ $end
$var wire 32 y" i_arg_A [31:0] $end
$var wire 32 z" i_arg_B [31:0] $end
$var wire 1 ! o_result $end
$upscope $end
$scope module porownanie $end
$var wire 32 {" i_arg_A [31:0] $end
$var wire 32 |" i_arg_B [31:0] $end
$var reg 1 " o_result $end
$upscope $end
$scope begin $ivl_for_loop0 $end
$var integer 32 }" i [31:0] $end
$upscope $end
$upscope $end
$enddefinitions $end
#0
$dumpvars
b0 }"
b0 |"
b0 {"
b0 z"
b0 y"
0x"
0w"
0v"
0u"
0t"
0s"
0r"
0q"
0p"
0o"
0n"
0m"
0l"
0k"
0j"
0i"
0h"
0g"
0f"
0e"
0d"
0c"
0b"
1a"
0`"
0_"
0^"
0]"
0\"
0["
0Z"
0Y"
0X"
0W"
1V"
0U"
0T"
0S"
0R"
1Q"
0P"
0O"
0N"
0M"
0L"
0K"
0J"
0I"
0H"
0G"
0F"
0E"
0D"
0C"
0B"
0A"
0@"
0?"
0>"
0="
0<"
0;"
0:"
09"
08"
07"
06"
05"
04"
03"
02"
01"
00"
0/"
0."
0-"
0,"
0+"
0*"
0)"
0("
0'"
0&"
0%"
0$"
0#"
0""
0!"
0~
0}
0|
0{
0z
0y
0x
0w
0v
0u
0t
0s
0r
0q
0p
1o
0n
0m
0l
0k
0j
0i
0h
0g
0f
0e
0d
0c
0b
0a
0`
0_
0^
0]
0\
0[
0Z
0Y
0X
0W
0V
0U
0T
0S
0R
0Q
0P
0O
0N
0M
0L
0K
0J
0I
0H
0G
0F
0E
0D
0C
0B
0A
0@
0?
1>
0=
0<
0;
0:
09
08
07
06
05
04
03
02
01
00
0/
0.
0-
0,
0+
0*
0)
0(
0'
0&
0%
b0 $
b0 #
0"
0!
$end
#2
1r
0>
1u
1B"
1g
1]"
19
1=
1]
1f
1A"
1["
1&
1'
12
17
1Y
1c
1h
1k
1|
1}
13"
1Z"
1\"
1c"
1q"
1s"
1.
18
1<
1[
1^
1`
1e
1%"
1'"
1/"
1@"
1G"
b1 }"
b1000000100010010101111010000001 $
b1000000100010010101111010000001 z"
b1000000100010010101111010000001 |"
b10010010000101010011010100100100 #
b10010010000101010011010100100100 y"
b10010010000101010011010100100100 {"
#3
1F"
1G
1x
1F
1w
1e"
0r
16"
1C
1>
1t
0o
1p
0B"
0Q"
1d"
09
0g
15"
0]"
1%
0=
1V
0u
1n
0A"
1P"
0["
1b"
1r"
1(
1-
1/
02
07
0c
0h
0|
0}
1~
14"
0Z"
0\"
1l"
0q"
0s"
1w"
0'
0<
1U
1W
1X
0Y
0^
0`
1l
1-"
1."
0/"
0@"
0G"
1O"
b10 }"
b110001111100000101011001100011 $
b110001111100000101011001100011 z"
b110001111100000101011001100011 |"
b100100001001101011000001001 #
b100100001001101011000001001 y"
b100100001001101011000001001 {"
#4
1!
1N"
1S
1R
1Q
0e"
0t
1a
06"
1P
1J
1D
1A
0>
1v
1r
18"
0I"
0d"
1i"
1?
0V
1Z
05"
1Y"
1p"
1,
16
15
1=
1u
1g
1,"
1A"
1H"
1["
0b"
0c"
1h"
0l"
0r"
1:
0U
1Y
0l
1|
1}
0~
0%"
0'"
1*"
0."
04"
1W"
1Z"
1n"
1q"
1*
0.
12
13
1<
1^
1`
1c
1d
0e
1m
1+"
1@"
1G"
1"
b11 }"
b11000110110111111001100110001101 $
b11000110110111111001100110001101 z"
b11000110110111111001100110001101 |"
b10000110101110010111101100001101 #
b10000110101110010111101100001101 y"
b10000110101110010111101100001101 {"
#5
0!
0N"
0F"
0G
0S
0x
0F
11
0R
0w
0J
0C
10
16"
1R"
1Q"
0Q
1e"
0D
0A
0v
0r
1o
0p
0p"
0%
1)
15"
0P"
0Y"
0P
1d"
0i"
0,
06
05
0]
0u
0a
0g
0f
0n
1("
0,"
08"
0A"
0["
1j"
1k"
0n"
1r"
1s"
0w"
1'
0|
0}
1&"
0+"
1/"
14"
0O"
0W"
0Z"
1b"
1c"
0h"
0*
1.
02
03
1;
0<
0[
0^
1_
0`
0c
0d
1i
0m
1~
1%"
1'"
0*"
0-"
0@"
0"
b100 }"
b1001001101110101001000010010 $
b1001001101110101001000010010 z"
b1001001101110101001000010010 |"
b110010110000101000010001100101 #
b110010110000101000010001100101 y"
b110010110000101000010001100101 {"
#6
1!
1N"
1S
1F"
1G
1R
1x
1F
1r
1Q
1w
1C
00
1q
0C"
06"
0R"
0Q"
1P
0e"
1D
1t
0o
1p
0B"
1%
0)
1j
05"
1P"
1Y"
0d"
1,
01
1V
0Z
0a
1n
0("
1A"
0j"
0k"
1l"
0r"
1w"
1x"
0'
0(
1T
0X
0_
1c
1h
0&"
1-"
1."
04"
1O"
1W"
1Z"
0b"
0c"
1*
0.
1<
1U
0Y
1^
1`
1m
0~
0%"
0'"
1@"
1"
b101 }"
b10000110110101111100110100001101 $
b10000110110101111100110100001101 z"
b10000110110101111100110100001101 |"
b10000000111100111110001100000001 #
b10000000111100111110001100000001 y"
b10000000111100111110001100000001 {"
#7
0G
1A
1L
0F
0r
1@
0a"
1N
0e"
1I
1J
0C
0D
0q
1:"
18"
16"
1R"
1Q"
19
1`"
1d"
1i"
1p"
0%
0,
0p
0A"
1$"
1,"
15"
0P"
12
17
0;
1_"
1b"
1c"
1g"
1j"
1n"
1r"
0s"
0w"
0x"
1'
0*
1_
0k
1~
1""
1#"
1%"
1+"
0/"
14"
0O"
1"
b110 }"
b10011110100011011100110100111101 $
b10011110100011011100110100111101 z"
b10011110100011011100110100111101 |"
b10111011001000111111000101110110 #
b10111011001000111111000101110110 y"
b10111011001000111111000101110110 {"
#8
1G
1?"
1B
1>"
1e"
11
1="
1a"
0N
1u
0L
10
16
0@
1>
1<"
0:"
06"
0R"
0`"
1]
0I
1)
15
09
0?
0H"
0=
1f
0j
1p
1A"
1{
0$"
05"
0_"
1[
0_
0c
0h
0#"
1'"
1X"
0g"
1h"
0j"
0l"
0r"
1(
1.
14
08
0:
0<
0T
1X
1e
0i
1k
1l
1y
1|
0""
1*"
0."
04"
1"
b111 }"
b11000110001011011111011110001100 $
b11000110001011011111011110001100 z"
b11000110001011011111011110001100 |"
b11110110110101000101011111101101 #
b11110110110101000101011111101101 y"
b11110110110101000101011111101101 {"
#9
1F
0e"
1G
1E
0a"
1N
0B
0t
1v
16"
1R"
0L
1t"
0J
1D
0>
1o
08"
1`"
0i"
01
1?
1H"
0V
1Z
15"
0I
1m"
0p"
1,
00
1=
0f
1j
0p
0A"
0n
1("
0,"
0W"
1\"
1^"
0h"
1l"
1r"
1*
0.
1:
0U
1Y
0m
1z
0~
0*"
1."
14"
1j"
1k"
0n"
1s"
1+
0/
1<
0[
1\
0`
1c
0e
1h
1i
0k
0l
1&"
0+"
1/"
1"
b1000 }"
b1100011001101110010010011000110 $
b1100011001101110010010011000110 z"
b1100011001101110010010011000110 |"
b11111100111111011110100111111001 #
b11111100111111011110100111111001 y"
b11111100111111011110100111111001 {"
#10
0!
0N"
0S
1e"
0R
1a"
0N
1t
0Q
0t"
0A
0v
0`"
10
05
1V
0Z
0P
0m"
06
0]
0u
0j
0("
0^"
0+
1/
04
18
1T
0X
1_
1k
0z
1~
0Z"
0\"
0j"
0k"
02
07
1;
0\
0^
0c
0h
0&"
0@"
0"
b1001 }"
b1010101000100111101001010101010 $
b1010101000100111101001010101010 z"
b1010101000100111101001010101010 |"
b1100010111101111000010011000101 #
b1100010111101111000010011000101 y"
b1100010111101111000010011000101 {"
#11
1!
1N"
1S
0R"
1R
0e"
1A
1J
1C
00
0E
0Q"
1Q
0f"
1O
0a"
1N
0D
1@
1u
0o
1p
1:"
0B"
0Y"
1p"
1%
0)
1,"
1P"
0P
1]"
1`"
0,
01
19
1]
1n
1$"
1A"
0X"
1["
1^"
1j"
1k"
0l"
1n"
0s"
1w"
0'
0<
0T
1X
0y
1z
1}
0~
1&"
1+"
0-"
0."
0/"
1O"
1Z"
1\"
1_"
0*
1.
12
17
1U
0Y
1[
1\
1^
0_
1l
1#"
0'"
1@"
1"
b1010 }"
b111011110100100111001001110111 $
b111011110100100111001001110111 z"
b111011110100100111001001110111 |"
b11110010101011111111011111100101 #
b11110010101011111111011111100101 y"
b11110010101011111111011111100101 {"
#12
0!
0N"
0S
0?"
0A
0R
1G
0>"
1L
1E
0@
1r
0Q
1F
0="
1t"
1K
1D
1>
0?
1q
1a"
0O
0C
0<"
1m"
1,
0=
1j
0`"
0N
0d"
0%
1)
0u
0{
0$"
0:"
0,"
0H"
1l"
1+
0/
0;
1T
0X
1c
1h
1-"
1."
0^"
0_"
0b"
0c"
0n"
1o"
0r"
1s"
0w"
1'
0\
0^
0z
0#"
0%"
0+"
1/"
12"
0G"
0O"
0"
b1011 }"
b11000111111011001101101110001111 $
b11000111111011001101101110001111 z"
b11000111111011001101101110001111 |"
b1001001100101101011000010010 #
b1001001100101101011000010010 y"
b1001001100101101011000010010 {"
