RTL/przesuniecie_rtl.sv
/* Generated by Yosys 0.9 (git sha1 1979e0b) */

module przesuniecie_rtl(i_arg_A, i_arg_B, o_result, o_error, o_overflow);
  wire _00_;
  wire _01_;
  wire _02_;
  wire _03_;
  wire _04_;
  wire _05_;
  wire _06_;
  wire _07_;
  wire _08_;
  wire _09_;
  wire _10_;
  wire _11_;
  wire _12_;
  wire _13_;
  wire _14_;
  wire _15_;
  wire _16_;
  wire _17_;
  wire _18_;
  wire _19_;
  wire _20_;
  wire _21_;
  wire _22_;
  wire _23_;
  wire _24_;
  wire _25_;
  wire _26_;
  wire _27_;
  wire _28_;
  wire _29_;
  wire _30_;
  wire _31_;
  wire _32_;
  input [31:0] i_arg_A;
  input [31:0] i_arg_B;
  output o_error;
  output o_overflow;
  output [31:0] o_result;
  assign _31_ = i_arg_B[4] & i_arg_B[3];
  assign _32_ = i_arg_B[2] & i_arg_B[1];
  assign _00_ = i_arg_B[0] & _32_;
  assign _01_ = _31_ & _00_;
  assign _02_ = i_arg_B[5] | _01_;
  assign _03_ = i_arg_B[9] & i_arg_B[8];
  assign _04_ = i_arg_B[7] & i_arg_B[6];
  assign _05_ = _03_ & _04_;
  assign _06_ = i_arg_B[13] & i_arg_B[12];
  assign _07_ = i_arg_B[11] & i_arg_B[10];
  assign _08_ = _06_ & _07_;
  assign _09_ = i_arg_B[17] & i_arg_B[16];
  assign _10_ = i_arg_B[15] & i_arg_B[14];
  assign _11_ = _09_ & _10_;
  assign _12_ = _08_ & _11_;
  assign _13_ = _05_ & _12_;
  assign _14_ = i_arg_B[31] & i_arg_B[30];
  assign _15_ = i_arg_B[29] & i_arg_B[28];
  assign _16_ = i_arg_B[27] & i_arg_B[26];
  assign _17_ = _15_ & _16_;
  assign _18_ = _14_ & _17_;
  assign _19_ = i_arg_B[21] & i_arg_B[20];
  assign _20_ = i_arg_B[19] & i_arg_B[18];
  assign _21_ = _19_ & _20_;
  assign _22_ = i_arg_B[25] & i_arg_B[24];
  assign _23_ = i_arg_B[23] & i_arg_B[22];
  assign _24_ = _22_ & _23_;
  assign _25_ = _21_ & _24_;
  assign _26_ = _18_ & _25_;
  assign _27_ = _13_ & _26_;
  assign _28_ = _02_ & _27_;
  assign o_overflow = ~_28_;
  assign _29_ = i_arg_B[5] & _01_;
  assign _30_ = _27_ & _29_;
  assign o_result[0] = i_arg_A[0] & _30_;
  assign o_result[1] = i_arg_A[1] & _30_;
  assign o_result[2] = i_arg_A[2] & _30_;
  assign o_result[3] = i_arg_A[3] & _30_;
  assign o_result[4] = i_arg_A[4] & _30_;
  assign o_result[5] = i_arg_A[5] & _30_;
  assign o_result[6] = i_arg_A[6] & _30_;
  assign o_result[7] = i_arg_A[7] & _30_;
  assign o_result[8] = i_arg_A[8] & _30_;
  assign o_result[9] = i_arg_A[9] & _30_;
  assign o_result[10] = i_arg_A[10] & _30_;
  assign o_result[11] = i_arg_A[11] & _30_;
  assign o_result[12] = i_arg_A[12] & _30_;
  assign o_result[13] = i_arg_A[13] & _30_;
  assign o_result[14] = i_arg_A[14] & _30_;
  assign o_result[15] = i_arg_A[15] & _30_;
  assign o_result[16] = i_arg_A[16] & _30_;
  assign o_result[17] = i_arg_A[17] & _30_;
  assign o_result[18] = i_arg_A[18] & _30_;
  assign o_result[19] = i_arg_A[19] & _30_;
  assign o_result[20] = i_arg_A[20] & _30_;
  assign o_result[21] = i_arg_A[21] & _30_;
  assign o_result[22] = i_arg_A[22] & _30_;
  assign o_result[23] = i_arg_A[23] & _30_;
  assign o_result[24] = i_arg_A[24] & _30_;
  assign o_result[25] = i_arg_A[25] & _30_;
  assign o_result[26] = i_arg_A[26] & _30_;
  assign o_result[27] = i_arg_A[27] & _30_;
  assign o_result[28] = i_arg_A[28] & _30_;
  assign o_result[29] = i_arg_A[29] & _30_;
  assign o_result[30] = i_arg_A[30] & _30_;
  assign o_result[31] = i_arg_A[31] & _30_;
  assign o_error = 1'h0;
endmodule

MODEL/przesuniecie.sv
// moduł przesunięcia arytmetycznego wejścia A o ~B bitów 
module przesuniecie (i_arg_A, i_arg_B, o_result, o_error, o_overflow);

// zadeklarowanie parametru szerokości wektorów wejściowych
parameter BITS = 32;

// zadeklarowanie wektorów wejściowych wraz z ich atrybutami
input logic  [BITS-1:0] i_arg_A;
input logic  [BITS-1:0] i_arg_B;

// zadeklarowanie wektora wyjściowego z jego atrybutami
output logic [BITS-1:0] o_result;

// zadeklarowanie bitów błędu i przepełnienia
output logic o_error;
output logic o_overflow;



always_comb 
begin
    o_result [BITS-1:0] = 32'bx;
    //przypadek wzorowy, przesunięcie nie przekracza 31 bitów
    // żadne flagi się nie zapalają
    if (~i_arg_B > 0 && ~i_arg_B < 32) begin
        o_result = i_arg_A >> i_arg_B;
        o_error = '0;
        o_overflow = '0;
    end

    // przypadek, jak przesunięcie wynosi 0, to wynik jest taki sam, jak wejście A
    // żadne flagi się nie zapalają
    else if (~i_arg_B == 0) begin
        o_result = i_arg_A;
        o_error = '0;
        o_overflow = '0;
    end

    // przypadek, jak przesunięcie wynosi tyle samo, co długość wektora wejściowego A. 
    // czyli 32 bity - przepełnienia nie ma, bo przesunęliśmy wszystkie bity i ani jednego więcej,
    // błędu nie ma, bo wartość wyjściowa jest ustawiona na ALL ONES lub ALL ZEROS w zależności od
    // znaku wektora wejściowego A: gdy A jest ujemne, wynik jest ustawiony na ALL ONES, 
    // w przeciwnym przypadku to jest ALL ZEROS
    else if (~i_arg_B == 32) begin
        o_result = (i_arg_A < 0) ? '1 :'0;
        o_error = '0;
        o_overflow = '0;
    end

    //przypadek, gdy przesunięcie jest ujemne - wynik jest nezdefiniowany i zapalony jest bit błędu
    // bit przepełnienia jest wyłączony, bo to nie jest przepełnienie, tylko błąd operacji
    else if (~i_arg_B < 0) begin
        o_error = '1;        
        o_overflow = '0;
    end
    
    // przypadek, gdy dochodzi do przepełnienia, więc zapalamy bit flagi przepełnienia, ale nie jest to
    // błąd operacji, chociaż wynik jest nieokreślony
    else if (~i_arg_B > 32) begin
        o_error = '0;
        o_overflow = '1;
    end    
end
endmodule

WORK/Verilog_modul_przesuniecie/przesuniecie_tb.sv
// testbench modułu przesunięcia arytmetycznego 

// deklaracja skali zegarka dla tej symulacji
`timescale 1ns/1ps
// zaczynamy moduł ławeczki testowej
module przesuniecie_tb;

    //parametryzowanie sygnałów, duże, bo chcemy sobie zobaczyć zachowanie sygnału B
    //na większym zakresie niż pół cyferki
    parameter BITS=32;
    
    // sygnały wewnętrzne w tej konkretnej ławeczce testowej
    logic [BITS-1:0] s_i_arg_A;
    logic [BITS-1:0] s_i_arg_B;
    logic            s_o_error_model;
    logic            s_o_error_synthesis;
    logic            s_o_overflow_model;
    logic            s_o_overflow_synthesis;
    logic [BITS-1:0] s_o_model;
    logic [BITS-1:0] s_o_synthesis;
    
    
    // tablica z kilkoma zestawami danych wejściowych
    typedef struct packed {
        int A;
        int B;
    } Testcase;

    Testcase testcases_examplary[0:4];
    Testcase testcases_zero_shift[0:4];
    Testcase testcases_32_shift[0:8];
    Testcase testcases_neg_shift[0:4];
    Testcase testcases_overflow[0:8];


    // instancjowanie wejść i wyjść, jawne przypisywanie portów, łączenie kabelków
    przesuniecie     #(.BITS(BITS))        
    przesuniecie     (
        .i_arg_A(s_i_arg_A), 
        .i_arg_B(s_i_arg_B),
        .o_result(s_o_model), 
        .o_error(s_o_error_model), 
        .o_overflow(s_o_overflow_model)
        ); 

    przesuniecie_rtl           
    przesuniecie_rtl (
        .i_arg_A(s_i_arg_A), 
        .i_arg_B(s_i_arg_B), 
        .o_result(s_o_synthesis), 
        .o_error(s_o_error_synthesis), 
        .o_overflow(s_o_overflow_synthesis)
        );

    // Dostarczenie zmiennych do testu, rozpoczęcie bloku initial
    initial begin

        //inicjalizacja ziarna losowości, żeby funkcja $urandom wyszła z progu
        $randomseed;

        //w tym pliku zostaną zapisane zapisane sygnały zarejestrowane w symulacji
        $dumpfile("signals.vcd");  

        //Wskazania, że wszystkie sygnały z testbencha i niżej mają być rejestrowane podczas symulacji
        $dumpvars(0, przesuniecie_tb);   

        //początkowe wyzerowanie wartości sygnałów A i B
        s_i_arg_A=0;
        s_i_arg_B=0;

        //zapełnienie pierwszych czterech pól tablicy przepełnienia i maksymalnego przesunięcia
        //muszę zobaczyć, jak to się zachowuje
        //skrajne przypadki, ujemne zero i dodatnie zero,
        //maksymalny integer dodatni, maksymalny integer ujemny
        //Testcase testcases_32_shift[0:3].A = '{Testcase'(32'h1, 32'h0), Testcase'(32'h1, 32'h1), Testcase'(32'h0, 32'h0), Testcase'(32'h0, 32'h1)};

        //Testcase testcases_overflow[0:3].A = '{Testcase'(32'h1, 32'h0), Testcase'(32'h1, 32'h1), Testcase'(32'h0, 32'h0), Testcase'(32'h0, 32'h1)};

        //wygenerowanie losowych wartości dla wybranych przeze mnie przypadków
        //ściągawka: maksymalne A = 2**BITS - 1; minimalne A = -(2**BITS - 1);
        for (int i = 0; i < 5; i++) begin

            //tablica wartości A dla idealnego przypadku
            testcases_examplary[i].A = $urandom_range(-2**(BITS-1)+1, 2**(BITS-1)-1); 
            //losowanie z maksymalnego zakresu B, które to wartości będą przypadkami wzorowymi
            testcases_examplary[i].B = $urandom_range(0, 31);
             //przypisanie wartości argumentom A i B
            #10
            s_i_arg_A = testcases_examplary[i].A;
            #10
            s_i_arg_B = testcases_examplary[i].B;

            //tablica wartości A dla przesunięcia równego zero
            testcases_zero_shift[i].A = $urandom_range(-2**(BITS-1)+1, 2**(BITS-1)-1);
            //przesunięcie równe zero, to każde B jest 0
            testcases_zero_shift[i].B = 0;
            #10
            s_i_arg_A = testcases_zero_shift[i].A;
            #10
            s_i_arg_B = testcases_zero_shift[i].B;

            //tablica wartości A dla negatywnego przesunięcia
            testcases_neg_shift[i].A = $urandom_range(-2**(BITS-1)+1, 2**(BITS-1)-1);
            //przesunięcie negatywne:
            testcases_neg_shift[i].B = $urandom_range(-2**(BITS-1)+1, 0);
            #10
            s_i_arg_A = testcases_neg_shift[i].A;
            #10
            s_i_arg_B = testcases_neg_shift[i].B;

        end

        for(i = 0; i<9; i++) begin
            //tablica wartości A dla przesunięcia maksymalnego z wartościami od 4 do 8 miejsca,
            //bo pierwsze 4 miejsca są zarezerwowane na 
            //skrajne przypadki, ujemne zero i dodatnie zero,
            testcases_32_shift[3+i].A = $urandom_range(-2**(BITS-1)+1, 2**(BITS-1)-1);
            //przesunięcie maksymalne, to każde B jest 32
            testcases_32_shift[i].B = 32;

            //tablica wartości A dla przepełnienia
            testcases_overflow[3+i].A = $urandom_range(-2**(BITS-1)+1, 2**(BITS-1)-1);
            //tablica wartości B dla przepełnienia, przesunięcie musi być dłuższe od liczby bitów,
            //na których zapisane jest A
            testcases_overflow[i].B = $urandom_range(33, 2**(BITS-1)-1);
            
            //dokonanie testu dla przepełnienia
            #10
            s_i_arg_A = testcases_overflow[i].A;
            #10
            s_i_arg_B = testcases_overflow[i].B;

            //dokonanie testu dla maksymalnego przesunięcia
            #10
            s_i_arg_A = testcases_32_shift[i].A;
            #10
            s_i_arg_B = testcases_32_shift[i].B;
        end    
    $finish;
    end    
endmodule

SIGNALS/signals_przesuniecie.vcd
$date
	Thu Nov 23 01:24:26 2023
$end
$version
	Icarus Verilog
$end
$timescale
	1s
$end
$scope module przesuniecie_tb $end
$var wire 1 ! s_o_error_synthesis $end
$var wire 32 " s_o_synthesis [31:0] $end
$var wire 1 # s_o_overflow_synthesis $end
$var wire 1 $ s_o_overflow_model $end
$var wire 32 % s_o_model [31:0] $end
$var wire 1 & s_o_error_model $end
$var reg 32 ' s_i_arg_A [31:0] $end
$var reg 32 ( s_i_arg_B [31:0] $end
$scope module przesuniecie $end
$var wire 32 ) i_arg_A [31:0] $end
$var wire 32 * i_arg_B [31:0] $end
$var reg 1 & o_error $end
$var reg 1 $ o_overflow $end
$var reg 32 + o_result [31:0] $end
$upscope $end
$scope module przesuniecie_rtl $end
$var wire 1 , _00_ $end
$var wire 1 - _01_ $end
$var wire 1 . _02_ $end
$var wire 1 / _03_ $end
$var wire 1 0 _04_ $end
$var wire 1 1 _05_ $end
$var wire 1 2 _06_ $end
$var wire 1 3 _07_ $end
$var wire 1 4 _08_ $end
$var wire 1 5 _09_ $end
$var wire 1 6 _10_ $end
$var wire 1 7 _11_ $end
$var wire 1 8 _12_ $end
$var wire 1 9 _13_ $end
$var wire 1 : _14_ $end
$var wire 1 ; _15_ $end
$var wire 1 < _16_ $end
$var wire 1 = _17_ $end
$var wire 1 > _18_ $end
$var wire 1 ? _19_ $end
$var wire 1 @ _20_ $end
$var wire 1 A _21_ $end
$var wire 1 B _22_ $end
$var wire 1 C _23_ $end
$var wire 1 D _24_ $end
$var wire 1 E _25_ $end
$var wire 1 F _26_ $end
$var wire 1 G _27_ $end
$var wire 1 H _28_ $end
$var wire 1 I _29_ $end
$var wire 1 J _30_ $end
$var wire 1 K _31_ $end
$var wire 1 L _32_ $end
$var wire 32 M i_arg_A [31:0] $end
$var wire 32 N i_arg_B [31:0] $end
$var wire 1 ! o_error $end
$var wire 1 # o_overflow $end
$var wire 32 O o_result [31:0] $end
$upscope $end
$scope begin $ivl_for_loop0 $end
$var integer 32 P i [31:0] $end
$upscope $end
$scope begin $ivl_for_loop1 $end
$var integer 32 Q i [31:0] $end
$upscope $end
$scope begin $ivl_for_loop2 $end
$var integer 32 R i [31:0] $end
$upscope $end
$scope begin $ivl_for_loop3 $end
$var integer 32 S i [31:0] $end
$upscope $end
$scope begin $ivl_for_loop4 $end
$var integer 32 T i [31:0] $end
$upscope $end
$upscope $end
$enddefinitions $end
#0
$dumpvars
b0 T
b0 S
b0 R
b0 Q
b0 P
b0 O
b0 N
b0 M
0L
0K
0J
0I
0H
0G
0F
0E
0D
0C
0B
0A
0@
0?
0>
0=
0<
0;
0:
09
08
07
06
05
04
03
02
01
00
0/
0.
0-
0,
bx +
b0 *
b0 )
b0 (
b0 '
0&
bx %
1$
1#
b0 "
0!
$end
#2
b1 P
b10010 (
b10010 *
b10010 N
b1111111111111111111111111111111 '
b1111111111111111111111111111111 )
b1111111111111111111111111111111 M
#3
b10 P
b1000 (
b1000 *
b1000 N
#4
b11 P
b0 (
b0 *
b0 N
#5
1L
b100 P
b110 (
b110 *
b110 N
#6
0L
b101 P
b10000 (
b10000 *
b10000 N
#7
b1 Q
b0 (
b0 *
b0 N
#8
b10 Q
#9
b11 Q
#10
b100 Q
#11
b101 Q
#12
1,
17
1L
10
13
15
16
1:
1@
1B
b1 R
b11100011011011111100110011000111 (
b11100011011011111100110011000111 *
b11100011011011111100110011000111 N
#13
0,
07
0L
1.
00
03
05
06
0:
0@
0B
b10 R
b10011001011000010100001000110011 (
b10011001011000010100001000110011 *
b10011001011000010100001000110011 N
#14
0.
15
b11 R
b10000100100110111010100100001010 (
b10000100100110111010100100001010 *
b10000100100110111010100100001010 N
#15
12
05
16
1:
1?
b100 R
b11000000011110011111000110000001 (
b11000000011110011111000110000001 *
b11000000011110011111000110000001 N
#16
1,
17
1L
02
15
0?
1B
b101 R
b11000011011010111110011010000111 (
b11000011011010111110011010000111 *
b11000011011010111110011010000111 N
#17
07
0L
0,
1.
05
06
0:
0B
b1 S
b100000 (
b100000 *
b100000 N
b1101110110010001111110001011101 '
b1101110110010001111110001011101 )
b1101110110010001111110001011101 M
#18
b10 S
b1100111101000110111001101001111 '
b1100111101000110111001101001111 )
b1100111101000110111001101001111 M
#19
b11 S
b1111101101101010001010111111011 '
b1111101101101010001010111111011 )
b1111101101101010001010111111011 M
#20
b100 S
b1110001100010110111110111100011 '
b1110001100010110111110111100011 )
b1110001100010110111110111100011 M
#21
b101 S
b1111111001111110111101001111110 '
b1111111001111110111101001111110 )
b1111111001111110111101001111110 M
#22
1,
1L
15
1;
b1 T
b110001100110111001001001110111 (
b110001100110111001001001110111 *
b110001100110111001001001110111 N
b1111111111111111111111111111111 '
b1111111111111111111111111111111 )
b1111111111111111111111111111111 M
#23
17
16
1?
b10 T
b110001011110111100001001110111 (
b110001011110111100001001110111 *
b110001011110111100001001110111 N
#24
0,
07
0L
05
0;
0?
b11 T
b101010100010011110100101101011 (
b101010100010011110100101101011 *
b101010100010011110100101101011 N
#25
11
17
1/
10
12
15
1;
b100 T
b1111001010101111111101111110100 (
b1111001010101111111101111110100 *
b1111001010101111111101111110100 N
#26
01
07
0.
0/
00
05
06
0;
1<
1C
b101 T
b11101111010010011100101010101 (
b11101111010010011100101010101 *
b11101111010010011100101010101 N
#27
1.
02
0<
0C
b100000 (
b100000 *
b100000 N
b10000000000000000000000000000000 '
b10000000000000000000000000000000 )
b10000000000000000000000000000000 M
#28
b10000000000000000000000000000001 '
b10000000000000000000000000000001 )
b10000000000000000000000000000001 M
#29
b0 '
b0 )
b0 M
#30
b1 '
b1 )
b1 M
#31
1/
b100100110010110101100101001 (
b100100110010110101100101001 *
b100100110010110101100101001 N
b10000000000000000000000000000000 '
b10000000000000000000000000000000 )
b10000000000000000000000000000000 M
#32
1,
1D
1L
0.
0/
10
13
1?
1B
1C
b1100011111101100110110111001111 (
b1100011111101100110110111001111 *
b1100011111101100110110111001111 N
b10000000000000000000000000000001 '
b10000000000000000000000000000001 )
b10000000000000000000000000000001 M
#33
1=
0D
1K
0L
0,
1.
12
03
1;
1<
0?
0B
0C
b1111100100110000011010011111010 (
b1111100100110000011010011111010 *
b1111100100110000011010011111010 N
b0 '
b0 )
b0 M
#34
0=
1/
00
02
15
0<
1?
1B
b110011101110110100101101111011 (
b110011101110110100101101111011 *
b110011101110110100101101111011 N
b1 '
b1 )
b1 M
