RTL/ustawienie_rtl.sv
/* Generated by Yosys 0.36 (git sha1 8f07a0d8404, clang 14.0.0-1ubuntu1.1 -fPIC -Os) */

module ustawienie_rtl(i_arg_A, i_arg_B, o_result, o_error);
  wire _000_;
  wire _001_;
  wire _002_;
  wire _003_;
  wire _004_;
  wire _005_;
  wire _006_;
  wire _007_;
  wire _008_;
  wire _009_;
  wire _010_;
  wire _011_;
  wire _012_;
  wire _013_;
  wire _014_;
  wire _015_;
  wire _016_;
  wire _017_;
  wire _018_;
  wire _019_;
  wire _020_;
  wire _021_;
  wire _022_;
  wire _023_;
  wire _024_;
  wire _025_;
  wire _026_;
  wire _027_;
  wire _028_;
  wire _029_;
  wire _030_;
  wire _031_;
  wire _032_;
  wire _033_;
  wire _034_;
  wire _035_;
  wire _036_;
  wire _037_;
  wire _038_;
  wire _039_;
  wire _040_;
  wire _041_;
  wire _042_;
  wire _043_;
  wire _044_;
  wire _045_;
  wire _046_;
  wire _047_;
  wire _048_;
  wire _049_;
  wire _050_;
  wire _051_;
  wire _052_;
  wire _053_;
  wire _054_;
  wire _055_;
  wire _056_;
  wire _057_;
  wire _058_;
  wire _059_;
  wire _060_;
  wire _061_;
  wire _062_;
  wire _063_;
  wire _064_;
  wire _065_;
  wire _066_;
  wire _067_;
  wire _068_;
  wire _069_;
  wire _070_;
  wire _071_;
  wire _072_;
  wire _073_;
  wire _074_;
  wire _075_;
  wire _076_;
  wire _077_;
  wire _078_;
  wire _079_;
  wire _080_;
  wire _081_;
  wire _082_;
  wire _083_;
  wire _084_;
  wire _085_;
  wire _086_;
  wire _087_;
  wire _088_;
  wire _089_;
  wire _090_;
  wire _091_;
  wire _092_;
  wire _093_;
  wire _094_;
  wire _095_;
  wire _096_;
  wire _097_;
  wire _098_;
  wire _099_;
  wire _100_;
  wire _101_;
  wire _102_;
  wire _103_;
  wire _104_;
  wire _105_;
  wire _106_;
  wire _107_;
  wire _108_;
  wire _109_;
  wire _110_;
  wire _111_;
  wire _112_;
  wire _113_;
  wire _114_;
  wire _115_;
  wire _116_;
  wire _117_;
  wire _118_;
  wire _119_;
  wire _120_;
  wire _121_;
  wire _122_;
  wire _123_;
  wire _124_;
  wire _125_;
  wire _126_;
  wire _127_;
  wire _128_;
  wire _129_;
  wire _130_;
  wire _131_;
  wire _132_;
  wire _133_;
  wire _134_;
  wire _135_;
  wire _136_;
  wire _137_;
  wire _138_;
  wire _139_;
  wire _140_;
  wire _141_;
  wire _142_;
  wire _143_;
  wire _144_;
  wire _145_;
  wire _146_;
  wire _147_;
  wire _148_;
  wire _149_;
  wire _150_;
  wire _151_;
  wire _152_;
  wire _153_;
  wire _154_;
  wire _155_;
  wire _156_;
  wire _157_;
  wire _158_;
  wire _159_;
  wire _160_;
  wire _161_;
  wire _162_;
  wire _163_;
  wire _164_;
  wire _165_;
  wire _166_;
  wire _167_;
  wire _168_;
  wire _169_;
  wire _170_;
  wire _171_;
  wire _172_;
  wire _173_;
  wire _174_;
  wire _175_;
  wire _176_;
  wire _177_;
  wire _178_;
  wire _179_;
  wire _180_;
  wire _181_;
  wire _182_;
  wire _183_;
  wire _184_;
  wire _185_;
  wire _186_;
  wire _187_;
  wire _188_;
  wire _189_;
  wire _190_;
  wire _191_;
  wire _192_;
  wire _193_;
  wire _194_;
  input [31:0] i_arg_A;
  wire [31:0] i_arg_A;
  input [31:0] i_arg_B;
  wire [31:0] i_arg_B;
  wire i_arg_B_MSB;
  output o_error;
  wire o_error;
  output [31:0] o_result;
  wire [31:0] o_result;
  assign o_result[0] = ~i_arg_A[0];
  assign _194_ = ~i_arg_B[3];
  assign _000_ = ~i_arg_B[2];
  assign _001_ = ~i_arg_B[1];
  assign _002_ = ~i_arg_B[0];
  assign _003_ = ~i_arg_B[6];
  assign _004_ = ~i_arg_B[19];
  assign _005_ = ~i_arg_B[20];
  assign _006_ = ~i_arg_B[25];
  assign _007_ = ~i_arg_B[29];
  assign _008_ = ~i_arg_B[31];
  assign _009_ = ~i_arg_A[1];
  assign _010_ = ~i_arg_A[2];
  assign _011_ = ~i_arg_A[3];
  assign _012_ = ~i_arg_A[4];
  assign _013_ = ~i_arg_A[5];
  assign _014_ = ~i_arg_A[6];
  assign _015_ = ~i_arg_A[7];
  assign _016_ = ~i_arg_A[8];
  assign _017_ = ~i_arg_A[9];
  assign _018_ = ~i_arg_A[10];
  assign _019_ = ~i_arg_A[11];
  assign _020_ = ~i_arg_A[12];
  assign _021_ = ~i_arg_A[13];
  assign _022_ = ~i_arg_A[14];
  assign _023_ = ~i_arg_A[15];
  assign _024_ = ~i_arg_A[16];
  assign _025_ = ~i_arg_A[17];
  assign _026_ = ~i_arg_A[18];
  assign _027_ = ~i_arg_A[19];
  assign _028_ = ~i_arg_A[20];
  assign _029_ = ~i_arg_A[21];
  assign _030_ = ~i_arg_A[22];
  assign _031_ = ~i_arg_A[23];
  assign _032_ = ~i_arg_A[24];
  assign _033_ = ~i_arg_A[25];
  assign _034_ = ~i_arg_A[26];
  assign _035_ = ~i_arg_A[27];
  assign _036_ = ~i_arg_A[28];
  assign _037_ = ~i_arg_A[29];
  assign _038_ = ~i_arg_A[30];
  assign _039_ = ~i_arg_A[31];
  assign _040_ = _001_ & _002_;
  assign _041_ = i_arg_B[1] | i_arg_B[0];
  assign _042_ = _000_ & _040_;
  assign _043_ = i_arg_B[2] | _041_;
  assign _044_ = i_arg_B[3] | _043_;
  assign _045_ = ~_044_;
  assign _046_ = i_arg_B[4] | _044_;
  assign _047_ = i_arg_B[4] & _044_;
  assign _048_ = i_arg_B[5] | _047_;
  assign _049_ = ~_048_;
  assign _050_ = _046_ & _049_;
  assign _051_ = i_arg_B[3] ^ _043_;
  assign _052_ = _194_ ^ _043_;
  assign _053_ = i_arg_B[5] | i_arg_B[6];
  assign _054_ = i_arg_B[5] | _046_;
  assign _055_ = _046_ | _053_;
  assign _056_ = i_arg_B[17] | i_arg_B[18];
  assign _057_ = i_arg_B[15] | i_arg_B[14];
  assign _058_ = i_arg_B[13] | _056_;
  assign _059_ = i_arg_B[16] | i_arg_B[19];
  assign _060_ = _057_ | _059_;
  assign _061_ = _058_ | _060_;
  assign _062_ = i_arg_B[7] | i_arg_B[9];
  assign _063_ = i_arg_B[11] | i_arg_B[10];
  assign _064_ = i_arg_B[8] | i_arg_B[12];
  assign _065_ = _062_ | _064_;
  assign _066_ = _063_ | _065_;
  assign _067_ = _061_ | _066_;
  assign _068_ = _055_ | _067_;
  assign _069_ = i_arg_B[23] | i_arg_B[22];
  assign _070_ = i_arg_B[21] | i_arg_B[24];
  assign _071_ = i_arg_B[20] | i_arg_B[25];
  assign _072_ = _070_ | _071_;
  assign _073_ = _069_ | _072_;
  assign _074_ = _068_ | _073_;
  assign _075_ = i_arg_B[27] & i_arg_B[28];
  assign _076_ = _074_ & _075_;
  assign _077_ = _007_ | _076_;
  assign _078_ = i_arg_B[13] | _066_;
  assign _079_ = _055_ | _078_;
  assign _080_ = i_arg_B[14] & _079_;
  assign _081_ = i_arg_B[27] | i_arg_B[28];
  assign _082_ = i_arg_B[26] | i_arg_B[29];
  assign _083_ = _081_ | _082_;
  assign _084_ = i_arg_B[30] & _083_;
  assign _085_ = i_arg_B[15] | i_arg_B[16];
  assign _086_ = _056_ | _085_;
  assign _087_ = _004_ & _086_;
  assign _088_ = _007_ & _081_;
  assign _089_ = _005_ & i_arg_B[25];
  assign _090_ = i_arg_B[19] | i_arg_B[31];
  assign _091_ = _089_ | _090_;
  assign _092_ = _088_ | _091_;
  assign _093_ = _087_ | _092_;
  assign _094_ = _084_ | _093_;
  assign _095_ = _078_ | _094_;
  assign _096_ = _080_ | _095_;
  assign _097_ = _003_ ^ _054_;
  assign _098_ = i_arg_B[20] & _068_;
  assign _099_ = _097_ | _098_;
  assign _100_ = _096_ | _099_;
  assign _101_ = ~_100_;
  assign _102_ = _077_ & _101_;
  assign _103_ = i_arg_B[20] & _097_;
  assign _104_ = _069_ | _070_;
  assign _105_ = _103_ | _104_;
  assign _106_ = ~_105_;
  assign _107_ = i_arg_B[25] | _106_;
  assign _108_ = i_arg_B[26] | _007_;
  assign _109_ = i_arg_B[26] | i_arg_B[30];
  assign _110_ = _074_ & _109_;
  assign _111_ = ~_110_;
  assign _112_ = i_arg_B[30] | _083_;
  assign _113_ = _074_ | _112_;
  assign _114_ = i_arg_B[21] & i_arg_B[23];
  assign _115_ = i_arg_B[22] & i_arg_B[24];
  assign _116_ = _114_ & _115_;
  assign _117_ = _068_ & _116_;
  assign _118_ = _006_ | _117_;
  assign _119_ = _113_ & _118_;
  assign _120_ = _111_ & _119_;
  assign _121_ = _108_ & _120_;
  assign _122_ = _107_ & _121_;
  assign _123_ = _102_ & _122_;
  assign _124_ = _001_ & i_arg_B[0];
  assign _125_ = _123_ & _124_;
  assign _126_ = _000_ & _125_;
  assign _127_ = _051_ & _126_;
  assign _128_ = _050_ & _127_;
  assign o_result[1] = _009_ | _128_;
  assign _129_ = i_arg_B[1] & _123_;
  assign _130_ = _002_ & _129_;
  assign _131_ = _000_ & _130_;
  assign _132_ = _051_ & _131_;
  assign _133_ = _050_ & _132_;
  assign o_result[2] = _010_ | _133_;
  assign _134_ = i_arg_B[0] & _129_;
  assign _135_ = _000_ & _134_;
  assign _136_ = _051_ & _135_;
  assign _137_ = _050_ & _136_;
  assign o_result[3] = _011_ | _137_;
  assign _138_ = i_arg_B[2] & _040_;
  assign _139_ = _123_ & _138_;
  assign _140_ = _194_ & _139_;
  assign _141_ = _050_ & _140_;
  assign o_result[4] = _012_ | _141_;
  assign _142_ = i_arg_B[2] & _125_;
  assign _143_ = _194_ & _142_;
  assign _144_ = _050_ & _143_;
  assign o_result[5] = _013_ | _144_;
  assign _145_ = i_arg_B[2] & _130_;
  assign _146_ = _194_ & _145_;
  assign _147_ = _050_ & _146_;
  assign o_result[6] = _014_ | _147_;
  assign _148_ = i_arg_B[2] & _134_;
  assign _149_ = _194_ & _148_;
  assign _150_ = _050_ & _149_;
  assign o_result[7] = _015_ | _150_;
  assign _151_ = i_arg_B[3] & _042_;
  assign _152_ = _123_ & _151_;
  assign _153_ = _050_ & _152_;
  assign o_result[8] = _016_ | _153_;
  assign _154_ = _052_ & _126_;
  assign _155_ = _050_ & _154_;
  assign o_result[9] = _017_ | _155_;
  assign _156_ = _052_ & _131_;
  assign _157_ = _050_ & _156_;
  assign o_result[10] = _018_ | _157_;
  assign _158_ = _052_ & _135_;
  assign _159_ = _050_ & _158_;
  assign o_result[11] = _019_ | _159_;
  assign _160_ = i_arg_B[3] & _139_;
  assign _161_ = _050_ & _160_;
  assign o_result[12] = _020_ | _161_;
  assign _162_ = i_arg_B[3] & _142_;
  assign _163_ = _050_ & _162_;
  assign o_result[13] = _021_ | _163_;
  assign _164_ = i_arg_B[3] & _145_;
  assign _165_ = _050_ & _164_;
  assign o_result[14] = _022_ | _165_;
  assign _166_ = i_arg_B[3] & _148_;
  assign _167_ = _050_ & _166_;
  assign o_result[15] = _023_ | _167_;
  assign _168_ = _045_ & _050_;
  assign _169_ = _123_ & _168_;
  assign o_result[16] = _024_ | _169_;
  assign _170_ = i_arg_B[5] & _046_;
  assign _171_ = ~_170_;
  assign _172_ = _048_ & _171_;
  assign _173_ = _127_ & _172_;
  assign o_result[17] = _025_ | _173_;
  assign _174_ = _132_ & _172_;
  assign o_result[18] = _026_ | _174_;
  assign _175_ = _136_ & _172_;
  assign o_result[19] = _027_ | _175_;
  assign _176_ = _140_ & _172_;
  assign o_result[20] = _028_ | _176_;
  assign _177_ = _143_ & _172_;
  assign o_result[21] = _029_ | _177_;
  assign _178_ = _146_ & _172_;
  assign o_result[22] = _030_ | _178_;
  assign _179_ = _149_ & _172_;
  assign o_result[23] = _031_ | _179_;
  assign _180_ = _152_ & _172_;
  assign o_result[24] = _032_ | _180_;
  assign _181_ = _154_ & _172_;
  assign o_result[25] = _033_ | _181_;
  assign _182_ = _156_ & _172_;
  assign o_result[26] = _034_ | _182_;
  assign _183_ = _158_ & _172_;
  assign o_result[27] = _035_ | _183_;
  assign _184_ = _160_ & _172_;
  assign o_result[28] = _036_ | _184_;
  assign _185_ = _162_ & _172_;
  assign o_result[29] = _037_ | _185_;
  assign _186_ = _164_ & _172_;
  assign o_result[30] = _038_ | _186_;
  assign _187_ = _166_ & _172_;
  assign o_result[31] = _039_ | _187_;
  assign _188_ = i_arg_B[30] | _053_;
  assign _189_ = _083_ | _188_;
  assign _190_ = _073_ | _189_;
  assign _191_ = _067_ | _190_;
  assign _192_ = _008_ & _191_;
  assign _193_ = i_arg_B[31] & _113_;
  assign o_error = _192_ | _193_;
  assign i_arg_B_MSB = i_arg_B[31];
endmodule

WORK/Verilog_modul_ustawienie/ustawienie.sv
//moduł ustawienia bitu w liczbie i_arg_A na 1, na indeksie wskazanym przez i_arg_B
module ustawienie (i_arg_A, i_arg_B, o_result, o_error);

//deklaracja parametrów
parameter BITS = 32;
localparam MOD_NUMBER = BITS -1;

//deklaracja wejść, wyjść i flag
    input logic signed [BITS-1:0] i_arg_A;
    input logic signed [BITS-1:0] i_arg_B;
    output logic signed [BITS-1:0] o_result;
    output logic o_error;
    logic [BITS-1:0] tymczasowy_rejestr;
    wire logic i_arg_B_MSB;

    assign i_arg_B_MSB = i_arg_B[BITS-1];

    //blok opisujący logikę
    always_comb begin 

        //defaultowe ustawienie wartości wyjść i rejestru tymczasowego
        o_result = 'bx;
        o_error = 0;
        tymczasowy_rejestr = '0;

        //jak B jest ujemne, to ustawiamy flagę błędu
        if (i_arg_B_MSB == 1 && i_arg_B != {1'b1, {MOD_NUMBER{1'b0}}}) begin
            o_error = 1;
        end

        //jak B jest większe od 31, to ustawiamy flagę błędu
        else if (i_arg_B > BITS-1) begin
            o_error = 1;
        end

        //inna reprezentacja B, to samo postępowanie, co wpadnięcie w zakres
        else if (i_arg_B == {MOD_NUMBER{1'b0}}) begin
            tymczasowy_rejestr[i_arg_B] = 0;
            o_result = tymczasowy_rejestr|(~i_arg_A);
        end

        //inna reprezentacja B, to samo postępowanie, co wpadnięcie w zakres 
        else if (i_arg_B == {1'b1, {MOD_NUMBER{1'b0}}}) begin
            tymczasowy_rejestr[i_arg_B] = 0;
            o_result = tymczasowy_rejestr|(~i_arg_A);
        end

        //jak B wpada w zakres, to ustawiamy tego bita
        else if ((i_arg_B>0) && i_arg_B<BITS) begin
            tymczasowy_rejestr[i_arg_B] = 1;
            o_result = tymczasowy_rejestr|(~i_arg_A);
        end

    end

endmodule

TEST/ustawienie_tb.sv
// testbench modułu ustawienia bitu na 1 na bicie i_arg_A o indeksie i_arg_B
// zaczynamy ławeczkę testową
module ustawienie_tb;
    parameter BITS = 32;
    localparam TOP = 2**(BITS-1)-1;
    localparam BOTTOM = -(2**(BITS-1)-1);
    localparam MOD_NUMBER = BITS-1;

    // sygnały wewnętrzne dla tej konketnej ławeczki testowej 
    logic [BITS-1:0] s_i_arg_A;
    logic [BITS-1:0] s_i_arg_B;
    logic            s_o_error_model;
    logic            s_o_error_synthesis;
    logic [BITS-1:0] s_o_model;
    logic [BITS-1:0] s_o_synthesis;
    integer i;

    // instancjowanie wejść i wyjść, jawne przypisywanie portów
    ustawienie #(.BITS(BITS))        
    ustawienie (
        .i_arg_A(s_i_arg_A), 
        .i_arg_B(s_i_arg_B), 
        .o_result(s_o_model), 
        .o_error(s_o_error_model)
        );    

    ustawienie_rtl           
    ustawienie_rtl (
        .i_arg_A(s_i_arg_A), 
        .i_arg_B(s_i_arg_B), 
        .o_result(s_o_synthesis), 
        .o_error(s_o_error_synthesis)
        );

    // Dostarczenie zmiennych do testu, rozpoczęcie bloku initial
    initial begin
        s_i_arg_A = '1;
        s_i_arg_B = 0;

        //w tym pliku zostaną zapisane zapisane sygnały zarejestrowane w symulacji
        $dumpfile("signals_ustawienie.vcd");  

        //Wskazania, że wszystkie sygnały z testbench i niżej mają być rejestrowane podczas symulacji
        $dumpvars(0, ustawienie_tb);       

        //najpierw testujemy przypadek idealny, na zerze najłatwiej zauważyć
        for (int i=0; i<6; i++) begin
            #1  
            s_i_arg_A = '1;
            s_i_arg_B = $urandom_range(1, BITS-1);
        end
        //teraz zobaczymy przypadki losowe dla liczb ujemnych 
        for (i=0; i<6; i++) begin
            #1  
            s_i_arg_B = $urandom_range(BOTTOM, -1);
        end

        //teraz zobaczymy przypadki losowe dla liczb >=32
        for (i=0; i<6; i++) begin
            #1  
            s_i_arg_B = $urandom_range(BITS, TOP);
        end

        //teraz zobaczymy przypadki losowe dla różnych reprezentacji 0, gdy B=0
        //zawartość A w każdym momencie tego modułu nie ma najmniejszego znaczenia
            #1  
            s_i_arg_B = {BITS{1'b0}};
            #1
            s_i_arg_B = {1'b1, {MOD_NUMBER{1'b0}}};
            #1

        $finish;
    end
endmodule

SIGNALS/signals_ustawienie.vcd
$date
	Tue Dec 19 16:59:42 2023
$end
$version
	Icarus Verilog
$end
$timescale
	1s
$end
$scope module ustawienie_tb $end
$var wire 32 ! s_o_synthesis [31:0] $end
$var wire 32 " s_o_model [31:0] $end
$var wire 1 # s_o_error_synthesis $end
$var wire 1 $ s_o_error_model $end
$var parameter 32 % BITS $end
$var parameter 34 & BOTTOM $end
$var parameter 33 ' MOD_NUMBER $end
$var parameter 34 ( TOP $end
$var reg 32 ) s_i_arg_A [31:0] $end
$var reg 32 * s_i_arg_B [31:0] $end
$var integer 32 + i [31:0] $end
$scope module ustawienie $end
$var wire 32 , i_arg_A [31:0] $end
$var wire 32 - i_arg_B [31:0] $end
$var wire 1 . i_arg_B_MSB $end
$var parameter 32 / BITS $end
$var parameter 33 0 MOD_NUMBER $end
$var reg 1 $ o_error $end
$var reg 32 1 o_result [31:0] $end
$var reg 32 2 tymczasowy_rejestr [31:0] $end
$upscope $end
$scope module ustawienie_rtl $end
$var wire 1 3 _000_ $end
$var wire 1 4 _001_ $end
$var wire 1 5 _002_ $end
$var wire 1 6 _003_ $end
$var wire 1 7 _004_ $end
$var wire 1 8 _005_ $end
$var wire 1 9 _006_ $end
$var wire 1 : _007_ $end
$var wire 1 ; _008_ $end
$var wire 1 < _009_ $end
$var wire 1 = _010_ $end
$var wire 1 > _011_ $end
$var wire 1 ? _012_ $end
$var wire 1 @ _013_ $end
$var wire 1 A _014_ $end
$var wire 1 B _015_ $end
$var wire 1 C _016_ $end
$var wire 1 D _017_ $end
$var wire 1 E _018_ $end
$var wire 1 F _019_ $end
$var wire 1 G _020_ $end
$var wire 1 H _021_ $end
$var wire 1 I _022_ $end
$var wire 1 J _023_ $end
$var wire 1 K _024_ $end
$var wire 1 L _025_ $end
$var wire 1 M _026_ $end
$var wire 1 N _027_ $end
$var wire 1 O _028_ $end
$var wire 1 P _029_ $end
$var wire 1 Q _030_ $end
$var wire 1 R _031_ $end
$var wire 1 S _032_ $end
$var wire 1 T _033_ $end
$var wire 1 U _034_ $end
$var wire 1 V _035_ $end
$var wire 1 W _036_ $end
$var wire 1 X _037_ $end
$var wire 1 Y _038_ $end
$var wire 1 Z _039_ $end
$var wire 1 [ _040_ $end
$var wire 1 \ _041_ $end
$var wire 1 ] _042_ $end
$var wire 1 ^ _043_ $end
$var wire 1 _ _044_ $end
$var wire 1 ` _045_ $end
$var wire 1 a _046_ $end
$var wire 1 b _047_ $end
$var wire 1 c _048_ $end
$var wire 1 d _049_ $end
$var wire 1 e _050_ $end
$var wire 1 f _051_ $end
$var wire 1 g _052_ $end
$var wire 1 h _053_ $end
$var wire 1 i _054_ $end
$var wire 1 j _055_ $end
$var wire 1 k _056_ $end
$var wire 1 l _057_ $end
$var wire 1 m _058_ $end
$var wire 1 n _059_ $end
$var wire 1 o _060_ $end
$var wire 1 p _061_ $end
$var wire 1 q _062_ $end
$var wire 1 r _063_ $end
$var wire 1 s _064_ $end
$var wire 1 t _065_ $end
$var wire 1 u _066_ $end
$var wire 1 v _067_ $end
$var wire 1 w _068_ $end
$var wire 1 x _069_ $end
$var wire 1 y _070_ $end
$var wire 1 z _071_ $end
$var wire 1 { _072_ $end
$var wire 1 | _073_ $end
$var wire 1 } _074_ $end
$var wire 1 ~ _075_ $end
$var wire 1 !" _076_ $end
$var wire 1 "" _077_ $end
$var wire 1 #" _078_ $end
$var wire 1 $" _079_ $end
$var wire 1 %" _080_ $end
$var wire 1 &" _081_ $end
$var wire 1 '" _082_ $end
$var wire 1 (" _083_ $end
$var wire 1 )" _084_ $end
$var wire 1 *" _085_ $end
$var wire 1 +" _086_ $end
$var wire 1 ," _087_ $end
$var wire 1 -" _088_ $end
$var wire 1 ." _089_ $end
$var wire 1 /" _090_ $end
$var wire 1 0" _091_ $end
$var wire 1 1" _092_ $end
$var wire 1 2" _093_ $end
$var wire 1 3" _094_ $end
$var wire 1 4" _095_ $end
$var wire 1 5" _096_ $end
$var wire 1 6" _097_ $end
$var wire 1 7" _098_ $end
$var wire 1 8" _099_ $end
$var wire 1 9" _100_ $end
$var wire 1 :" _101_ $end
$var wire 1 ;" _102_ $end
$var wire 1 <" _103_ $end
$var wire 1 =" _104_ $end
$var wire 1 >" _105_ $end
$var wire 1 ?" _106_ $end
$var wire 1 @" _107_ $end
$var wire 1 A" _108_ $end
$var wire 1 B" _109_ $end
$var wire 1 C" _110_ $end
$var wire 1 D" _111_ $end
$var wire 1 E" _112_ $end
$var wire 1 F" _113_ $end
$var wire 1 G" _114_ $end
$var wire 1 H" _115_ $end
$var wire 1 I" _116_ $end
$var wire 1 J" _117_ $end
$var wire 1 K" _118_ $end
$var wire 1 L" _119_ $end
$var wire 1 M" _120_ $end
$var wire 1 N" _121_ $end
$var wire 1 O" _122_ $end
$var wire 1 P" _123_ $end
$var wire 1 Q" _124_ $end
$var wire 1 R" _125_ $end
$var wire 1 S" _126_ $end
$var wire 1 T" _127_ $end
$var wire 1 U" _128_ $end
$var wire 1 V" _129_ $end
$var wire 1 W" _130_ $end
$var wire 1 X" _131_ $end
$var wire 1 Y" _132_ $end
$var wire 1 Z" _133_ $end
$var wire 1 [" _134_ $end
$var wire 1 \" _135_ $end
$var wire 1 ]" _136_ $end
$var wire 1 ^" _137_ $end
$var wire 1 _" _138_ $end
$var wire 1 `" _139_ $end
$var wire 1 a" _140_ $end
$var wire 1 b" _141_ $end
$var wire 1 c" _142_ $end
$var wire 1 d" _143_ $end
$var wire 1 e" _144_ $end
$var wire 1 f" _145_ $end
$var wire 1 g" _146_ $end
$var wire 1 h" _147_ $end
$var wire 1 i" _148_ $end
$var wire 1 j" _149_ $end
$var wire 1 k" _150_ $end
$var wire 1 l" _151_ $end
$var wire 1 m" _152_ $end
$var wire 1 n" _153_ $end
$var wire 1 o" _154_ $end
$var wire 1 p" _155_ $end
$var wire 1 q" _156_ $end
$var wire 1 r" _157_ $end
$var wire 1 s" _158_ $end
$var wire 1 t" _159_ $end
$var wire 1 u" _160_ $end
$var wire 1 v" _161_ $end
$var wire 1 w" _162_ $end
$var wire 1 x" _163_ $end
$var wire 1 y" _164_ $end
$var wire 1 z" _165_ $end
$var wire 1 {" _166_ $end
$var wire 1 |" _167_ $end
$var wire 1 }" _168_ $end
$var wire 1 ~" _169_ $end
$var wire 1 !# _170_ $end
$var wire 1 "# _171_ $end
$var wire 1 ## _172_ $end
$var wire 1 $# _173_ $end
$var wire 1 %# _174_ $end
$var wire 1 &# _175_ $end
$var wire 1 '# _176_ $end
$var wire 1 (# _177_ $end
$var wire 1 )# _178_ $end
$var wire 1 *# _179_ $end
$var wire 1 +# _180_ $end
$var wire 1 ,# _181_ $end
$var wire 1 -# _182_ $end
$var wire 1 .# _183_ $end
$var wire 1 /# _184_ $end
$var wire 1 0# _185_ $end
$var wire 1 1# _186_ $end
$var wire 1 2# _187_ $end
$var wire 1 3# _188_ $end
$var wire 1 4# _189_ $end
$var wire 1 5# _190_ $end
$var wire 1 6# _191_ $end
$var wire 1 7# _192_ $end
$var wire 1 8# _193_ $end
$var wire 1 9# _194_ $end
$var wire 32 :# i_arg_A [31:0] $end
$var wire 32 ;# i_arg_B [31:0] $end
$var wire 1 # o_error $end
$var wire 32 <# o_result [31:0] $end
$var wire 1 =# i_arg_B_MSB $end
$upscope $end
$scope begin $ivl_for_loop0 $end
$var integer 32 ># i [31:0] $end
$upscope $end
$upscope $end
$enddefinitions $end
$comment Show the parameter values. $end
$dumpall
b11111 0
b100000 /
b1111111111111111111111111111111 (
b11111 '
b1110000000000000000000000000000001 &
b100000 %
$end
#0
$dumpvars
b0 >#
0=#
b0 <#
b0 ;#
b11111111111111111111111111111111 :#
19#
08#
07#
06#
05#
04#
03#
02#
01#
00#
0/#
0.#
0-#
0,#
0+#
0*#
0)#
0(#
0'#
0&#
0%#
0$#
0##
1"#
0!#
0~"
0}"
0|"
0{"
0z"
0y"
0x"
0w"
0v"
0u"
0t"
0s"
0r"
0q"
0p"
0o"
0n"
0m"
0l"
0k"
0j"
0i"
0h"
0g"
0f"
0e"
0d"
0c"
0b"
0a"
0`"
0_"
0^"
0]"
0\"
0["
0Z"
0Y"
0X"
0W"
0V"
0U"
0T"
0S"
0R"
0Q"
0P"
0O"
0N"
0M"
0L"
1K"
0J"
0I"
0H"
0G"
0F"
0E"
1D"
0C"
0B"
1A"
1@"
1?"
0>"
0="
0<"
0;"
0:"
19"
18"
07"
16"
05"
04"
03"
02"
01"
00"
0/"
0."
0-"
0,"
0+"
0*"
0)"
0("
0'"
0&"
0%"
0$"
0#"
1""
0!"
0~
0}
0|
0{
0z
0y
0x
0w
0v
0u
0t
0s
0r
0q
0p
0o
0n
0m
0l
0k
0j
0i
0h
1g
0f
0e
1d
0c
0b
0a
1`
0_
0^
1]
0\
1[
0Z
0Y
0X
0W
0V
0U
0T
0S
0R
0Q
0P
0O
0N
0M
0L
0K
0J
0I
0H
0G
0F
0E
0D
0C
0B
0A
0@
0?
0>
0=
0<
1;
1:
19
18
17
16
15
14
13
b0 2
b0 1
0.
b0 -
b11111111111111111111111111111111 ,
bx +
b0 *
b11111111111111111111111111111111 )
0$
0#
b0 "
b0 !
$end
#1
b1000000000000000000 !
b1000000000000000000 <#
1%#
1Y"
1X"
1W"
1V"
1P"
1O"
1N"
1;"
1M"
0d
1##
1:"
1L"
1c
09"
1F"
0`
1b
08"
1}
0]
1_
1f
0g
0}"
06"
1w
1$"
0[
1^
0e
1i
1j
04
1\
1a
b1000000000000000000 2
b1000000000000000000 "
b1000000000000000000 1
b1 >#
b10010 *
b10010 -
b10010 ;#
#2
1n"
1m"
1l"
1e
b100000000 !
b100000000 <#
1]
1d
0##
0%#
0X"
1[
0^
0c
0Y"
0W"
09#
14
0\
0b
1f
0V"
b100000000 2
b100000000 "
b100000000 1
b10 >#
b1000 *
b1000 -
b1000 ;#
#3
1O"
1P"
1N"
1;"
1M"
1:"
1L"
1U"
09"
1F"
08"
1}
06"
1w
1$"
1T"
b10 !
b10 <#
0]
1e
1i
1j
1S"
0n"
0[
1^
0`
1a
1R"
0m"
19#
05
1\
1_
1f
1Q"
0l"
b10 2
b10 "
b10 1
b11 >#
b1 *
b1 -
b1 ;#
#4
1k"
0U"
1j"
b10000000 !
b10000000 <#
0T"
0R"
1i"
0e"
0S"
0Q"
1["
0d"
03
04
1V"
0c"
b10000000 2
b10000000 "
b10000000 1
b100 >#
b111 *
b111 -
b111 ;#
#5
1$#
1T"
1S"
0e
b100000000000000000 !
b100000000000000000 <#
1R"
0d
1##
0k"
1Q"
1c
0["
0j"
13
14
1b
0V"
0i"
b100000000000000000 2
b100000000000000000 "
b100000000000000000 1
b101 >#
b10001 *
b10001 -
b10001 ;#
#6
1,#
b10000000000000000000000000 !
b10000000000000000000000000 <#
1o"
0$#
1g
0T"
09#
0f
b10000000000000000000000000 2
b10000000000000000000000000 "
b10000000000000000000000000 1
b0 +
b110 >#
b11001 *
b11001 -
b11001 ;#
#7
0O"
0P"
14"
0@"
0;"
13"
b0 !
b0 <#
0S"
1v
1#"
16#
0?"
0:"
12"
0]"
0,#
0o"
0R"
1p
1u
15#
1>"
19"
1E"
14#
1,"
11"
0\"
0##
0g
0Q"
0T"
13#
1o
1t
1|
1{
1="
1!"
15"
1("
1-"
1+"
10"
0["
0"#
1#
19#
04
0;
1f
1h
1l
1n
1q
1x
1y
1~
1%"
1&"
1*"
1/"
1H"
0V"
1!#
18#
1$
b0 2
bx "
bx 1
1.
1=#
b1 +
b10011001011000010100001000110011 *
b10011001011000010100001000110011 -
b10011001011000010100001000110011 ;#
#8
0N"
1e
0M"
1d
0D"
1g
0,"
0c
03#
0!"
0-"
18"
1C"
1"#
09#
15
07
08
0b
0f
0h
1k
1m
0q
1r
1s
0y
1z
0~
0%"
0&"
1'"
17"
1B"
0H"
0!#
1$
b10 +
b10000100100110111010100100001010 *
b10000100100110111010100100001010 -
b10000100100110111010100100001010 ;#
#9
0g
1Q"
0("
19#
14
05
1f
0k
1q
0r
1y
1%"
0'"
0)"
13#
1$
b11 +
b11000000011110011111000110000001 *
b11000000011110011111000110000001 -
b11000000011110011111000110000001 ;#
#10
0L"
0Q"
1."
0K"
08"
03
04
18
09
1k
1r
0s
07"
1@"
1H"
1$
b100 +
b11000011011010111110011010000111 *
b11000011011010111110011010000111 -
b11000011011010111110011010000111 ;#
#11
1L"
0e
1)"
1g
1,"
1K"
0d
1!"
1-"
1("
18"
0"#
09#
13
17
08
19
1b
1c
0f
1h
0k
1s
1~
1&"
1'"
0."
17"
0@"
0H"
1!#
1$
b101 +
b11011101100100011111100010111011 *
b11011101100100011111100010111011 -
b11011101100100011111100010111011 ;#
#12
0L"
1##
1."
0K"
0!"
08"
1"#
03
15
18
09
0h
1k
0n
0s
0~
07"
1@"
1H"
0!#
1$
b0 +
b11001111010001101110011010011110 *
b11001111010001101110011010011110 -
b11001111010001101110011010011110 ;#
