WORK/Verilog_modul_konwersja/konwersja_rtl.sv
/* Generated by Yosys 0.9 (git sha1 1979e0b) */

module konwersja_rtl(i_arg_A, o_result, o_error);
  wire _000_;
  wire _001_;
  wire _002_;
  wire _003_;
  wire _004_;
  wire _005_;
  wire _006_;
  wire _007_;
  wire _008_;
  wire _009_;
  wire _010_;
  wire _011_;
  wire _012_;
  wire _013_;
  wire _014_;
  wire _015_;
  wire _016_;
  wire _017_;
  wire _018_;
  wire _019_;
  wire _020_;
  wire _021_;
  wire _022_;
  wire _023_;
  wire _024_;
  wire _025_;
  wire _026_;
  wire _027_;
  wire _028_;
  wire _029_;
  wire _030_;
  wire _031_;
  wire _032_;
  wire _033_;
  wire _034_;
  wire _035_;
  wire _036_;
  wire _037_;
  input [31:0] i_arg_A;
  wire i_arg_A_MSB;
  wire i_arg_A_MSB_2;
  wire [30:0] i_arg_A_REST;
  output o_error;
  output [31:0] o_result;
  assign _033_ = ~i_arg_A[30];
  assign _034_ = ~i_arg_A[31];
  assign _035_ = i_arg_A[0] | i_arg_A[31];
  assign _036_ = _033_ & i_arg_A[31];
  assign _037_ = i_arg_A[30] | _034_;
  assign o_result[0] = _035_ & _037_;
  assign o_result[1] = i_arg_A[31] | i_arg_A[1];
  assign o_result[2] = _034_ & i_arg_A[2];
  assign o_result[3] = _034_ & i_arg_A[3];
  assign o_result[4] = _034_ & i_arg_A[4];
  assign o_result[5] = _034_ & i_arg_A[5];
  assign o_result[6] = _034_ & i_arg_A[6];
  assign o_result[7] = _034_ & i_arg_A[7];
  assign o_result[8] = _034_ & i_arg_A[8];
  assign o_result[9] = _034_ & i_arg_A[9];
  assign o_result[10] = _034_ & i_arg_A[10];
  assign o_result[11] = _034_ & i_arg_A[11];
  assign o_result[12] = _034_ & i_arg_A[12];
  assign o_result[13] = _034_ & i_arg_A[13];
  assign o_result[14] = _034_ & i_arg_A[14];
  assign o_result[15] = _034_ & i_arg_A[15];
  assign o_result[16] = _034_ & i_arg_A[16];
  assign o_result[17] = _034_ & i_arg_A[17];
  assign o_result[18] = _034_ & i_arg_A[18];
  assign o_result[19] = _034_ & i_arg_A[19];
  assign o_result[20] = _034_ & i_arg_A[20];
  assign o_result[21] = _034_ & i_arg_A[21];
  assign o_result[22] = _034_ & i_arg_A[22];
  assign o_result[23] = _034_ & i_arg_A[23];
  assign o_result[24] = _034_ & i_arg_A[24];
  assign o_result[25] = _034_ & i_arg_A[25];
  assign o_result[26] = _034_ & i_arg_A[26];
  assign o_result[27] = _034_ & i_arg_A[27];
  assign o_result[28] = _034_ & i_arg_A[28];
  assign o_result[29] = _034_ & i_arg_A[29];
  assign o_result[30] = i_arg_A[30] & _034_;
  assign _000_ = i_arg_A[18] | i_arg_A[19];
  assign _001_ = i_arg_A[20] | i_arg_A[21];
  assign _002_ = _000_ | _001_;
  assign _003_ = i_arg_A[14] | i_arg_A[15];
  assign _004_ = i_arg_A[16] | i_arg_A[17];
  assign _005_ = _003_ | _004_;
  assign _006_ = _002_ | _005_;
  assign _007_ = i_arg_A[26] | i_arg_A[27];
  assign _008_ = i_arg_A[28] | i_arg_A[29];
  assign _009_ = _007_ | _008_;
  assign _010_ = i_arg_A[22] | i_arg_A[23];
  assign _011_ = i_arg_A[24] | i_arg_A[25];
  assign _012_ = _010_ | _011_;
  assign _013_ = _009_ | _012_;
  assign _014_ = _006_ | _013_;
  assign _015_ = ~_014_;
  assign _016_ = i_arg_A[2] | i_arg_A[3];
  assign _017_ = i_arg_A[4] | i_arg_A[5];
  assign _018_ = _016_ | _017_;
  assign _019_ = ~_018_;
  assign _020_ = i_arg_A[0] | i_arg_A[1];
  assign _021_ = ~_020_;
  assign _022_ = _036_ & _021_;
  assign _023_ = _019_ & _022_;
  assign _024_ = i_arg_A[10] | i_arg_A[11];
  assign _025_ = i_arg_A[12] | i_arg_A[13];
  assign _026_ = _024_ | _025_;
  assign _027_ = i_arg_A[6] | i_arg_A[7];
  assign _028_ = i_arg_A[8] | i_arg_A[9];
  assign _029_ = _027_ | _028_;
  assign _030_ = _026_ | _029_;
  assign _031_ = ~_030_;
  assign _032_ = _023_ & _031_;
  assign o_error = _015_ & _032_;
  assign i_arg_A_MSB = i_arg_A[31];
  assign i_arg_A_MSB_2 = i_arg_A[30];
  assign i_arg_A_REST = i_arg_A[30:0];
  assign o_result[31] = 1'h0;
endmodule

MODEL/konwersja.sv
// moduł konwersji liczby A zapisanej w kodzie ZM na liczbę kodowaną w U2

//nasz maksymalny zakresik konwersji:
//<-(2^30)+1, 2^30-1>
module konwersja (i_arg_A, o_result, o_error);

    //zadeklarowanie szerokości wektora wejścia
    parameter BITS = 32;

    //zadeklarowanie wejścia i wyjść
    input logic signed [BITS-1:0] i_arg_A;
    output logic [BITS-1:0] o_result;
    output logic o_error;    

    wire logic i_arg_A_MSB;
    wire logic i_arg_A_MSB_2;
    wire [BITS-2:0] i_arg_A_REST;

    assign  i_arg_A_MSB = i_arg_A[BITS-1];
    assign  i_arg_A_MSB_2 = i_arg_A[BITS-2];
    assign  i_arg_A_REST = i_arg_A[BITS-2:0];

    //blok opisujący logikę
    always_comb begin
        //defaultowe ustawienie wartości wyjścia i wejścia
        o_result = 'bx;
        o_error = 0;

        //sytuacja, jak mamy dodatnią liczbę kodowaną w typie ZM, to nic nie trzeba robić
        if (i_arg_A_MSB == 0) begin
            o_result = i_arg_A;
        end
    
        //sytuacja, jak mamy ujemną liczbę kodowaną w ZM, to korzystamy z formuły
        //wyjscie = {1'b1, ~i_arg_A[BITS-2] +1'b1}
        //mamy w ogóle jakiekolwiek wyjście, dopóki nam się zero ujemne nie wylosuje. 
        //nie ma takiej opcji, że on poprawnie przekonwertuje mi {1'b1, '0}
        else if (i_arg_A_MSB == 1 && |i_arg_A_REST != 0) begin
            o_result = {1'b1, (~i_arg_A_MSB_2) +1'b1};
        end
        else begin 
            o_error = 1;
        end
    end
endmodule

TEST/konwersja_tb.sv
//testbench dla modułu konwersji
//wstępnie przewidziany z kilkoma testami warunków brzegowych
module konwersja_tb;

    parameter BITS = 32;
    localparam MOD_NUMBER = BITS-1;

    // sygnały wewnętrzne i ich atrybuty
    logic [BITS-1:0] s_i_arg_A;
    logic [BITS-1:0] s_o_model;
    logic [BITS-1:0] s_o_synthesis;
    logic            s_o_error_model;
    logic            s_o_error_synthesis;
    integer i;

    // instancjowanie wejść i wyjść, jawne przypisywanie portów
    konwersja     #(.BITS(BITS))        
    konwersja (
        .i_arg_A(s_i_arg_A), 
        .o_result(s_o_model), 
        .o_error(s_o_error_model)
        );

    konwersja_rtl           
    konwersja_rtl (
        .i_arg_A(s_i_arg_A), 
        .o_result(s_o_synthesis), 
        .o_error(s_o_error_synthesis)
        );    

    // Dostarczenie zmiennych do testu, rozpoczęcie bloku initial
    initial begin
        s_i_arg_A = '0;

        //w tym pliku zostaną zapisane zapisane sygnały zarejestrowane w symulacji 
        $dumpfile("signals_konwersja.vcd"); 

        //Wskazania ze wszystkie sygnaly z testbench i nizej maja byc rejestrowane podczas symulacji
        $dumpvars(0, konwersja_tb);   
        
        // Pętla for przypisująca losowe wartości argumentom wejścia dla pięciu iteracji, rozpoczęcie symulacji
        //przypadki losowe, ale totalnie wpadające w zakres normalnego zachowania modułu
        for(i = 0; i < 6; i++) begin
                #1 s_i_arg_A = $urandom;
        end

        //test na ujemne zero:
        #1
        s_i_arg_A = {1'b1, {MOD_NUMBER{1'b0}}};

        //test na zero 
        #1
        s_i_arg_A = {{BITS{1'b1}}};

        //test na maksymalną i minimalną wartość:
        #1    
        s_i_arg_A = {1'b1, '1};
        #1
        s_i_arg_A = {1'b0, '1};
        #1
        $finish;
    end
endmodule

SIGNALS/signals_konwersja.vcd
$date
	Tue Dec 19 16:57:51 2023
$end
$version
	Icarus Verilog
$end
$timescale
	1s
$end
$scope module konwersja_tb $end
$var wire 32 ! s_o_synthesis [31:0] $end
$var wire 32 " s_o_model [31:0] $end
$var wire 1 # s_o_error_synthesis $end
$var wire 1 $ s_o_error_model $end
$var parameter 32 % BITS $end
$var parameter 33 & MOD_NUMBER $end
$var reg 32 ' s_i_arg_A [31:0] $end
$var integer 32 ( i [31:0] $end
$scope module konwersja $end
$var wire 32 ) i_arg_A [31:0] $end
$var wire 31 * i_arg_A_REST [30:0] $end
$var wire 1 + i_arg_A_MSB_2 $end
$var wire 1 , i_arg_A_MSB $end
$var parameter 32 - BITS $end
$var reg 1 $ o_error $end
$var reg 32 . o_result [31:0] $end
$upscope $end
$scope module konwersja_rtl $end
$var wire 1 / _000_ $end
$var wire 1 0 _001_ $end
$var wire 1 1 _002_ $end
$var wire 1 2 _003_ $end
$var wire 1 3 _004_ $end
$var wire 1 4 _005_ $end
$var wire 1 5 _006_ $end
$var wire 1 6 _007_ $end
$var wire 1 7 _008_ $end
$var wire 1 8 _009_ $end
$var wire 1 9 _010_ $end
$var wire 1 : _011_ $end
$var wire 1 ; _012_ $end
$var wire 1 < _013_ $end
$var wire 1 = _014_ $end
$var wire 1 > _015_ $end
$var wire 1 ? _016_ $end
$var wire 1 @ _017_ $end
$var wire 1 A _018_ $end
$var wire 1 B _019_ $end
$var wire 1 C _020_ $end
$var wire 1 D _021_ $end
$var wire 1 E _022_ $end
$var wire 1 F _023_ $end
$var wire 1 G _024_ $end
$var wire 1 H _025_ $end
$var wire 1 I _026_ $end
$var wire 1 J _027_ $end
$var wire 1 K _028_ $end
$var wire 1 L _029_ $end
$var wire 1 M _030_ $end
$var wire 1 N _031_ $end
$var wire 1 O _032_ $end
$var wire 1 P _033_ $end
$var wire 1 Q _034_ $end
$var wire 1 R _035_ $end
$var wire 1 S _036_ $end
$var wire 1 T _037_ $end
$var wire 32 U i_arg_A [31:0] $end
$var wire 1 # o_error $end
$var wire 32 V o_result [31:0] $end
$var wire 31 W i_arg_A_REST [30:0] $end
$var wire 1 X i_arg_A_MSB_2 $end
$var wire 1 Y i_arg_A_MSB $end
$upscope $end
$upscope $end
$enddefinitions $end
$comment Show the parameter values. $end
$dumpall
b100000 -
b11111 &
b100000 %
$end
#0
$dumpvars
0Y
0X
b0 W
b0 V
b0 U
1T
0S
0R
1Q
1P
0O
1N
0M
0L
0K
0J
0I
0H
0G
0F
0E
1D
0C
1B
0A
0@
0?
1>
0=
0<
0;
0:
09
08
07
06
05
04
03
02
01
00
0/
b0 .
0,
0+
b0 *
b0 )
b0 (
b0 '
0$
0#
b0 "
b0 !
$end
#1
0>
1=
0N
15
1<
0B
1M
0T
1E
11
14
18
1;
1A
1I
1L
0Q
1R
1S
b10 !
b10 V
1/
10
13
17
1:
1?
1@
1G
1H
1K
b10 "
b10 .
1,
b10010000101010011010100100100 *
1Y
b10010000101010011010100100100 W
b1 (
b10010010000101010011010100100100 '
b10010010000101010011010100100100 )
b10010010000101010011010100100100 U
#2
1B
0E
08
0A
0D
0P
1Q
0S
1T
b1000000100010010101111010000001 !
b1000000100010010101111010000001 V
00
12
07
19
0:
0?
0@
1C
1J
b1000000100010010101111010000001 "
b1000000100010010101111010000001 .
0,
1+
b1000000100010010101111010000001 *
0Y
1X
b1000000100010010101111010000001 W
b10 (
b1000000100010010101111010000001 '
b1000000100010010101111010000001 )
b1000000100010010101111010000001 U
#3
0B
18
1A
1P
b100100001001101011000001001 !
b100100001001101011000001001 V
03
16
1?
0J
b100100001001101011000001001 "
b100100001001101011000001001 .
0+
b100100001001101011000001001 *
0X
b100100001001101011000001001 W
b11 (
b100100001001101011000001001 '
b100100001001101011000001001 )
b100100001001101011000001001 U
#4
b110001111100000101011001100011 !
b110001111100000101011001100011 V
0/
10
06
17
1:
0?
1@
1J
b110001111100000101011001100011 "
b110001111100000101011001100011 .
b110001111100000101011001100011 *
b110001111100000101011001100011 W
b100 (
b110001111100000101011001100011 '
b110001111100000101011001100011 )
b110001111100000101011001100011 U
#5
0T
0Q
1S
b10 !
b10 V
1/
13
16
07
1?
0@
0J
b10 "
b10 .
1,
b110101110010111101100001101 *
1Y
b110101110010111101100001101 W
b101 (
b10000110101110010111101100001101 '
b10000110101110010111101100001101 )
b10000110101110010111101100001101 U
#6
0S
b11 !
b11 V
0P
1T
1J
b11 "
b11 .
1+
b1000110110111111001100110001101 *
1X
b1000110110111111001100110001101 W
b110 (
b11000110110111111001100110001101 '
b11000110110111111001100110001101 )
b11000110110111111001100110001101 U
#7
1#
1>
1O
0=
1F
1N
05
0<
1B
1E
0M
1S
b10 !
b10 V
01
04
08
0;
0A
1D
0I
0L
1P
0T
0/
00
02
03
06
09
0:
0?
0C
0G
0H
0J
0K
1$
bx "
bx .
0+
b0 *
0X
b0 W
b10000000000000000000000000000000 '
b10000000000000000000000000000000 )
b10000000000000000000000000000000 U
#8
0#
0>
0O
1=
0F
0N
15
1<
0B
0E
1M
0S
b11 !
b11 V
11
14
18
1;
1A
0D
1I
1L
0P
1T
1/
10
12
13
16
17
19
1:
1?
1@
1C
1G
1H
1J
1K
b11 "
b11 .
0$
1+
b1111111111111111111111111111111 *
1X
b1111111111111111111111111111111 W
b11111111111111111111111111111111 '
b11111111111111111111111111111111 )
b11111111111111111111111111111111 U
#9
1>
0=
1N
05
0<
1B
0M
b11 !
b11 V
01
04
08
0;
0A
0I
0L
1P
1Q
1T
0/
00
02
03
06
07
09
0:
0?
0@
0G
0H
0J
0K
b11 "
b11 .
0,
0+
b11 *
0Y
0X
b11 W
b11 '
b11 )
b11 U
#10
b1 !
b1 V
b1 "
b1 .
b1 *
b1 W
b1 '
b1 )
b1 U
