WORK/Verilog_modul_konwersja/konwersja_rtl.sv
/* Generated by Yosys 0.9 (git sha1 1979e0b) */

module konwersja_rtl(i_arg_A, o_result, o_error);
  wire _000_;
  wire _001_;
  wire _002_;
  wire _003_;
  wire _004_;
  wire _005_;
  wire _006_;
  wire _007_;
  wire _008_;
  wire _009_;
  wire _010_;
  wire _011_;
  wire _012_;
  wire _013_;
  wire _014_;
  wire _015_;
  wire _016_;
  wire _017_;
  wire _018_;
  wire _019_;
  wire _020_;
  wire _021_;
  wire _022_;
  wire _023_;
  wire _024_;
  wire _025_;
  wire _026_;
  wire _027_;
  wire _028_;
  wire _029_;
  wire _030_;
  wire _031_;
  wire _032_;
  wire _033_;
  wire _034_;
  wire _035_;
  wire _036_;
  wire _037_;
  input [31:0] i_arg_A;
  output o_error;
  output [31:0] o_result;
  assign _033_ = ~i_arg_A[30];
  assign _034_ = ~i_arg_A[31];
  assign _035_ = i_arg_A[0] | i_arg_A[31];
  assign _036_ = _033_ & i_arg_A[31];
  assign _037_ = i_arg_A[30] | _034_;
  assign o_result[0] = _035_ & _037_;
  assign o_result[1] = i_arg_A[31] | i_arg_A[1];
  assign o_result[2] = _034_ & i_arg_A[2];
  assign o_result[3] = _034_ & i_arg_A[3];
  assign o_result[4] = _034_ & i_arg_A[4];
  assign o_result[5] = _034_ & i_arg_A[5];
  assign o_result[6] = _034_ & i_arg_A[6];
  assign o_result[7] = _034_ & i_arg_A[7];
  assign o_result[8] = _034_ & i_arg_A[8];
  assign o_result[9] = _034_ & i_arg_A[9];
  assign o_result[10] = _034_ & i_arg_A[10];
  assign o_result[11] = _034_ & i_arg_A[11];
  assign o_result[12] = _034_ & i_arg_A[12];
  assign o_result[13] = _034_ & i_arg_A[13];
  assign o_result[14] = _034_ & i_arg_A[14];
  assign o_result[15] = _034_ & i_arg_A[15];
  assign o_result[16] = _034_ & i_arg_A[16];
  assign o_result[17] = _034_ & i_arg_A[17];
  assign o_result[18] = _034_ & i_arg_A[18];
  assign o_result[19] = _034_ & i_arg_A[19];
  assign o_result[20] = _034_ & i_arg_A[20];
  assign o_result[21] = _034_ & i_arg_A[21];
  assign o_result[22] = _034_ & i_arg_A[22];
  assign o_result[23] = _034_ & i_arg_A[23];
  assign o_result[24] = _034_ & i_arg_A[24];
  assign o_result[25] = _034_ & i_arg_A[25];
  assign o_result[26] = _034_ & i_arg_A[26];
  assign o_result[27] = _034_ & i_arg_A[27];
  assign o_result[28] = _034_ & i_arg_A[28];
  assign o_result[29] = _034_ & i_arg_A[29];
  assign o_result[30] = i_arg_A[30] & _034_;
  assign _000_ = i_arg_A[18] | i_arg_A[19];
  assign _001_ = i_arg_A[20] | i_arg_A[21];
  assign _002_ = _000_ | _001_;
  assign _003_ = i_arg_A[14] | i_arg_A[15];
  assign _004_ = i_arg_A[16] | i_arg_A[17];
  assign _005_ = _003_ | _004_;
  assign _006_ = _002_ | _005_;
  assign _007_ = i_arg_A[26] | i_arg_A[27];
  assign _008_ = i_arg_A[28] | i_arg_A[29];
  assign _009_ = _007_ | _008_;
  assign _010_ = i_arg_A[22] | i_arg_A[23];
  assign _011_ = i_arg_A[24] | i_arg_A[25];
  assign _012_ = _010_ | _011_;
  assign _013_ = _009_ | _012_;
  assign _014_ = _006_ | _013_;
  assign _015_ = ~_014_;
  assign _016_ = i_arg_A[2] | i_arg_A[3];
  assign _017_ = i_arg_A[4] | i_arg_A[5];
  assign _018_ = _016_ | _017_;
  assign _019_ = ~_018_;
  assign _020_ = i_arg_A[0] | i_arg_A[1];
  assign _021_ = ~_020_;
  assign _022_ = _036_ & _021_;
  assign _023_ = _019_ & _022_;
  assign _024_ = i_arg_A[10] | i_arg_A[11];
  assign _025_ = i_arg_A[12] | i_arg_A[13];
  assign _026_ = _024_ | _025_;
  assign _027_ = i_arg_A[6] | i_arg_A[7];
  assign _028_ = i_arg_A[8] | i_arg_A[9];
  assign _029_ = _027_ | _028_;
  assign _030_ = _026_ | _029_;
  assign _031_ = ~_030_;
  assign _032_ = _023_ & _031_;
  assign o_error = _015_ & _032_;
  assign o_result[31] = 1'h0;
endmodule

WORK/Verilog_modul_konwersja/konwersja.sv
// moduł konwersji liczby A zapisanej w kodzie ZM na liczbę kodowaną w U2

//nasz maksymalny zakresik konwersji:
//<-(2^30)+1, 2^30-1>
module konwersja (i_arg_A, o_result, o_error);

    //zadeklarowanie szerokości wektora wejścia
    parameter BITS = 32;

    //zadeklarowanie wejścia i wyjść
    input logic signed [BITS-1:0] i_arg_A;
    output logic [BITS-1:0] o_result;
    output logic o_error;    

    //blok opisujący logikę
    always_comb begin
        //defaultowe ustawienie wartości wyjścia i wejścia
        o_result = 'bx;
        o_error = 0;

        //sytuacja, jak mamy dodatnią liczbę kodowaną w typie ZM, to nic nie trzeba robić
        if (i_arg_A[BITS-1] == 0) begin
            o_result = i_arg_A;
        end
    
        //sytuacja, jak mamy ujemną liczbę kodowaną w ZM, to korzystamy z formuły
        //wyjscie = {1'b1, ~i_arg_A[BITS-2] +1'b1}
        //mamy w ogóle jakiekolwiek wyjście, dopóki nam się zero ujemne nie wylosuje. 
        //nie ma takiej opcji, że on poprawnie przekonwertuje mi {1'b1, '0}
        else if (i_arg_A[BITS-1] == 1 && |i_arg_A[BITS-2:0] != 0) begin
            o_result = {1'b1, (~i_arg_A[BITS-2]) +1'b1};
        end
        else begin 
            o_error = 1;
        end
    end
endmodule

WORK/Verilog_modul_konwersja/konwersja_tb.sv
//testbench dla modułu konwersji
//wstępnie przewidziany z kilkoma testami warunków brzegowych
module konwersja_tb;

    parameter BITS = 32;

    // sygnały wewnętrzne i ich atrybuty
    logic [BITS-1:0] s_i_arg_A;
    logic [BITS-1:0] s_o_model;
    logic [BITS-1:0] s_o_synthesis;
    logic            s_o_error_model;
    logic            s_o_error_synthesis;
    integer i;

    // instancjowanie wejść i wyjść, jawne przypisywanie portów
    konwersja     #(.BITS(BITS))        
    konwersja (
        .i_arg_A(s_i_arg_A), 
        .o_result(s_o_model), 
        .o_error(s_o_error_model)
        );

    konwersja_rtl           
    konwersja_rtl (
        .i_arg_A(s_i_arg_A), 
        .o_result(s_o_synthesis), 
        .o_error(s_o_error_synthesis)
        );    

    // Dostarczenie zmiennych do testu, rozpoczęcie bloku initial
    initial begin
        s_i_arg_A = '0;

        //w tym pliku zostaną zapisane zapisane sygnały zarejestrowane w symulacji 
        $dumpfile("signals_konwersja.vcd"); 

        //Wskazania ze wszystkie sygnaly z testbench i nizej maja byc rejestrowane podczas symulacji
        $dumpvars(0, konwersja_tb);   
        
        // Pętla for przypisująca losowe wartości argumentom wejścia dla pięciu iteracji, rozpoczęcie symulacji
        //przypadki losowe, ale totalnie wpadające w zakres normalnego zachowania modułu
        for(i = 0; i < 6; i++) begin
                #1 s_i_arg_A = $urandom;
        end

        //test na ujemne zero:
        #1
        s_i_arg_A = {1'b1, '0};

        //test na zero 
        #1
        s_i_arg_A = '0;

        //test na maksymalną i minimalną wartość:
        #1    
        s_i_arg_A = {1'b1, '1};
        #1
        s_i_arg_A = {1'b0, '1};
        #1
        $finish;
    end
endmodule

WORK/Verilog_modul_konwersja/signals_konwersja.vcd
$date
	Tue Nov 28 00:45:22 2023
$end
$version
	Icarus Verilog
$end
$timescale
	1s
$end
$scope module konwersja_tb $end
$var wire 32 ! s_o_synthesis [31:0] $end
$var wire 32 " s_o_model [31:0] $end
$var wire 1 # s_o_error_synthesis $end
$var wire 1 $ s_o_error_model $end
$var reg 32 % s_i_arg_A [31:0] $end
$var integer 32 & i [31:0] $end
$scope module konwersja $end
$var wire 32 ' i_arg_A [31:0] $end
$var reg 1 $ o_error $end
$var reg 32 ( o_result [31:0] $end
$upscope $end
$scope module konwersja_rtl $end
$var wire 1 ) _000_ $end
$var wire 1 * _001_ $end
$var wire 1 + _002_ $end
$var wire 1 , _003_ $end
$var wire 1 - _004_ $end
$var wire 1 . _005_ $end
$var wire 1 / _006_ $end
$var wire 1 0 _007_ $end
$var wire 1 1 _008_ $end
$var wire 1 2 _009_ $end
$var wire 1 3 _010_ $end
$var wire 1 4 _011_ $end
$var wire 1 5 _012_ $end
$var wire 1 6 _013_ $end
$var wire 1 7 _014_ $end
$var wire 1 8 _015_ $end
$var wire 1 9 _016_ $end
$var wire 1 : _017_ $end
$var wire 1 ; _018_ $end
$var wire 1 < _019_ $end
$var wire 1 = _020_ $end
$var wire 1 > _021_ $end
$var wire 1 ? _022_ $end
$var wire 1 @ _023_ $end
$var wire 1 A _024_ $end
$var wire 1 B _025_ $end
$var wire 1 C _026_ $end
$var wire 1 D _027_ $end
$var wire 1 E _028_ $end
$var wire 1 F _029_ $end
$var wire 1 G _030_ $end
$var wire 1 H _031_ $end
$var wire 1 I _032_ $end
$var wire 1 J _033_ $end
$var wire 1 K _034_ $end
$var wire 1 L _035_ $end
$var wire 1 M _036_ $end
$var wire 1 N _037_ $end
$var wire 32 O i_arg_A [31:0] $end
$var wire 1 # o_error $end
$var wire 32 P o_result [31:0] $end
$upscope $end
$upscope $end
$enddefinitions $end
#0
$dumpvars
b0 P
b0 O
1N
0M
0L
1K
1J
0I
1H
0G
0F
0E
0D
0C
0B
0A
0@
0?
1>
0=
1<
0;
0:
09
18
07
06
05
04
03
02
01
00
0/
0.
0-
0,
0+
0*
0)
b0 (
b0 '
b0 &
b0 %
0$
0#
b0 "
b0 !
$end
#1
08
17
0H
1/
16
0<
1G
0N
1?
1+
1.
12
15
1;
1C
1F
0K
1L
1M
b10 !
b10 P
1)
1*
1-
11
14
19
1:
1A
1B
1E
b10 "
b10 (
b1 &
b10010010000101010011010100100100 %
b10010010000101010011010100100100 '
b10010010000101010011010100100100 O
#2
1<
0?
02
0;
0>
0J
1K
0M
1N
b1000000100010010101111010000001 !
b1000000100010010101111010000001 P
0*
1,
01
13
04
09
0:
1=
1D
b1000000100010010101111010000001 "
b1000000100010010101111010000001 (
b10 &
b1000000100010010101111010000001 %
b1000000100010010101111010000001 '
b1000000100010010101111010000001 O
#3
0<
12
1;
1J
b100100001001101011000001001 !
b100100001001101011000001001 P
0-
10
19
0D
b100100001001101011000001001 "
b100100001001101011000001001 (
b11 &
b100100001001101011000001001 %
b100100001001101011000001001 '
b100100001001101011000001001 O
#4
b110001111100000101011001100011 !
b110001111100000101011001100011 P
0)
1*
00
11
14
09
1:
1D
b110001111100000101011001100011 "
b110001111100000101011001100011 (
b100 &
b110001111100000101011001100011 %
b110001111100000101011001100011 '
b110001111100000101011001100011 O
#5
0N
0K
1M
b10 !
b10 P
1)
1-
10
01
19
0:
0D
b10 "
b10 (
b101 &
b10000110101110010111101100001101 %
b10000110101110010111101100001101 '
b10000110101110010111101100001101 O
#6
0M
b11 !
b11 P
0J
1N
1D
b11 "
b11 (
b110 &
b11000110110111111001100110001101 %
b11000110110111111001100110001101 '
b11000110110111111001100110001101 O
#7
18
07
1H
0/
06
1<
0G
b10 !
b10 P
0+
0.
02
05
0;
0C
0F
1J
1K
0L
1N
0)
0*
0,
0-
00
03
04
09
0A
0B
0D
0E
b10 "
b10 (
b10 %
b10 '
b10 O
#8
1>
b0 !
b0 P
0=
b0 "
b0 (
b0 %
b0 '
b0 O
#9
0>
1L
b11 !
b11 P
1=
b11 "
b11 (
b11 %
b11 '
b11 O
#10
b1 !
b1 P
b1 "
b1 (
b1 %
b1 '
b1 O
