WORK/Verilog_modul_ustawienie/ustawienie_rtl.sv
/* Generated by Yosys 0.9 (git sha1 1979e0b) */

module ustawienie_rtl(i_arg_A, i_arg_B, o_result, o_error);
  wire _000_;
  wire _001_;
  wire _002_;
  wire _003_;
  wire _004_;
  wire _005_;
  wire _006_;
  wire _007_;
  wire _008_;
  wire _009_;
  wire _010_;
  wire _011_;
  wire _012_;
  wire _013_;
  wire _014_;
  wire _015_;
  wire _016_;
  wire _017_;
  wire _018_;
  wire _019_;
  wire _020_;
  wire _021_;
  wire _022_;
  wire _023_;
  wire _024_;
  wire _025_;
  wire _026_;
  wire _027_;
  wire _028_;
  wire _029_;
  wire _030_;
  wire _031_;
  wire _032_;
  wire _033_;
  wire _034_;
  wire _035_;
  wire _036_;
  wire _037_;
  wire _038_;
  wire _039_;
  wire _040_;
  wire _041_;
  wire _042_;
  wire _043_;
  wire _044_;
  wire _045_;
  wire _046_;
  wire _047_;
  wire _048_;
  wire _049_;
  wire _050_;
  wire _051_;
  wire _052_;
  wire _053_;
  wire _054_;
  wire _055_;
  wire _056_;
  wire _057_;
  wire _058_;
  wire _059_;
  wire _060_;
  wire _061_;
  wire _062_;
  wire _063_;
  wire _064_;
  wire _065_;
  wire _066_;
  wire _067_;
  wire _068_;
  wire _069_;
  wire _070_;
  wire _071_;
  wire _072_;
  wire _073_;
  wire _074_;
  wire _075_;
  wire _076_;
  wire _077_;
  wire _078_;
  wire _079_;
  wire _080_;
  wire _081_;
  wire _082_;
  wire _083_;
  wire _084_;
  wire _085_;
  wire _086_;
  wire _087_;
  wire _088_;
  wire _089_;
  wire _090_;
  wire _091_;
  wire _092_;
  wire _093_;
  wire _094_;
  wire _095_;
  wire _096_;
  wire _097_;
  wire _098_;
  wire _099_;
  wire _100_;
  wire _101_;
  wire _102_;
  wire _103_;
  wire _104_;
  wire _105_;
  wire _106_;
  wire _107_;
  wire _108_;
  wire _109_;
  wire _110_;
  wire _111_;
  wire _112_;
  wire _113_;
  wire _114_;
  wire _115_;
  wire _116_;
  wire _117_;
  wire _118_;
  wire _119_;
  wire _120_;
  wire _121_;
  wire _122_;
  wire _123_;
  wire _124_;
  wire _125_;
  wire _126_;
  wire _127_;
  wire _128_;
  wire _129_;
  wire _130_;
  wire _131_;
  wire _132_;
  wire _133_;
  wire _134_;
  wire _135_;
  wire _136_;
  wire _137_;
  wire _138_;
  wire _139_;
  wire _140_;
  wire _141_;
  wire _142_;
  wire _143_;
  wire _144_;
  wire _145_;
  wire _146_;
  wire _147_;
  wire _148_;
  wire _149_;
  wire _150_;
  wire _151_;
  wire _152_;
  wire _153_;
  wire _154_;
  wire _155_;
  wire _156_;
  wire _157_;
  wire _158_;
  wire _159_;
  wire _160_;
  wire _161_;
  wire _162_;
  wire _163_;
  wire _164_;
  input [31:0] i_arg_A;
  input [31:0] i_arg_B;
  output o_error;
  output [31:0] o_result;
  assign _163_ = ~i_arg_B[1];
  assign _164_ = ~i_arg_B[0];
  assign _000_ = ~i_arg_B[2];
  assign _001_ = ~i_arg_B[3];
  assign _002_ = ~i_arg_B[31];
  assign _003_ = i_arg_B[6] | i_arg_B[7];
  assign _004_ = ~_003_;
  assign _005_ = _163_ & _164_;
  assign _006_ = i_arg_B[1] | i_arg_B[0];
  assign _007_ = _000_ & _005_;
  assign _008_ = i_arg_B[2] | _006_;
  assign _009_ = i_arg_B[3] | _008_;
  assign _010_ = ~_009_;
  assign _011_ = i_arg_B[4] | _009_;
  assign _012_ = i_arg_B[5] & _011_;
  assign _013_ = ~_012_;
  assign _014_ = _004_ & _013_;
  assign _015_ = _003_ | _012_;
  assign _016_ = i_arg_B[12] | i_arg_B[13];
  assign _017_ = i_arg_B[14] | i_arg_B[15];
  assign _018_ = _016_ | _017_;
  assign _019_ = i_arg_B[8] | i_arg_B[11];
  assign _020_ = i_arg_B[9] | i_arg_B[10];
  assign _021_ = _019_ | _020_;
  assign _022_ = _018_ | _021_;
  assign _023_ = ~_022_;
  assign _024_ = _014_ & _023_;
  assign _025_ = _015_ | _022_;
  assign _026_ = i_arg_B[4] & _009_;
  assign _027_ = i_arg_B[5] | _026_;
  assign _028_ = ~_027_;
  assign _029_ = _024_ & _027_;
  assign _030_ = i_arg_B[21] | i_arg_B[22];
  assign _031_ = i_arg_B[20] | i_arg_B[23];
  assign _032_ = _030_ | _031_;
  assign _033_ = i_arg_B[16] | i_arg_B[19];
  assign _034_ = i_arg_B[17] | i_arg_B[18];
  assign _035_ = _033_ | _034_;
  assign _036_ = _032_ | _035_;
  assign _037_ = _025_ | _036_;
  assign _038_ = ~_037_;
  assign _039_ = i_arg_B[24] | i_arg_B[25];
  assign _040_ = i_arg_B[26] | i_arg_B[27];
  assign _041_ = _039_ | _040_;
  assign _042_ = _037_ | _041_;
  assign _043_ = ~_042_;
  assign _044_ = i_arg_B[28] & i_arg_B[29];
  assign _045_ = i_arg_B[30] & _044_;
  assign _046_ = _042_ & _045_;
  assign _047_ = _002_ | _046_;
  assign _048_ = i_arg_B[29] | i_arg_B[30];
  assign _049_ = i_arg_B[28] | _048_;
  assign _050_ = _042_ | _049_;
  assign _051_ = ~_050_;
  assign _052_ = i_arg_B[31] | _051_;
  assign o_error = ~_052_;
  assign _053_ = i_arg_B[20] & i_arg_B[21];
  assign _054_ = i_arg_B[22] & i_arg_B[23];
  assign _055_ = _053_ & _054_;
  assign _056_ = i_arg_B[16] & i_arg_B[17];
  assign _057_ = i_arg_B[18] & i_arg_B[19];
  assign _058_ = _056_ & _057_;
  assign _059_ = _055_ & _058_;
  assign _060_ = _025_ & _059_;
  assign _061_ = _038_ | _060_;
  assign _062_ = i_arg_B[24] & i_arg_B[25];
  assign _063_ = i_arg_B[26] & i_arg_B[27];
  assign _064_ = _062_ & _063_;
  assign _065_ = _037_ & _064_;
  assign _066_ = _043_ | _065_;
  assign _067_ = _061_ & _066_;
  assign _068_ = _047_ & _067_;
  assign _069_ = _052_ & _068_;
  assign _070_ = i_arg_B[2] ^ _006_;
  assign _071_ = _000_ ^ _006_;
  assign _072_ = _001_ & _070_;
  assign _073_ = _163_ & i_arg_B[0];
  assign _074_ = _072_ & _073_;
  assign _075_ = _069_ & _074_;
  assign _076_ = _029_ & _075_;
  assign _077_ = i_arg_B[13] & i_arg_B[14];
  assign _078_ = i_arg_B[8] & i_arg_B[11];
  assign _079_ = i_arg_B[12] & i_arg_B[15];
  assign _080_ = _077_ & _079_;
  assign _081_ = i_arg_B[9] & i_arg_B[10];
  assign _082_ = _080_ & _081_;
  assign _083_ = _078_ & _082_;
  assign _084_ = _015_ & _083_;
  assign _085_ = _024_ | _084_;
  assign _086_ = i_arg_B[6] & i_arg_B[7];
  assign _087_ = _012_ & _086_;
  assign _088_ = _014_ | _087_;
  assign o_result[15] = i_arg_A[15] | _076_;
  assign _089_ = _011_ & _028_;
  assign _090_ = _088_ & _089_;
  assign _091_ = _085_ & _090_;
  assign _092_ = _069_ & _091_;
  assign _093_ = _010_ & _092_;
  assign o_result[16] = i_arg_A[16] | _093_;
  assign _094_ = i_arg_B[3] & _007_;
  assign _095_ = _001_ ^ _008_;
  assign _096_ = i_arg_B[3] ^ _008_;
  assign _097_ = _071_ & _095_;
  assign _098_ = i_arg_B[1] & i_arg_B[0];
  assign _099_ = _097_ & _098_;
  assign _100_ = _092_ & _099_;
  assign o_result[17] = i_arg_A[17] | _100_;
  assign _101_ = i_arg_B[1] & _164_;
  assign _102_ = _097_ & _101_;
  assign _103_ = _092_ & _102_;
  assign o_result[18] = i_arg_A[18] | _103_;
  assign _104_ = _073_ & _097_;
  assign _105_ = _092_ & _104_;
  assign o_result[19] = i_arg_A[19] | _105_;
  assign _106_ = i_arg_B[3] & _070_;
  assign _107_ = _005_ & _106_;
  assign _108_ = _092_ & _107_;
  assign o_result[20] = i_arg_A[20] | _108_;
  assign _109_ = _098_ & _106_;
  assign _110_ = _092_ & _109_;
  assign o_result[21] = i_arg_A[21] | _110_;
  assign _111_ = _101_ & _106_;
  assign _112_ = _092_ & _111_;
  assign o_result[22] = i_arg_A[22] | _112_;
  assign _113_ = _073_ & _106_;
  assign _114_ = _092_ & _113_;
  assign o_result[23] = i_arg_A[23] | _114_;
  assign _115_ = _092_ & _094_;
  assign o_result[24] = i_arg_A[24] | _115_;
  assign _116_ = _071_ & _096_;
  assign _117_ = _098_ & _116_;
  assign _118_ = _092_ & _117_;
  assign o_result[25] = i_arg_A[25] | _118_;
  assign _119_ = _101_ & _116_;
  assign _120_ = _092_ & _119_;
  assign o_result[26] = i_arg_A[26] | _120_;
  assign _121_ = _073_ & _116_;
  assign _122_ = _092_ & _121_;
  assign o_result[27] = i_arg_A[27] | _122_;
  assign _123_ = _005_ & _072_;
  assign _124_ = _092_ & _123_;
  assign o_result[28] = i_arg_A[28] | _124_;
  assign _125_ = _072_ & _098_;
  assign _126_ = _092_ & _125_;
  assign o_result[29] = i_arg_A[29] | _126_;
  assign _127_ = _072_ & _101_;
  assign _128_ = _092_ & _127_;
  assign o_result[30] = i_arg_A[30] | _128_;
  assign _129_ = _075_ & _091_;
  assign o_result[31] = i_arg_A[31] | _129_;
  assign _130_ = _003_ | _011_;
  assign _131_ = ~_130_;
  assign _132_ = i_arg_B[5] & _131_;
  assign _133_ = _085_ & _132_;
  assign _134_ = _069_ & _133_;
  assign o_result[0] = i_arg_A[0] | _134_;
  assign _135_ = _029_ & _099_;
  assign _136_ = _069_ & _135_;
  assign o_result[1] = i_arg_A[1] | _136_;
  assign _137_ = _029_ & _102_;
  assign _138_ = _069_ & _137_;
  assign o_result[2] = i_arg_A[2] | _138_;
  assign _139_ = _029_ & _104_;
  assign _140_ = _069_ & _139_;
  assign o_result[3] = i_arg_A[3] | _140_;
  assign _141_ = _029_ & _107_;
  assign _142_ = _069_ & _141_;
  assign o_result[4] = i_arg_A[4] | _142_;
  assign _143_ = _029_ & _109_;
  assign _144_ = _069_ & _143_;
  assign o_result[5] = i_arg_A[5] | _144_;
  assign _145_ = _029_ & _111_;
  assign _146_ = _069_ & _145_;
  assign o_result[6] = i_arg_A[6] | _146_;
  assign _147_ = _029_ & _113_;
  assign _148_ = _069_ & _147_;
  assign o_result[7] = i_arg_A[7] | _148_;
  assign _149_ = _029_ & _094_;
  assign _150_ = _069_ & _149_;
  assign o_result[8] = i_arg_A[8] | _150_;
  assign _151_ = _029_ & _117_;
  assign _152_ = _069_ & _151_;
  assign o_result[9] = i_arg_A[9] | _152_;
  assign _153_ = _029_ & _119_;
  assign _154_ = _069_ & _153_;
  assign o_result[10] = i_arg_A[10] | _154_;
  assign _155_ = _029_ & _121_;
  assign _156_ = _069_ & _155_;
  assign o_result[11] = i_arg_A[11] | _156_;
  assign _157_ = _029_ & _123_;
  assign _158_ = _069_ & _157_;
  assign o_result[12] = i_arg_A[12] | _158_;
  assign _159_ = _029_ & _125_;
  assign _160_ = _069_ & _159_;
  assign o_result[13] = i_arg_A[13] | _160_;
  assign _161_ = _029_ & _127_;
  assign _162_ = _069_ & _161_;
  assign o_result[14] = i_arg_A[14] | _162_;
endmodule

WORK/Verilog_modul_ustawienie/ustawienie.sv
//moduł ustawienia bitu w liczbie i_arg_A na 1, na indeksie wskazanym przez i_arg_B
module ustawienie (i_arg_A, i_arg_B, o_result, o_error);

//deklaracja parametrów
parameter BITS = 32;

//deklaracja wejść, wyjść i flag
    input logic signed [BITS-1:0] i_arg_A;
    input logic signed [BITS-1:0] i_arg_B;
    output logic [BITS-1:0] o_result;
    output logic o_error;
    logic [BITS-1:0] tymczasowy_rejestr;

    //blok opisujący logikę
    always_comb 
    begin 

        //defaultowe ustawienie wartości wyjść i rejestru tymczasowego
        o_result = 'bx;
        o_error = 0;
        tymczasowy_rejestr = '0;

        //jak B jest ujemne, to ustawiamy flagę błędu
        if (i_arg_B[BITS] == 1) begin
            o_error = 1;
        end

        //jak B jest większe od 32, to ustawiamy flagę błędu
        else if (i_arg_B > BITS) begin
            o_error = 1;
        end

        //jak B wpada w zakres, to ustawiamy tego bita
        else if (i_arg_B>=0 && i_arg_B<BITS+1) begin
            tymczasowy_rejestr[BITS-i_arg_B] = 1;
            o_result = tymczasowy_rejestr|i_arg_A;
        end

    end

endmodule

WORK/Verilog_modul_ustawienie/ustawienie_tb.sv
// testbench modułu ustawienia bitu na 1 na bicie i_arg_A o indeksie i_arg_B
// zaczynamy ławeczkę testową
module ustawienie_tb;
parameter BITS = 32;

// sygnały wewnętrzne dla tej konketnej ławeczki testowej 
logic [BITS-1:0] s_i_arg_A;
logic [BITS-1:0] s_i_arg_B;
logic            s_o_error_model;
logic            s_o_error_synthesis;
logic [BITS-1:0] s_o_model;
logic [BITS-1:0] s_o_synthesis;
integer i;

// instancjowanie wejść i wyjść, jawne przypisywanie portów
ustawienie #(.BITS(BITS))        
ustawienie (
    .i_arg_A(s_i_arg_A), 
    .i_arg_B(s_i_arg_B), 
    .o_result(s_o_model), 
    .o_error(s_o_error_model)
    );    

ustawienie_rtl           
ustawienie_rtl (
    .i_arg_A(s_i_arg_A), 
    .i_arg_B(s_i_arg_B), 
    .o_result(s_o_synthesis), 
    .o_error(s_o_error_synthesis)
    );

// Dostarczenie zmiennych do testu, rozpoczęcie bloku initial
initial begin
    s_i_arg_A = '0;
    s_i_arg_B = '0;

    //w tym pliku zostaną zapisane zapisane sygnały zarejestrowane w symulacji
    $dumpfile("signals_ustawienie.vcd");  

    //Wskazania, że wszystkie sygnały z testbench i niżej mają być rejestrowane podczas symulacji
    $dumpvars(0, ustawienie_tb);       

    //najpierw testujemy przypadek idealny, na zerze najłatwiej zauważyć
    for (int i=0; i<6; i++) begin
        #1  
        s_i_arg_A = 0;
        s_i_arg_B = $urandom_range(0,31);
    end
    //teraz zobaczymy przypadki losowe dla liczb ujemnych 
    for (i=0; i<6; i++) begin
        #1  
        s_i_arg_A = '0;
        s_i_arg_B = $urandom_range(-2147483647, -1);
    end

    //teraz zobaczymy przypadki losowe dla liczb >32
   for (i=0; i<6; i++) begin
        #1  
        s_i_arg_A = '0;
        s_i_arg_B = $urandom_range(33, 2147483647);
    end
    $finish;
end
endmodule

WORK/Verilog_modul_ustawienie/signals_ustawienie.vcd
$date
	Mon Nov 27 02:11:03 2023
$end
$version
	Icarus Verilog
$end
$timescale
	1s
$end
$scope module ustawienie_tb $end
$var wire 32 ! s_o_synthesis [31:0] $end
$var wire 32 " s_o_model [31:0] $end
$var wire 1 # s_o_error_synthesis $end
$var wire 1 $ s_o_error_model $end
$var reg 32 % s_i_arg_A [31:0] $end
$var reg 32 & s_i_arg_B [31:0] $end
$var integer 32 ' i [31:0] $end
$scope module ustawienie $end
$var wire 32 ( i_arg_A [31:0] $end
$var wire 32 ) i_arg_B [31:0] $end
$var reg 1 $ o_error $end
$var reg 32 * o_result [31:0] $end
$var reg 32 + tymczasowy_rejestr [31:0] $end
$upscope $end
$scope module ustawienie_rtl $end
$var wire 1 , _000_ $end
$var wire 1 - _001_ $end
$var wire 1 . _002_ $end
$var wire 1 / _003_ $end
$var wire 1 0 _004_ $end
$var wire 1 1 _005_ $end
$var wire 1 2 _006_ $end
$var wire 1 3 _007_ $end
$var wire 1 4 _008_ $end
$var wire 1 5 _009_ $end
$var wire 1 6 _010_ $end
$var wire 1 7 _011_ $end
$var wire 1 8 _012_ $end
$var wire 1 9 _013_ $end
$var wire 1 : _014_ $end
$var wire 1 ; _015_ $end
$var wire 1 < _016_ $end
$var wire 1 = _017_ $end
$var wire 1 > _018_ $end
$var wire 1 ? _019_ $end
$var wire 1 @ _020_ $end
$var wire 1 A _021_ $end
$var wire 1 B _022_ $end
$var wire 1 C _023_ $end
$var wire 1 D _024_ $end
$var wire 1 E _025_ $end
$var wire 1 F _026_ $end
$var wire 1 G _027_ $end
$var wire 1 H _028_ $end
$var wire 1 I _029_ $end
$var wire 1 J _030_ $end
$var wire 1 K _031_ $end
$var wire 1 L _032_ $end
$var wire 1 M _033_ $end
$var wire 1 N _034_ $end
$var wire 1 O _035_ $end
$var wire 1 P _036_ $end
$var wire 1 Q _037_ $end
$var wire 1 R _038_ $end
$var wire 1 S _039_ $end
$var wire 1 T _040_ $end
$var wire 1 U _041_ $end
$var wire 1 V _042_ $end
$var wire 1 W _043_ $end
$var wire 1 X _044_ $end
$var wire 1 Y _045_ $end
$var wire 1 Z _046_ $end
$var wire 1 [ _047_ $end
$var wire 1 \ _048_ $end
$var wire 1 ] _049_ $end
$var wire 1 ^ _050_ $end
$var wire 1 _ _051_ $end
$var wire 1 ` _052_ $end
$var wire 1 a _053_ $end
$var wire 1 b _054_ $end
$var wire 1 c _055_ $end
$var wire 1 d _056_ $end
$var wire 1 e _057_ $end
$var wire 1 f _058_ $end
$var wire 1 g _059_ $end
$var wire 1 h _060_ $end
$var wire 1 i _061_ $end
$var wire 1 j _062_ $end
$var wire 1 k _063_ $end
$var wire 1 l _064_ $end
$var wire 1 m _065_ $end
$var wire 1 n _066_ $end
$var wire 1 o _067_ $end
$var wire 1 p _068_ $end
$var wire 1 q _069_ $end
$var wire 1 r _070_ $end
$var wire 1 s _071_ $end
$var wire 1 t _072_ $end
$var wire 1 u _073_ $end
$var wire 1 v _074_ $end
$var wire 1 w _075_ $end
$var wire 1 x _076_ $end
$var wire 1 y _077_ $end
$var wire 1 z _078_ $end
$var wire 1 { _079_ $end
$var wire 1 | _080_ $end
$var wire 1 } _081_ $end
$var wire 1 ~ _082_ $end
$var wire 1 !" _083_ $end
$var wire 1 "" _084_ $end
$var wire 1 #" _085_ $end
$var wire 1 $" _086_ $end
$var wire 1 %" _087_ $end
$var wire 1 &" _088_ $end
$var wire 1 '" _089_ $end
$var wire 1 (" _090_ $end
$var wire 1 )" _091_ $end
$var wire 1 *" _092_ $end
$var wire 1 +" _093_ $end
$var wire 1 ," _094_ $end
$var wire 1 -" _095_ $end
$var wire 1 ." _096_ $end
$var wire 1 /" _097_ $end
$var wire 1 0" _098_ $end
$var wire 1 1" _099_ $end
$var wire 1 2" _100_ $end
$var wire 1 3" _101_ $end
$var wire 1 4" _102_ $end
$var wire 1 5" _103_ $end
$var wire 1 6" _104_ $end
$var wire 1 7" _105_ $end
$var wire 1 8" _106_ $end
$var wire 1 9" _107_ $end
$var wire 1 :" _108_ $end
$var wire 1 ;" _109_ $end
$var wire 1 <" _110_ $end
$var wire 1 =" _111_ $end
$var wire 1 >" _112_ $end
$var wire 1 ?" _113_ $end
$var wire 1 @" _114_ $end
$var wire 1 A" _115_ $end
$var wire 1 B" _116_ $end
$var wire 1 C" _117_ $end
$var wire 1 D" _118_ $end
$var wire 1 E" _119_ $end
$var wire 1 F" _120_ $end
$var wire 1 G" _121_ $end
$var wire 1 H" _122_ $end
$var wire 1 I" _123_ $end
$var wire 1 J" _124_ $end
$var wire 1 K" _125_ $end
$var wire 1 L" _126_ $end
$var wire 1 M" _127_ $end
$var wire 1 N" _128_ $end
$var wire 1 O" _129_ $end
$var wire 1 P" _130_ $end
$var wire 1 Q" _131_ $end
$var wire 1 R" _132_ $end
$var wire 1 S" _133_ $end
$var wire 1 T" _134_ $end
$var wire 1 U" _135_ $end
$var wire 1 V" _136_ $end
$var wire 1 W" _137_ $end
$var wire 1 X" _138_ $end
$var wire 1 Y" _139_ $end
$var wire 1 Z" _140_ $end
$var wire 1 [" _141_ $end
$var wire 1 \" _142_ $end
$var wire 1 ]" _143_ $end
$var wire 1 ^" _144_ $end
$var wire 1 _" _145_ $end
$var wire 1 `" _146_ $end
$var wire 1 a" _147_ $end
$var wire 1 b" _148_ $end
$var wire 1 c" _149_ $end
$var wire 1 d" _150_ $end
$var wire 1 e" _151_ $end
$var wire 1 f" _152_ $end
$var wire 1 g" _153_ $end
$var wire 1 h" _154_ $end
$var wire 1 i" _155_ $end
$var wire 1 j" _156_ $end
$var wire 1 k" _157_ $end
$var wire 1 l" _158_ $end
$var wire 1 m" _159_ $end
$var wire 1 n" _160_ $end
$var wire 1 o" _161_ $end
$var wire 1 p" _162_ $end
$var wire 1 q" _163_ $end
$var wire 1 r" _164_ $end
$var wire 32 s" i_arg_A [31:0] $end
$var wire 32 t" i_arg_B [31:0] $end
$var wire 1 # o_error $end
$var wire 32 u" o_result [31:0] $end
$upscope $end
$scope begin $ivl_for_loop0 $end
$var integer 32 v" i [31:0] $end
$upscope $end
$upscope $end
$enddefinitions $end
#0
$dumpvars
b0 v"
b0 u"
b0 t"
b0 s"
1r"
1q"
0p"
0o"
0n"
0m"
0l"
0k"
0j"
0i"
0h"
0g"
0f"
0e"
0d"
0c"
0b"
0a"
0`"
0_"
0^"
0]"
0\"
0["
0Z"
0Y"
0X"
0W"
0V"
0U"
0T"
0S"
0R"
1Q"
0P"
0O"
0N"
0M"
0L"
0K"
0J"
0I"
0H"
0G"
0F"
0E"
0D"
0C"
0B"
0A"
0@"
0?"
0>"
0="
0<"
0;"
0:"
09"
08"
07"
06"
05"
04"
03"
02"
01"
00"
1/"
0."
1-"
0,"
0+"
0*"
0)"
0("
0'"
1&"
0%"
0$"
1#"
0""
0!"
0~
0}
0|
0{
0z
0y
0x
0w
0v
0u
0t
1s
0r
1q
1p
1o
1n
0m
0l
0k
0j
1i
0h
0g
0f
0e
0d
0c
0b
0a
1`
1_
0^
0]
0\
1[
0Z
0Y
0X
1W
0V
0U
0T
0S
1R
0Q
0P
0O
0N
0M
0L
0K
0J
0I
1H
0G
0F
0E
1D
1C
0B
0A
0@
0?
0>
0=
0<
0;
1:
19
08
07
16
05
04
13
02
11
10
0/
1.
1-
1,
b0 +
b0 *
b0 )
b0 (
bx '
b0 &
b0 %
0$
0#
b0 "
b0 !
$end
#1
1p"
1o"
0H
1I
b100000000000000 !
b100000000000000 u"
1G
0N"
0*"
06
1F
1M"
0)"
03
15
0-"
1."
1t
0/"
0("
0Q"
01
14
1r
0s
0'"
1P"
04"
0q"
12
17
13"
b100000000000000 +
b100000000000000 "
b100000000000000 *
b1 v"
b10010 &
b10010 )
b10010 t"
#2
1A"
1*"
1)"
1("
b1000000000000000000000000 !
b1000000000000000000000000 u"
1,"
1B"
1'"
0p"
13
1H
0I
0o"
11
0t
04
0r
1s
0G
0M"
1q"
0-
02
0F
1."
03"
08"
b1000000000000000000000000 +
b1000000000000000000000000 "
b1000000000000000000000000 *
b10 v"
b1000 &
b1000 )
b1000 t"
#3
0*"
0)"
0("
1Q"
1/"
0+"
0'"
0P"
b0 !
b0 u"
1-"
16
07
0A"
0B"
1-
05
0,"
0."
b0 +
b0 "
b0 *
b11 v"
b0 &
b0 )
b0 t"
#4
b100000000000000000000000000 !
b100000000000000000000000000 u"
1F"
1*"
1)"
1("
0Q"
1'"
1P"
1E"
06
17
0/"
1B"
0M"
01
03
15
0-"
1."
0t
04"
0q"
0,
12
14
0r
13"
b100000000000000000000000000 +
b100000000000000000000000000 "
b100000000000000000000000000 *
b100 v"
b110 &
b110 )
b110 t"
#5
1*"
1)"
1+"
1("
0l"
16
1/"
0B"
1'"
0J"
0k"
b10000000000000000 !
b10000000000000000 u"
13
05
1-"
0."
1H
0I
0I"
0F"
11
04
0G
0t
0E"
1q"
1,
02
0F
0r
03"
b10000000000000000 +
b10000000000000000 "
b10000000000000000 *
b101 v"
b10000 &
b10000 )
b10000 t"
#6
0*"
0)"
0("
1d"
0'"
1c"
0H
1I
0/"
0+"
1G
b100000000 !
b100000000 u"
0-"
06
1F
0A"
1B"
0-
15
1,"
1."
b100000000 +
b100000000 "
b100000000 *
b0 '
b110 v"
b11000 &
b11000 )
b11000 t"
#7
0i
0o
0I
0#"
0R
0n
0m"
0q
0D
0&"
0C
1Q
0W
b0 !
b0 u"
0f"
0h"
03
1K"
0p
0:
1E
1B
1P
1V
0_
0d"
0e"
0g"
01
1t
0[
14
1r
0s
06
1F
09
1;
1>
1A
1L
1O
1U
1^
0c"
0B"
0C"
0E"
0q"
0r"
1-
0.
12
15
18
1=
1@
1J
1M
1S
1T
1]
0u
0,"
1."
10"
03"
b0 +
bx "
bx *
b1 '
b10011001011000010100001000110011 &
b10011001011000010100001000110011 )
b10011001011000010100001000110011 t"
#8
1("
1&"
1'"
1="
1:
1H
13"
0t
1-"
19
0;
0G
0K"
1r"
0-
08
1<
1?
0@
0F
0J
1K
1N
0S
0]
1d
1z
0."
00"
18"
b10 '
b10000100100110111010100100001010 &
b10000100100110111010100100001010 )
b10000100100110111010100100001010 t"
#9
0("
0&"
1v
0:
1u
1t
0-"
00
1;
0U
1]
1|
0="
1q"
0r"
1-
1/
1J
0N
0T
1\
1a
0d
1y
0z
1{
1."
03"
08"
b11 '
b11000000011110011111000110000001 &
b11000000011110011111000110000001 )
b11000000011110011111000110000001 t"
#10
1C"
1B"
0v
0u
1s
1U
0t
0|
0~
0K"
0q"
0,
0?
1@
0K
1N
1S
0a
1d
1j
0r
0{
1}
10"
b100 '
b11000011011010111110011010000111 &
b11000011011010111110011010000111 )
b11000011011010111110011010000111 t"
#11
0'"
1;"
0C"
0s
1-"
09
0H
18"
1|
0B"
1,
0-
18
1?
0@
1F
1G
0J
1K
0N
1T
0d
0j
1k
1r
1{
0}
0."
b101 '
b11011101100100011111100010111011 &
b11011101100100011111100010111011 )
b11011101100100011111100010111011 t"
#12
1n
14"
1/"
1m
13"
1s
19
1l
08"
0|
0~
0;"
1r"
0,
08
0?
1@
1J
0K
0M
1N
1j
0r
0{
1}
00"
b0 '
b11001111010001101110011010011110 &
b11001111010001101110011010011110 )
b11001111010001101110011010011110 t"
#13
1,"
0/"
1B"
0n
13
0-"
1."
1Z
0m
09"
1&"
11
1[
04
09
1Y
1#
0l
08"
1%"
04"
1q"
1,
1.
02
18
0=
1?
1M
1X
0`
0k
0r
0y
1z
0}
1$"
03"
1$
b1 '
b1111011011010100010101111111000 &
b1111011011010100010101111111000 )
b1111011011010100010101111111000 t"
#14
16"
1'"
0,"
1/"
0B"
0&"
1H
0Z
0?"
01
03
1-"
0."
19
0%"
0G
0Y
08"
0G"
1|
0r"
0,
12
14
08
1=
0F
0J
1K
0M
0T
0X
0r
1u
1y
1{
1$
b10 '
b1100011000101101111101111001101 &
b1100011000101101111101111001101 )
b1100011000101101111101111001101 t"
#15
1&"
0'"
1Z
09
1%"
0H
1Y
18
0?
1F
1G
1J
1M
1T
1X
1a
1e
0j
1k
0z
1$
b11 '
b1111110011111101111010011111101 &
b1111110011111101111010011111101 )
b1111110011111101111010011111101 t"
#16
06"
0/"
0&"
1C"
0u
0-"
0Z
0|
0%"
1B"
01"
0q"
1-
0J
0T
0Y
0a
1d
0e
0k
0y
0$"
1."
10"
1$
b100 '
b110001100110111001001001110111 &
b110001100110111001001001110111 )
b110001100110111001001001110111 t"
#17
0<
1J
1a
0{
1$
b101 '
b110001011110111100001001110111 &
b110001011110111100001001110111 )
b110001011110111100001001110111 t"
#18
1;"
0C"
0s
1-"
18"
0B"
1,
0-
1<
1?
0@
0F
0J
0N
1T
0X
0a
0d
1r
1y
1z
0."
1$
b110 '
b101010100010011110100101101011 &
b101010100010011110100101101011 )
b101010100010011110100101101011 t"
