WORK/Verilog_modul_ustawienie/ustawienie_rtl.sv
/* Generated by Yosys 0.9 (git sha1 1979e0b) */

module ustawienie_rtl(i_arg_A, i_arg_B, o_result, o_error);
  wire _000_;
  wire _001_;
  wire _002_;
  wire _003_;
  wire _004_;
  wire _005_;
  wire _006_;
  wire _007_;
  wire _008_;
  wire _009_;
  wire _010_;
  wire _011_;
  wire _012_;
  wire _013_;
  wire _014_;
  wire _015_;
  wire _016_;
  wire _017_;
  wire _018_;
  wire _019_;
  wire _020_;
  wire _021_;
  wire _022_;
  wire _023_;
  wire _024_;
  wire _025_;
  wire _026_;
  wire _027_;
  wire _028_;
  wire _029_;
  wire _030_;
  wire _031_;
  wire _032_;
  wire _033_;
  wire _034_;
  wire _035_;
  wire _036_;
  wire _037_;
  wire _038_;
  wire _039_;
  wire _040_;
  wire _041_;
  wire _042_;
  wire _043_;
  wire _044_;
  wire _045_;
  wire _046_;
  wire _047_;
  wire _048_;
  wire _049_;
  wire _050_;
  wire _051_;
  wire _052_;
  wire _053_;
  wire _054_;
  wire _055_;
  wire _056_;
  wire _057_;
  wire _058_;
  wire _059_;
  wire _060_;
  wire _061_;
  wire _062_;
  wire _063_;
  wire _064_;
  wire _065_;
  wire _066_;
  wire _067_;
  wire _068_;
  wire _069_;
  wire _070_;
  wire _071_;
  wire _072_;
  wire _073_;
  wire _074_;
  wire _075_;
  wire _076_;
  wire _077_;
  wire _078_;
  wire _079_;
  wire _080_;
  wire _081_;
  wire _082_;
  wire _083_;
  wire _084_;
  wire _085_;
  wire _086_;
  wire _087_;
  wire _088_;
  wire _089_;
  wire _090_;
  wire _091_;
  wire _092_;
  wire _093_;
  wire _094_;
  wire _095_;
  wire _096_;
  wire _097_;
  wire _098_;
  wire _099_;
  wire _100_;
  wire _101_;
  wire _102_;
  wire _103_;
  wire _104_;
  wire _105_;
  wire _106_;
  wire _107_;
  wire _108_;
  wire _109_;
  wire _110_;
  wire _111_;
  wire _112_;
  wire _113_;
  wire _114_;
  wire _115_;
  wire _116_;
  wire _117_;
  wire _118_;
  wire _119_;
  wire _120_;
  wire _121_;
  wire _122_;
  wire _123_;
  wire _124_;
  wire _125_;
  wire _126_;
  wire _127_;
  wire _128_;
  wire _129_;
  wire _130_;
  wire _131_;
  wire _132_;
  input [31:0] i_arg_A;
  input [31:0] i_arg_B;
  output o_error;
  output [31:0] o_result;
  assign _131_ = ~i_arg_B[1];
  assign _132_ = ~i_arg_B[0];
  assign _000_ = ~i_arg_B[3];
  assign _001_ = ~i_arg_B[2];
  assign _002_ = ~i_arg_A[0];
  assign _003_ = ~i_arg_A[1];
  assign _004_ = ~i_arg_A[2];
  assign _005_ = ~i_arg_A[3];
  assign _006_ = ~i_arg_A[4];
  assign _007_ = ~i_arg_A[5];
  assign _008_ = ~i_arg_A[6];
  assign _009_ = ~i_arg_A[7];
  assign _010_ = ~i_arg_A[8];
  assign _011_ = ~i_arg_A[9];
  assign _012_ = ~i_arg_A[10];
  assign _013_ = ~i_arg_A[11];
  assign _014_ = ~i_arg_A[12];
  assign _015_ = ~i_arg_A[13];
  assign _016_ = ~i_arg_A[14];
  assign _017_ = ~i_arg_A[15];
  assign _018_ = ~i_arg_A[16];
  assign _019_ = ~i_arg_A[17];
  assign _020_ = ~i_arg_A[18];
  assign _021_ = ~i_arg_A[19];
  assign _022_ = ~i_arg_A[20];
  assign _023_ = ~i_arg_A[21];
  assign _024_ = ~i_arg_A[22];
  assign _025_ = ~i_arg_A[23];
  assign _026_ = ~i_arg_A[24];
  assign _027_ = ~i_arg_A[25];
  assign _028_ = ~i_arg_A[26];
  assign _029_ = ~i_arg_A[27];
  assign _030_ = ~i_arg_A[28];
  assign _031_ = ~i_arg_A[29];
  assign _032_ = ~i_arg_A[30];
  assign _033_ = ~i_arg_A[31];
  assign _034_ = _000_ & _001_;
  assign _035_ = i_arg_B[13] | i_arg_B[12];
  assign _036_ = i_arg_B[15] | i_arg_B[14];
  assign _037_ = _035_ | _036_;
  assign _038_ = ~_037_;
  assign _039_ = i_arg_B[9] | i_arg_B[8];
  assign _040_ = i_arg_B[11] | i_arg_B[10];
  assign _041_ = _039_ | _040_;
  assign _042_ = ~_041_;
  assign _043_ = _038_ & _042_;
  assign _044_ = i_arg_B[1] | i_arg_B[0];
  assign _045_ = ~_044_;
  assign _046_ = _043_ & _045_;
  assign _047_ = _034_ & _046_;
  assign _048_ = i_arg_B[20] | i_arg_B[23];
  assign _049_ = i_arg_B[17] | i_arg_B[18];
  assign _050_ = _048_ | _049_;
  assign _051_ = i_arg_B[29] | i_arg_B[30];
  assign _052_ = i_arg_B[24] | i_arg_B[27];
  assign _053_ = _051_ | _052_;
  assign _054_ = _050_ | _053_;
  assign _055_ = ~_054_;
  assign _056_ = i_arg_B[21] | i_arg_B[22];
  assign _057_ = i_arg_B[16] | i_arg_B[19];
  assign _058_ = _056_ | _057_;
  assign _059_ = i_arg_B[28] | i_arg_B[31];
  assign _060_ = i_arg_B[25] | i_arg_B[26];
  assign _061_ = _059_ | _060_;
  assign _062_ = _058_ | _061_;
  assign _063_ = ~_062_;
  assign _064_ = _055_ & _063_;
  assign _065_ = i_arg_B[5] | i_arg_B[7];
  assign _066_ = i_arg_B[6] | _065_;
  assign _067_ = ~_066_;
  assign _068_ = i_arg_B[4] | _066_;
  assign _069_ = ~_068_;
  assign _070_ = _064_ & _069_;
  assign _071_ = _047_ & _070_;
  assign o_result[0] = _002_ | _071_;
  assign _072_ = _131_ & i_arg_B[0];
  assign _073_ = _043_ & _072_;
  assign _074_ = _034_ & _073_;
  assign _075_ = _070_ & _074_;
  assign o_result[1] = _003_ | _075_;
  assign _076_ = i_arg_B[1] & _132_;
  assign _077_ = _043_ & _076_;
  assign _078_ = _034_ & _077_;
  assign _079_ = _070_ & _078_;
  assign o_result[2] = _004_ | _079_;
  assign _080_ = i_arg_B[1] & i_arg_B[0];
  assign _081_ = _043_ & _080_;
  assign _082_ = _034_ & _081_;
  assign _083_ = _070_ & _082_;
  assign o_result[3] = _005_ | _083_;
  assign _084_ = _000_ & i_arg_B[2];
  assign _085_ = _046_ & _084_;
  assign _086_ = _070_ & _085_;
  assign o_result[4] = _006_ | _086_;
  assign _087_ = _073_ & _084_;
  assign _088_ = _070_ & _087_;
  assign o_result[5] = _007_ | _088_;
  assign _089_ = _077_ & _084_;
  assign _090_ = _070_ & _089_;
  assign o_result[6] = _008_ | _090_;
  assign _091_ = _081_ & _084_;
  assign _092_ = _070_ & _091_;
  assign o_result[7] = _009_ | _092_;
  assign _093_ = i_arg_B[3] & _001_;
  assign _094_ = _046_ & _093_;
  assign _095_ = _070_ & _094_;
  assign o_result[8] = _010_ | _095_;
  assign _096_ = _073_ & _093_;
  assign _097_ = _070_ & _096_;
  assign o_result[9] = _011_ | _097_;
  assign _098_ = _077_ & _093_;
  assign _099_ = _070_ & _098_;
  assign o_result[10] = _012_ | _099_;
  assign _100_ = _081_ & _093_;
  assign _101_ = _070_ & _100_;
  assign o_result[11] = _013_ | _101_;
  assign _102_ = i_arg_B[3] & i_arg_B[2];
  assign _103_ = _046_ & _102_;
  assign _104_ = _070_ & _103_;
  assign o_result[12] = _014_ | _104_;
  assign _105_ = _073_ & _102_;
  assign _106_ = _070_ & _105_;
  assign o_result[13] = _015_ | _106_;
  assign _107_ = _077_ & _102_;
  assign _108_ = _070_ & _107_;
  assign o_result[14] = _016_ | _108_;
  assign _109_ = _081_ & _102_;
  assign _110_ = _070_ & _109_;
  assign o_result[15] = _017_ | _110_;
  assign _111_ = i_arg_B[4] & _067_;
  assign _112_ = _064_ & _111_;
  assign _113_ = _047_ & _112_;
  assign o_result[16] = _018_ | _113_;
  assign _114_ = _074_ & _112_;
  assign o_result[17] = _019_ | _114_;
  assign _115_ = _078_ & _112_;
  assign o_result[18] = _020_ | _115_;
  assign _116_ = _082_ & _112_;
  assign o_result[19] = _021_ | _116_;
  assign _117_ = _085_ & _112_;
  assign o_result[20] = _022_ | _117_;
  assign _118_ = _087_ & _112_;
  assign o_result[21] = _023_ | _118_;
  assign _119_ = _089_ & _112_;
  assign o_result[22] = _024_ | _119_;
  assign _120_ = _091_ & _112_;
  assign o_result[23] = _025_ | _120_;
  assign _121_ = _094_ & _112_;
  assign o_result[24] = _026_ | _121_;
  assign _122_ = _096_ & _112_;
  assign o_result[25] = _027_ | _122_;
  assign _123_ = _098_ & _112_;
  assign o_result[26] = _028_ | _123_;
  assign _124_ = _100_ & _112_;
  assign o_result[27] = _029_ | _124_;
  assign _125_ = _103_ & _112_;
  assign o_result[28] = _030_ | _125_;
  assign _126_ = _105_ & _112_;
  assign o_result[29] = _031_ | _126_;
  assign _127_ = _107_ & _112_;
  assign o_result[30] = _032_ | _127_;
  assign _128_ = _109_ & _112_;
  assign o_result[31] = _033_ | _128_;
  assign _129_ = _043_ & _064_;
  assign _130_ = ~_129_;
  assign o_error = _066_ | _130_;
endmodule

WORK/Verilog_modul_ustawienie/ustawienie.sv
//moduł ustawienia bitu w liczbie i_arg_A na 1, na indeksie wskazanym przez i_arg_B
module ustawienie (i_arg_A, i_arg_B, o_result, o_error);

//deklaracja parametrów
parameter BITS = 32;

//deklaracja wejść, wyjść i flag
    input logic signed [BITS-1:0] i_arg_A;
    input logic signed [BITS-1:0] i_arg_B;
    output logic signed [BITS-1:0] o_result;
    output logic o_error;
    logic [BITS-1:0] tymczasowy_rejestr;

    //blok opisujący logikę
    always_comb begin 

        //defaultowe ustawienie wartości wyjść i rejestru tymczasowego
        o_result = 'bx;
        o_error = 0;
        tymczasowy_rejestr = '0;

        //jak B jest ujemne, to ustawiamy flagę błędu
        if (i_arg_B[BITS-1] == 1) begin
            o_error = 1;
        end

        //jak B jest większe od 31, to ustawiamy flagę błędu
        else if (i_arg_B > BITS-1) begin
            o_error = 1;
        end

        //jak B wpada w zakres, to ustawiamy tego bita
        else if (((i_arg_B>='0) || (i_arg_B>={1'b1, '0})) && i_arg_B<BITS) begin
            tymczasowy_rejestr[i_arg_B] = 1;
            o_result = tymczasowy_rejestr|(~i_arg_A);
        end

    end

endmodule

WORK/Verilog_modul_ustawienie/ustawienie_tb.sv
// testbench modułu ustawienia bitu na 1 na bicie i_arg_A o indeksie i_arg_B
// zaczynamy ławeczkę testową
module ustawienie_tb;
    parameter BITS = 32;
    localparam TOP = 2**(BITS-1)-1;
    localparam BOTTOM = -(2**(BITS-1)-1);

    // sygnały wewnętrzne dla tej konketnej ławeczki testowej 
    logic [BITS-1:0] s_i_arg_A;
    logic [BITS-1:0] s_i_arg_B;
    logic            s_o_error_model;
    logic            s_o_error_synthesis;
    logic [BITS-1:0] s_o_model;
    logic [BITS-1:0] s_o_synthesis;
    integer i;

    // instancjowanie wejść i wyjść, jawne przypisywanie portów
    ustawienie #(.BITS(BITS))        
    ustawienie (
        .i_arg_A(s_i_arg_A), 
        .i_arg_B(s_i_arg_B), 
        .o_result(s_o_model), 
        .o_error(s_o_error_model)
        );    

    ustawienie_rtl           
    ustawienie_rtl (
        .i_arg_A(s_i_arg_A), 
        .i_arg_B(s_i_arg_B), 
        .o_result(s_o_synthesis), 
        .o_error(s_o_error_synthesis)
        );

    // Dostarczenie zmiennych do testu, rozpoczęcie bloku initial
    initial begin
        s_i_arg_A = '0;
        s_i_arg_B = '0;

        //w tym pliku zostaną zapisane zapisane sygnały zarejestrowane w symulacji
        $dumpfile("signals_ustawienie.vcd");  

        //Wskazania, że wszystkie sygnały z testbench i niżej mają być rejestrowane podczas symulacji
        $dumpvars(0, ustawienie_tb);       

        //najpierw testujemy przypadek idealny, na zerze najłatwiej zauważyć
        for (int i=0; i<6; i++) begin
            #1  
            s_i_arg_A = '1;
            s_i_arg_B = $urandom_range(1, BITS-1);
        end
        //teraz zobaczymy przypadki losowe dla liczb ujemnych 
        for (i=0; i<6; i++) begin
            #1  
            s_i_arg_B = $urandom_range(BOTTOM, -1);
        end

        //teraz zobaczymy przypadki losowe dla liczb >=32
        for (i=0; i<6; i++) begin
            #1  
            s_i_arg_B = $urandom_range(BITS, TOP);
        end

        //teraz zobaczymy przypadki losowe dla różnych reprezentacji 0, gdy B=0
        //zawartość A w każdym momencie tego modułu nie ma najmniejszego znaczenia
            #1  
            s_i_arg_B = '0;
            #1
            s_i_arg_B = {1'b1, '0};

        $finish;
    end
endmodule

WORK/Verilog_modul_ustawienie/signals_ustawienie.vcd
$date
	Tue Nov 28 00:29:40 2023
$end
$version
	Icarus Verilog
$end
$timescale
	1s
$end
$scope module ustawienie_tb $end
$var wire 32 ! s_o_synthesis [31:0] $end
$var wire 32 " s_o_model [31:0] $end
$var wire 1 # s_o_error_synthesis $end
$var wire 1 $ s_o_error_model $end
$var reg 32 % s_i_arg_A [31:0] $end
$var reg 32 & s_i_arg_B [31:0] $end
$var integer 32 ' i [31:0] $end
$scope module ustawienie $end
$var wire 32 ( i_arg_A [31:0] $end
$var wire 32 ) i_arg_B [31:0] $end
$var reg 1 $ o_error $end
$var reg 32 * o_result [31:0] $end
$var reg 32 + tymczasowy_rejestr [31:0] $end
$upscope $end
$scope module ustawienie_rtl $end
$var wire 1 , _000_ $end
$var wire 1 - _001_ $end
$var wire 1 . _002_ $end
$var wire 1 / _003_ $end
$var wire 1 0 _004_ $end
$var wire 1 1 _005_ $end
$var wire 1 2 _006_ $end
$var wire 1 3 _007_ $end
$var wire 1 4 _008_ $end
$var wire 1 5 _009_ $end
$var wire 1 6 _010_ $end
$var wire 1 7 _011_ $end
$var wire 1 8 _012_ $end
$var wire 1 9 _013_ $end
$var wire 1 : _014_ $end
$var wire 1 ; _015_ $end
$var wire 1 < _016_ $end
$var wire 1 = _017_ $end
$var wire 1 > _018_ $end
$var wire 1 ? _019_ $end
$var wire 1 @ _020_ $end
$var wire 1 A _021_ $end
$var wire 1 B _022_ $end
$var wire 1 C _023_ $end
$var wire 1 D _024_ $end
$var wire 1 E _025_ $end
$var wire 1 F _026_ $end
$var wire 1 G _027_ $end
$var wire 1 H _028_ $end
$var wire 1 I _029_ $end
$var wire 1 J _030_ $end
$var wire 1 K _031_ $end
$var wire 1 L _032_ $end
$var wire 1 M _033_ $end
$var wire 1 N _034_ $end
$var wire 1 O _035_ $end
$var wire 1 P _036_ $end
$var wire 1 Q _037_ $end
$var wire 1 R _038_ $end
$var wire 1 S _039_ $end
$var wire 1 T _040_ $end
$var wire 1 U _041_ $end
$var wire 1 V _042_ $end
$var wire 1 W _043_ $end
$var wire 1 X _044_ $end
$var wire 1 Y _045_ $end
$var wire 1 Z _046_ $end
$var wire 1 [ _047_ $end
$var wire 1 \ _048_ $end
$var wire 1 ] _049_ $end
$var wire 1 ^ _050_ $end
$var wire 1 _ _051_ $end
$var wire 1 ` _052_ $end
$var wire 1 a _053_ $end
$var wire 1 b _054_ $end
$var wire 1 c _055_ $end
$var wire 1 d _056_ $end
$var wire 1 e _057_ $end
$var wire 1 f _058_ $end
$var wire 1 g _059_ $end
$var wire 1 h _060_ $end
$var wire 1 i _061_ $end
$var wire 1 j _062_ $end
$var wire 1 k _063_ $end
$var wire 1 l _064_ $end
$var wire 1 m _065_ $end
$var wire 1 n _066_ $end
$var wire 1 o _067_ $end
$var wire 1 p _068_ $end
$var wire 1 q _069_ $end
$var wire 1 r _070_ $end
$var wire 1 s _071_ $end
$var wire 1 t _072_ $end
$var wire 1 u _073_ $end
$var wire 1 v _074_ $end
$var wire 1 w _075_ $end
$var wire 1 x _076_ $end
$var wire 1 y _077_ $end
$var wire 1 z _078_ $end
$var wire 1 { _079_ $end
$var wire 1 | _080_ $end
$var wire 1 } _081_ $end
$var wire 1 ~ _082_ $end
$var wire 1 !" _083_ $end
$var wire 1 "" _084_ $end
$var wire 1 #" _085_ $end
$var wire 1 $" _086_ $end
$var wire 1 %" _087_ $end
$var wire 1 &" _088_ $end
$var wire 1 '" _089_ $end
$var wire 1 (" _090_ $end
$var wire 1 )" _091_ $end
$var wire 1 *" _092_ $end
$var wire 1 +" _093_ $end
$var wire 1 ," _094_ $end
$var wire 1 -" _095_ $end
$var wire 1 ." _096_ $end
$var wire 1 /" _097_ $end
$var wire 1 0" _098_ $end
$var wire 1 1" _099_ $end
$var wire 1 2" _100_ $end
$var wire 1 3" _101_ $end
$var wire 1 4" _102_ $end
$var wire 1 5" _103_ $end
$var wire 1 6" _104_ $end
$var wire 1 7" _105_ $end
$var wire 1 8" _106_ $end
$var wire 1 9" _107_ $end
$var wire 1 :" _108_ $end
$var wire 1 ;" _109_ $end
$var wire 1 <" _110_ $end
$var wire 1 =" _111_ $end
$var wire 1 >" _112_ $end
$var wire 1 ?" _113_ $end
$var wire 1 @" _114_ $end
$var wire 1 A" _115_ $end
$var wire 1 B" _116_ $end
$var wire 1 C" _117_ $end
$var wire 1 D" _118_ $end
$var wire 1 E" _119_ $end
$var wire 1 F" _120_ $end
$var wire 1 G" _121_ $end
$var wire 1 H" _122_ $end
$var wire 1 I" _123_ $end
$var wire 1 J" _124_ $end
$var wire 1 K" _125_ $end
$var wire 1 L" _126_ $end
$var wire 1 M" _127_ $end
$var wire 1 N" _128_ $end
$var wire 1 O" _129_ $end
$var wire 1 P" _130_ $end
$var wire 1 Q" _131_ $end
$var wire 1 R" _132_ $end
$var wire 32 S" i_arg_A [31:0] $end
$var wire 32 T" i_arg_B [31:0] $end
$var wire 1 # o_error $end
$var wire 32 U" o_result [31:0] $end
$upscope $end
$scope begin $ivl_for_loop0 $end
$var integer 32 V" i [31:0] $end
$upscope $end
$upscope $end
$enddefinitions $end
#0
$dumpvars
b0 V"
b11111111111111111111111111111111 U"
b0 T"
b0 S"
1R"
1Q"
0P"
1O"
0N"
0M"
0L"
0K"
0J"
0I"
0H"
0G"
0F"
0E"
0D"
0C"
0B"
0A"
0@"
0?"
0>"
0="
0<"
0;"
0:"
09"
08"
07"
06"
05"
04"
03"
02"
01"
00"
0/"
0."
0-"
0,"
0+"
0*"
0)"
0("
0'"
0&"
0%"
0$"
0#"
0""
0!"
0~
0}
0|
0{
0z
0y
0x
0w
0v
0u
0t
1s
1r
1q
0p
1o
0n
0m
1l
1k
0j
0i
0h
0g
0f
0e
0d
1c
0b
0a
0`
0_
0^
0]
0\
1[
1Z
1Y
0X
1W
1V
0U
0T
0S
1R
0Q
0P
0O
1N
1M
1L
1K
1J
1I
1H
1G
1F
1E
1D
1C
1B
1A
1@
1?
1>
1=
1<
1;
1:
19
18
17
16
15
14
13
12
11
10
1/
1.
1-
1,
b1 +
b11111111111111111111111111111111 *
b0 )
b0 (
bx '
b0 &
b0 %
0$
0#
b11111111111111111111111111111111 "
b11111111111111111111111111111111 !
$end
#1
0[
0s
1A"
0Z
0r
1z
0?"
0Y
0q
1y
1>"
b1000000000000000000 !
b1000000000000000000 U"
0Q"
1X
1p
1x
1="
0.
0/
00
01
02
03
04
05
06
07
08
09
0:
0;
0<
0=
0>
0?
0@
0A
0B
0C
0D
0E
0F
0G
0H
0I
0J
0K
0L
0M
b1000000000000000000 +
b1000000000000000000 "
b1000000000000000000 *
b1 V"
b10010 &
b10010 )
b10010 T"
b11111111111111111111111111111111 %
b11111111111111111111111111111111 (
b11111111111111111111111111111111 S"
#2
1-"
1,"
b100000000 !
b100000000 U"
1Z
1r
0z
0A"
0N
1Y
1q
0y
00"
0>"
1Q"
0,
0X
0p
0x
1+"
0="
b100000000 +
b100000000 "
b100000000 *
b10 V"
b1000 &
b1000 )
b1000 T"
#3
1w
b10 !
b10 U"
0Z
1v
0-"
1N
0Y
1u
0,"
0R"
1,
1X
1t
0+"
b10 +
b10 "
b10 *
b11 V"
b1 &
b1 )
b1 T"
#4
0w
1*"
b10000000 !
b10000000 U"
0u
0v
1)"
0&"
0t
0N
1}
0%"
0Q"
0-
1|
1""
b10000000 +
b10000000 "
b10000000 *
b100 V"
b111 &
b111 )
b111 T"
#5
1@"
1v
b100000000000000000 !
b100000000000000000 U"
1u
0r
0*"
1t
1N
0q
0}
0)"
1>"
1Q"
1-
1p
0|
0""
1="
b100000000000000000 +
b100000000000000000 "
b100000000000000000 *
b101 V"
b10001 &
b10001 )
b10001 T"
#6
0@"
b10000000000000000000000000 !
b10000000000000000000000000 U"
0v
1H"
0N
1."
0,
1+"
b10000000000000000000000000 +
b10000000000000000000000000 "
b10000000000000000000000000 *
b0 '
b110 V"
b11001 &
b11001 )
b11001 T"
#7
1P"
0O"
0l
0>"
0@"
0W
0c
0k
0="
0B"
b0 !
b0 U"
0u
0v
0R
0V
1b
1j
0o
1#
0~
0H"
0t
1N
1Q
1U
1a
1f
1i
1n
0}
0."
0Q"
1,
1P
1S
1`
1d
1e
1g
1m
1|
0+"
1$
b0 +
bx "
bx *
b1 '
b10011001011000010100001000110011 &
b10011001011000010100001000110011 )
b10011001011000010100001000110011 T"
#8
1q
1o
0p
1x
0N
1^
0a
0n
1R"
0,
1O
1T
1\
1]
0`
0d
1h
0m
0|
1+"
1$
b10 '
b10000100100110111010100100001010 &
b10000100100110111010100100001010 )
b10000100100110111010100100001010 T"
#9
0q
0o
1p
1t
1N
1a
1n
1Q"
0R"
1,
0T
0]
1_
1d
0h
1m
0x
0+"
1$
b11 '
b11000000011110011111000110000001 &
b11000000011110011111000110000001 )
b11000000011110011111000110000001 T"
#10
0t
0N
0Q"
0-
1T
0\
1]
1`
1h
1|
1""
1$
b100 '
b11000011011010111110011010000111 &
b11000011011010111110011010000111 )
b11000011011010111110011010000111 T"
#11
1+"
0,
1-
0S
1\
0]
0d
0""
1$
b101 '
b11011101100100011111100010111011 &
b11011101100100011111100010111011 )
b11011101100100011111100010111011 T"
#12
1x
0+"
1R"
0-
1S
0\
1]
1d
0e
0|
14"
1$
b0 '
b11001111010001101110011010011110 &
b11001111010001101110011010011110 )
b11001111010001101110011010011110 T"
#13
0x
1""
0R"
1,
0P
1e
1|
04"
1$
b1 '
b1111011011010100010101111110111 &
b1111011011010100010101111110111 )
b1111011011010100010101111110111 T"
#14
1t
0""
0f
1Q"
0,
1P
1\
0d
0e
0g
0|
14"
1$
b10 '
b1100011000101101111101111001101 &
b1100011000101101111101111001101 )
b1100011000101101111101111001101 T"
#15
1f
0S
1d
1e
1g
1$
b11 '
b1111110011111101111010011111101 &
b1111110011111101111010011111101 )
b1111110011111101111010011111101 T"
#16
1x
1""
0Q"
1R"
1,
1S
0T
0d
0h
0t
04"
1$
b100 '
b110001100110111001001001110110 &
b110001100110111001001001110110 )
b110001100110111001001001110110 T"
#17
0O
1d
1$
b101 '
b110001011110111100001001110110 &
b110001011110111100001001110110 )
b110001011110111100001001110110 T"
#18
1+"
0,
1-
1O
1T
0]
0d
0g
1h
0""
1$
b110 '
b101010100010011110100101101010 &
b101010100010011110100101101010 )
b101010100010011110100101101010 T"
#19
b1 !
b1 U"
0#
1s
1[
0P"
1r
1Z
1O"
1l
1W
1c
1k
1q
1R
1V
0b
0j
1o
0p
1N
0Q
0U
1Y
0^
0a
0f
0i
0n
1Q"
1,
0O
0P
0S
0T
0X
0\
0_
0`
0e
0h
0m
0x
0+"
b1 "
b1 *
b1 +
0$
b0 &
b0 )
b0 T"
#20
0s
b100 !
b100 U"
0[
1{
0Z
1z
0Y
1y
0Q"
1X
1x
b100 +
b100 "
b100 *
b10 &
b10 )
b10 T"
